Workbook

Sheet 🏠 INICIO
B1: AMYSA · GESTIÓN DE VENTAS POR CATÁLOGO | F1: #VALUE!
B4: Yanbal • Esika • Cyzone • LBel • Natura • Avon • Farmasi • Oriflame
B6: ⚙️ CONFIGURA TU SISTEMA AQUÍ (solo toca estas 3 celdas)
B7: 👤 Tu nombre de consultora: | C7: MARIABEL | D7: ← escribe tu nombre aquí
B8: 💰 Tu % de comisión base: | C8: 0.1 | D8: Precio de comision que las vendedoras (en caso la tengas o tu misma si eres la que vende tambien) reciben
B9: 📅 Año de control: | C9: 2025 | D9: ← el año que estás registrando
G10: 25
B11: 📋 GUÍA DE HOJAS — ¿QUÉ HACE CADA UNA? | G11: 0.1
B12: 💰 PRECIOS BASE | C12: Tu menú permanente de productos: qué te cuesta, cuánto venderlo y tu margen. | G12: =G10*G11 -> 2.5
C13: 📌 CONFIGURA UNA VEZ. Solo cuando agregas un producto nuevo o cambia su precio.
B15: 📊 CALCULADORA CAMPAÑA | C15: Registra los productos vendidos en UNA campaña y calcula ganancia + comisión.
C16: ✅ ÚSALA CADA CAMPAÑA. Una campaña = una vez cada ~3 semanas.
B18: 💵 ¿CUÁNTO ME PAGO? | C18: Tu sueldo real: cuánto separar para pagarte, cubrir costos y reinvertir.
C19: 🎯 REVÍSALA CADA CAMPAÑA. Aquí sabes si tu negocio es rentable.
B21: 🗂️ MONITOREO CATÁLOGOS | C21: Resumen por catálogo: factura, ventas reales y ganancia neta por marca.
C22: 📈 ÚSALA CADA MES. Ingresa factura y ventas reales de cada catálogo.
B24: 📅 SEG - ENERO … DIC | C24: Registro detallado de cada venta: cliente, producto, pago y estado.
C25: 📝 ÚSALA DIARIO. Anota cada venta en el mes que corresponde.
B27: 📊 RESUMEN ANUAL | C27: Dashboard de todo el año: ventas, comisiones y gráficos mes a mes.
C28: 👀 SOLO LECTURA. Se calcula solo con los datos que vayas ingresando.
B30: 🧾 FACTURAS | C30: Control de facturas por catálogo: lo que debes pagar a cada empresa.
C31: 💳 ÚSALA AL CERRAR CAMPAÑA. Registra cuánto debes pagar a cada catálogo.
B34: 🎨 LEYENDA DE COLORES EN LAS TABLAS
B35: 🔵 CELDA AZUL sobre fondo amarillo | C35: Aquí TÚ ingresas datos (precio, nombre, cantidad, etc.)
B36: ⚫ CELDA AZUL sobre fondo azul claro | C36: Calculado automáticamente — NO lo edites
B37: 🟢 CELDA VERDE | C37: Tu ganancia o dinero que entra
B38: 🔴 CELDA ROJA | C38: Costo, gasto o dinero que sale

Sheet COSTO UNITARIO
B2: 🧮 CALCULADORA DE COSTO UNITARIO — ¿Cuánto me cuesta cada producto que vendo?
B3: Llena solo las celdas AMARILLAS 🟡 — las azules se calculan solas automáticamente ⚡
B5: 📦 PASO 1 — Costos Variables (lo que compras por lote) | G5: 🏢 PASO 2 — Costos Fijos (gastos del negocio cada mes)
B6: Material / Insumo | C6: Precio del lote (S/) | D6: Cantidad en el lote | E6: Costo por unidad (S/) | G6: Gasto Mensual | H6: Costo S/ | J6: Costo por pedido (S/)
B7: Bolsas | C7: 180 | D7: 1000 | E7: =IF(AND(C7<>"",D7<>"",D7<>0),C7/D7,"") -> 0.18 | G7: Luz | H7: 25 | J7: =H7 -> 25
B8: Caja provincia | C8: 120 | D8: 100 | E8: =IF(AND(C8<>"",D8<>"",D8<>0),C8/D8,"") -> 1.2 | G8: Internet | H8: 25 | J8: =H8 -> 25
B9: Cinta adhesiva | C9: 5 | D9: 50 | E9: =IF(AND(C9<>"",D9<>"",D9<>0),C9/D9,"") -> 0.1 | G9: Publicidad / redes | H9: 100 | J9: =H9 -> 100
B10: Film stretch | C10: 18 | D10: 100 | E10: =IF(AND(C10<>"",D10<>"",D10<>0),C10/D10,"") -> 0.18 | G10: Celular (depreciación) | H10: 52.78 | J10: =H10 -> 52.78
B11: Tarjetas agradecimiento | C11: 35 | D11: 1000 | E11: =IF(AND(C11<>"",D11<>"",D11<>0),C11/D11,"") -> 0.035 | G11: Marketing | H11: 100 | J11: =H11 -> 100
B12: Papel de seda | C12: 2 | D12: 12 | E12: =IF(AND(C12<>"",D12<>"",D12<>0),C12/D12,"") -> 0.16666667 | G12: Sueldo de gerente | H12: 200 | J12: =H12 -> 200
E13: =IF(AND(C13<>"",D13<>"",D13<>0),C13/D13,"") | G13: Sueldo logística | H13: 50 | J13: =H13 -> 50
E14: =IF(AND(C14<>"",D14<>"",D14<>0),C14/D14,"") | G14: Contador | H14: 30 | J14: =H14 -> 30
E15: =IF(AND(C15<>"",D15<>"",D15<>0),C15/D15,"") | G15: Tijera | H15: 2 | I15: 200 | J15: =IF(AND(H15<>"",I15<>"",I15<>0),H15/I15,"") -> 0.01
E16: =IF(AND(C16<>"",D16<>"",D16<>0),C16/D16,"") | G16: Lapicero | H16: 2 | I16: 100 | J16: =IF(AND(H16<>"",I16<>"",I16<>0),H16/I16,"") -> 0.02
B18: 📦 TOTAL costo variable por unidad | E18: =SUM(E7:E16) -> 1.8616667 | G18: 🏢 TOTAL costo fijo por pedido | J18: =SUM(J7:J16) -> 582.81
B21: 📦 PASO 3 — ¿Cuántos pedidos haces al mes? (para repartir los gastos fijos entre cada venta)
B22: 🔢 Número de pedidos al mes: | C22: 300 | D22: ← Escribe aquí cuántos pedidos vendes en un mes normal
B25: ✅ RESULTADO — Tu Costo Unitario Total por producto
B26: 🧮 COSTO UNITARIO = costo variable + (costo fijo ÷ pedidos al mes) | E26: =(E18+J18)/C22 -> 1.9489056
B29: 💡 EJEMPLO EXPLICADO — ¿Cómo funciona este cálculo?
B30: Bolsas: compraste 1,000 por S/312 | E30: → cada bolsa te cuesta | G30: S/ 0.31
B31: Caja provincia: 100 por S/120 | E31: → cada caja te cuesta | G31: S/ 1.20
B32: Cinta: 50 por S/5 | E32: → cada rollo te cuesta | G32: S/ 0.10
B33: TOTAL costo variable por unidad: | G33: S/ 2.00
B34: Gastos fijos del mes: S/582 | E34: ÷ 300 pedidos al mes | G34: S/ 1.94 por pedido
B35: ► COSTO UNITARIO TOTAL: | E35: S/ 2.00 + S/ 1.94 | G35: 3.94
B38: 🔗 CONEXIÓN AUTOMÁTICA — Este valor pasa directo a la hoja INVENTARIO EN STOCK
B39: ✅ En la hoja INVENTARIO EN STOCK, la columna "📦 costo unitario" ya usa este resultado automáticamente.
B40: ➡ Si cambias cualquier costo aquí, la ganancia y el precio de venta se actualizan solos en toda la planilla.
B43: ⭐ TIPS PARA EMPRENDEDORAS
B44: 🟡 Celdas AMARILLAS → Son las que TÚ llenas. Cambia los valores según tus gastos reales.
B45: 🔵 Celdas AZULES / ROJAS → Se calculan solas. ¡No las toques!
B46: 📦 Costos Variables = materiales que usas para cada pedido (bolsas, cajas, cinta, etc.)
B47: 🏢 Costos Fijos = gastos del negocio que pagas siempre (luz, internet, sueldo, etc.) — se dividen entre todos tus pedidos.
B48: 📊 Pedidos al mes = ¿cuántos paquetes/ventas haces en un mes? Pon un número promedio.
B49: 💡 Actualiza esta hoja cuando cambien tus precios de insumos o tus gastos mensuales.
B51: =#VALUE! -> #VALUE!

Sheet INVENTARIO EN STOCK
B1: 💰 PRECIOS BASE — Tu Menú Permanente de Productos
B2: 📌 Configura aquí tus productos UNA VEZ. NO la uses para registrar ventas — para eso usa 📊 CALCULADORA CAMPAÑA
B3: ⚙️ COMISIÓN GLOBAL (se toma de INICIO): | C3: ='🏠 INICIO'!C8 -> 0.1 | E3: ← Cámbialo en hoja INICIO
B4: 🔵 Tú ingresas | E4: ⚫ Calculado auto | H4: 🟡 % comisión editable | L4: 🟢 Ganancia real
B5: # | C5: CATÁLOGO | D5: PRODUCTO | E5: 💰 COSTO (lo que pagas) | F5: 📦 Costo unitario (desde hoja COSTO UNITARIO 🔗) | G5: 📥 INVERSIÓN (costo+empaque) | H5: 📈 % MARGEN utilidad (30%) | I5: 🏷️ PRECIO VENTA (calculado) | J5: 💸 COSTO TOTAL | L5: 💵 MARGEN S/ (ganancia bruta) | M5: 🏆 COMISIÓN ventas % | N5: 💎 COMISIÓN S/ | O5: ✅ GANANCIA NETA
B6: 1 | C6: NATURA | D6: Crema tododia ciruela y flor de vainila | E6: 21 | F6: ='COSTO UNITARIO'!#REF! -> #REF! | G6: =E6+F6 -> #REF! | H6: 0.2 | I6: =IF(G6<>"",G6/(1-H6)/(1-M6),"") -> #REF! | J6: =IF(G6<>"",G6,"") -> #REF! | L6: =IF(I6<>"",(G6/(1-H6))-G6,"") -> #REF! | M6: 0.1 | N6: =IF(I6<>"",I6-(G6/(1-H6)),"") -> #REF! | O6: =IF(I6<>"",L6,"") -> #REF!
B7: 2 | C7: CYZONE | D7: Mini Chic Colonia | E7: 15 | F7: ='COSTO UNITARIO'!#REF! -> #REF! | G7: =E7+F7 -> #REF! | H7: 0.2 | I7: =IF(G7<>"",G7/(1-H7)/(1-M7),"") -> #REF! | J7: =IF(G7<>"",G7,"") -> #REF! | L7: =IF(I7<>"",(G7/(1-H7))-G7,"") -> #REF! | M7: 0.1 | N7: =IF(I7<>"",I7-(G7/(1-H7)),"") -> #REF! | O7: =IF(I7<>"",L7,"") -> #REF!
B8: 3 | C8: ESIKA | D8: Expression Magic | F8: ='COSTO UNITARIO'!#REF! -> #REF! | G8: =E8+F8 -> #REF! | H8: 0.2 | I8: =IF(G8<>"",G8/(1-H8)/(1-M8),"") -> #REF! | J8: =IF(G8<>"",G8,"") -> #REF! | L8: =IF(I8<>"",(G8/(1-H8))-G8,"") -> #REF! | M8: ='🏠 INICIO'!C8 -> 0.1 | N8: =IF(I8<>"",I8-(G8/(1-H8)),"") -> #REF! | O8: =IF(I8<>"",L8,"") -> #REF!
B9: 4 | C9: NATURA | D9: Perfume Tododia Floral | F9: ='COSTO UNITARIO'!#REF! -> #REF! | G9: =E9+F9 -> #REF! | H9: 0.25 | I9: =IF(G9<>"",G9/(1-H9)/(1-M9),"") -> #REF! | J9: =IF(G9<>"",G9,"") -> #REF! | L9: =IF(I9<>"",(G9/(1-H9))-G9,"") -> #REF! | M9: ='🏠 INICIO'!C8 -> 0.1 | N9: =IF(I9<>"",I9-(G9/(1-H9)),"") -> #REF! | O9: =IF(I9<>"",L9,"") -> #REF!
B10: 5 | C10: AVON | D10: Anew Gold Crema | F10: ='COSTO UNITARIO'!#REF! -> #REF! | G10: =E10+F10 -> #REF! | H10: 0.3 | I10: =IF(G10<>"",G10/(1-H10)/(1-M10),"") -> #REF! | J10: =IF(G10<>"",G10,"") -> #REF! | L10: =IF(I10<>"",(G10/(1-H10))-G10,"") -> #REF! | M10: ='🏠 INICIO'!C8 -> 0.1 | N10: =IF(I10<>"",I10-(G10/(1-H10)),"") -> #REF! | O10: =IF(I10<>"",L10,"") -> #REF!
B11: 6 | C11: ORIFLAME | F11: ='COSTO UNITARIO'!#REF! -> #REF! | G11: =E11+F11 -> #REF! | H11: 0.3 | I11: =IF(G11<>"",G11/(1-H11)/(1-M11),"") -> #REF! | J11: =IF(G11<>"",G11,"") -> #REF! | L11: =IF(I11<>"",(G11/(1-H11))-G11,"") -> #REF! | M11: ='🏠 INICIO'!C8 -> 0.1 | N11: =IF(I11<>"",I11-(G11/(1-H11)),"") -> #REF! | O11: =IF(I11<>"",L11,"") -> #REF!
B12: 7 | C12: FARMASI | F12: ='COSTO UNITARIO'!#REF! -> #REF! | G12: =E12+F12 -> #REF! | H12: 0.3 | I12: =IF(G12<>"",G12/(1-H12)/(1-M12),"") -> #REF! | J12: =IF(G12<>"",G12,"") -> #REF! | L12: =IF(I12<>"",(G12/(1-H12))-G12,"") -> #REF! | M12: ='🏠 INICIO'!C8 -> 0.1 | N12: =IF(I12<>"",I12-(G12/(1-H12)),"") -> #REF! | O12: =IF(I12<>"",L12,"") -> #REF!
B13: 8 | C13: YANBAL | F13: ='COSTO UNITARIO'!#REF! -> #REF! | G13: =E13+F13 -> #REF! | H13: 0.35 | I13: =IF(G13<>"",G13/(1-H13)/(1-M13),"") -> #REF! | J13: =IF(G13<>"",G13,"") -> #REF! | L13: =IF(I13<>"",(G13/(1-H13))-G13,"") -> #REF! | M13: ='🏠 INICIO'!C8 -> 0.1 | N13: =IF(I13<>"",I13-(G13/(1-H13)),"") -> #REF! | O13: =IF(I13<>"",L13,"") -> #REF!
B14: 9 | C14: YANBAL | F14: ='COSTO UNITARIO'!#REF! -> #REF! | G14: =E14+F14 -> #REF! | H14: 0.35 | I14: =IF(G14<>"",G14/(1-H14)/(1-M14),"") -> #REF! | J14: =IF(G14<>"",G14,"") -> #REF! | L14: =IF(I14<>"",(G14/(1-H14))-G14,"") -> #REF! | M14: ='🏠 INICIO'!C8 -> 0.1 | N14: =IF(I14<>"",I14-(G14/(1-H14)),"") -> #REF! | O14: =IF(I14<>"",L14,"") -> #REF!
B15: 10 | C15: ESIKA | F15: ='COSTO UNITARIO'!#REF! -> #REF! | G15: =E15+F15 -> #REF! | H15: 0.35 | I15: =IF(G15<>"",G15/(1-H15)/(1-M15),"") -> #REF! | J15: =IF(G15<>"",G15,"") -> #REF! | L15: =IF(I15<>"",(G15/(1-H15))-G15,"") -> #REF! | M15: ='🏠 INICIO'!C8 -> 0.1 | N15: =IF(I15<>"",I15-(G15/(1-H15)),"") -> #REF! | O15: =IF(I15<>"",L15,"") -> #REF!
B16: 11 | C16: CYZONE | F16: ='COSTO UNITARIO'!#REF! -> #REF! | G16: =E16+F16 -> #REF! | H16: 0.35 | I16: =IF(G16<>"",G16/(1-H16)/(1-M16),"") -> #REF! | J16: =IF(G16<>"",G16,"") -> #REF! | L16: =IF(I16<>"",(G16/(1-H16))-G16,"") -> #REF! | M16: ='🏠 INICIO'!C8 -> 0.1 | N16: =IF(I16<>"",I16-(G16/(1-H16)),"") -> #REF! | O16: =IF(I16<>"",L16,"") -> #REF!
B17: 12 | C17: NATURA | F17: ='COSTO UNITARIO'!#REF! -> #REF! | G17: =E17+F17 -> #REF! | H17: 0.35 | I17: =IF(G17<>"",G17/(1-H17)/(1-M17),"") -> #REF! | J17: =IF(G17<>"",G17,"") -> #REF! | L17: =IF(I17<>"",(G17/(1-H17))-G17,"") -> #REF! | M17: ='🏠 INICIO'!C8 -> 0.1 | N17: =IF(I17<>"",I17-(G17/(1-H17)),"") -> #REF! | O17: =IF(I17<>"",L17,"") -> #REF!
B18: 13 | C18: AVON | F18: ='COSTO UNITARIO'!#REF! -> #REF! | G18: =E18+F18 -> #REF! | H18: 0.3 | I18: =IF(G18<>"",G18/(1-H18)/(1-M18),"") -> #REF! | J18: =IF(G18<>"",G18,"") -> #REF! | L18: =IF(I18<>"",(G18/(1-H18))-G18,"") -> #REF! | M18: ='🏠 INICIO'!C8 -> 0.1 | N18: =IF(I18<>"",I18-(G18/(1-H18)),"") -> #REF! | O18: =IF(I18<>"",L18,"") -> #REF!
B19: 14 | C19: FARMASI | F19: ='COSTO UNITARIO'!#REF! -> #REF! | G19: =E19+F19 -> #REF! | H19: 0.3 | I19: =IF(G19<>"",G19/(1-H19)/(1-M19),"") -> #REF! | J19: =IF(G19<>"",G19,"") -> #REF! | L19: =IF(I19<>"",(G19/(1-H19))-G19,"") -> #REF! | M19: ='🏠 INICIO'!C8 -> 0.1 | N19: =IF(I19<>"",I19-(G19/(1-H19)),"") -> #REF! | O19: =IF(I19<>"",L19,"") -> #REF!
B20: 15 | C20: LBEL | F20: ='COSTO UNITARIO'!#REF! -> #REF! | G20: =E20+F20 -> #REF! | H20: 0.35 | I20: =IF(G20<>"",G20/(1-H20)/(1-M20),"") -> #REF! | J20: =IF(G20<>"",G20,"") -> #REF! | L20: =IF(I20<>"",(G20/(1-H20))-G20,"") -> #REF! | M20: ='🏠 INICIO'!C8 -> 0.1 | N20: =IF(I20<>"",I20-(G20/(1-H20)),"") -> #REF! | O20: =IF(I20<>"",L20,"") -> #REF!
B21: 16 | C21: LBEL | F21: ='COSTO UNITARIO'!#REF! -> #REF! | G21: =E21+F21 -> #REF! | H21: 0.35 | I21: =IF(G21<>"",G21/(1-H21)/(1-M21),"") -> #REF! | J21: =IF(G21<>"",G21,"") -> #REF! | L21: =IF(I21<>"",(G21/(1-H21))-G21,"") -> #REF! | M21: ='🏠 INICIO'!C8 -> 0.1 | N21: =IF(I21<>"",I21-(G21/(1-H21)),"") -> #REF! | O21: =IF(I21<>"",L21,"") -> #REF!
B22: 17 | C22: ORIFLAME | F22: ='COSTO UNITARIO'!#REF! -> #REF! | G22: =E22+F22 -> #REF! | H22: 0.3 | I22: =IF(G22<>"",G22/(1-H22)/(1-M22),"") -> #REF! | J22: =IF(G22<>"",G22,"") -> #REF! | L22: =IF(I22<>"",(G22/(1-H22))-G22,"") -> #REF! | M22: ='🏠 INICIO'!C8 -> 0.1 | N22: =IF(I22<>"",I22-(G22/(1-H22)),"") -> #REF! | O22: =IF(I22<>"",L22,"") -> #REF!
B23: 18 | C23: YANBAL | F23: ='COSTO UNITARIO'!#REF! -> #REF! | G23: =E23+F23 -> #REF! | H23: 0.36 | I23: =IF(G23<>"",G23/(1-H23)/(1-M23),"") -> #REF! | J23: =IF(G23<>"",G23,"") -> #REF! | L23: =IF(I23<>"",(G23/(1-H23))-G23,"") -> #REF! | M23: ='🏠 INICIO'!C8 -> 0.1 | N23: =IF(I23<>"",I23-(G23/(1-H23)),"") -> #REF! | O23: =IF(I23<>"",L23,"") -> #REF!
B24: 19 | C24: CYZONE | F24: ='COSTO UNITARIO'!#REF! -> #REF! | G24: =E24+F24 -> #REF! | H24: 0.35 | I24: =IF(G24<>"",G24/(1-H24)/(1-M24),"") -> #REF! | J24: =IF(G24<>"",G24,"") -> #REF! | L24: =IF(I24<>"",(G24/(1-H24))-G24,"") -> #REF! | M24: ='🏠 INICIO'!C8 -> 0.1 | N24: =IF(I24<>"",I24-(G24/(1-H24)),"") -> #REF! | O24: =IF(I24<>"",L24,"") -> #REF!
B25: 20 | C25: ESIKA | F25: ='COSTO UNITARIO'!#REF! -> #REF! | G25: =E25+F25 -> #REF! | H25: 0.35 | I25: =IF(G25<>"",G25/(1-H25)/(1-M25),"") -> #REF! | J25: =IF(G25<>"",G25,"") -> #REF! | L25: =IF(I25<>"",(G25/(1-H25))-G25,"") -> #REF! | M25: ='🏠 INICIO'!C8 -> 0.1 | N25: =IF(I25<>"",I25-(G25/(1-H25)),"") -> #REF! | O25: =IF(I25<>"",L25,"") -> #REF!
B26: 21 | F26: ='COSTO UNITARIO'!#REF! -> #REF! | G26: =IF(E26<>"",E26+F26,"") | I26: =IF(G26<>"",G26/(1-H26)/(1-M26),"") | J26: =IF(G26<>"",G26,"") | L26: =IF(I26<>"",(G26/(1-H26))-G26,"") | M26: ='🏠 INICIO'!C8 -> 0.1 | N26: =IF(I26<>"",I26-(G26/(1-H26)),"") | O26: =IF(I26<>"",L26,"")
B27: 22 | F27: ='COSTO UNITARIO'!#REF! -> #REF! | G27: =IF(E27<>"",E27+F27,"") | I27: =IF(G27<>"",G27/(1-H27)/(1-M27),"") | J27: =IF(G27<>"",G27,"") | L27: =IF(I27<>"",(G27/(1-H27))-G27,"") | M27: ='🏠 INICIO'!C8 -> 0.1 | N27: =IF(I27<>"",I27-(G27/(1-H27)),"") | O27: =IF(I27<>"",L27,"")
B28: 23 | F28: ='COSTO UNITARIO'!#REF! -> #REF! | G28: =IF(E28<>"",E28+F28,"") | I28: =IF(G28<>"",G28/(1-H28)/(1-M28),"") | J28: =IF(G28<>"",G28,"") | L28: =IF(I28<>"",(G28/(1-H28))-G28,"") | M28: ='🏠 INICIO'!C8 -> 0.1 | N28: =IF(I28<>"",I28-(G28/(1-H28)),"") | O28: =IF(I28<>"",L28,"")
B29: 24 | F29: ='COSTO UNITARIO'!#REF! -> #REF! | G29: =IF(E29<>"",E29+F29,"") | I29: =IF(G29<>"",G29/(1-H29)/(1-M29),"") | J29: =IF(G29<>"",G29,"") | L29: =IF(I29<>"",(G29/(1-H29))-G29,"") | M29: ='🏠 INICIO'!C8 -> 0.1 | N29: =IF(I29<>"",I29-(G29/(1-H29)),"") | O29: =IF(I29<>"",L29,"")
B30: 25 | F30: ='COSTO UNITARIO'!#REF! -> #REF! | G30: =IF(E30<>"",E30+F30,"") | I30: =IF(G30<>"",G30/(1-H30)/(1-M30),"") | J30: =IF(G30<>"",G30,"") | L30: =IF(I30<>"",(G30/(1-H30))-G30,"") | M30: ='🏠 INICIO'!C8 -> 0.1 | N30: =IF(I30<>"",I30-(G30/(1-H30)),"") | O30: =IF(I30<>"",L30,"")
B31: 26 | F31: ='COSTO UNITARIO'!#REF! -> #REF! | G31: =IF(E31<>"",E31+F31,"") | I31: =IF(G31<>"",G31/(1-H31)/(1-M31),"") | J31: =IF(G31<>"",G31,"") | L31: =IF(I31<>"",(G31/(1-H31))-G31,"") | M31: ='🏠 INICIO'!C8 -> 0.1 | N31: =IF(I31<>"",I31-(G31/(1-H31)),"") | O31: =IF(I31<>"",L31,"")
B32: 27 | F32: ='COSTO UNITARIO'!#REF! -> #REF! | G32: =IF(E32<>"",E32+F32,"") | I32: =IF(G32<>"",G32/(1-H32)/(1-M32),"") | J32: =IF(G32<>"",G32,"") | L32: =IF(I32<>"",(G32/(1-H32))-G32,"") | M32: ='🏠 INICIO'!C8 -> 0.1 | N32: =IF(I32<>"",I32-(G32/(1-H32)),"") | O32: =IF(I32<>"",L32,"")
B33: 28 | F33: ='COSTO UNITARIO'!#REF! -> #REF! | G33: =IF(E33<>"",E33+F33,"") | I33: =IF(G33<>"",G33/(1-H33)/(1-M33),"") | J33: =IF(G33<>"",G33,"") | L33: =IF(I33<>"",(G33/(1-H33))-G33,"") | M33: ='🏠 INICIO'!C8 -> 0.1 | N33: =IF(I33<>"",I33-(G33/(1-H33)),"") | O33: =IF(I33<>"",L33,"")
B34: 29 | F34: ='COSTO UNITARIO'!#REF! -> #REF! | G34: =IF(E34<>"",E34+F34,"") | I34: =IF(G34<>"",G34/(1-H34)/(1-M34),"") | J34: =IF(G34<>"",G34,"") | L34: =IF(I34<>"",(G34/(1-H34))-G34,"") | M34: ='🏠 INICIO'!C8 -> 0.1 | N34: =IF(I34<>"",I34-(G34/(1-H34)),"") | O34: =IF(I34<>"",L34,"")
B35: 30 | F35: ='COSTO UNITARIO'!#REF! -> #REF! | G35: =IF(E35<>"",E35+F35,"") | I35: =IF(G35<>"",G35/(1-H35)/(1-M35),"") | J35: =IF(G35<>"",G35,"") | L35: =IF(I35<>"",(G35/(1-H35))-G35,"") | M35: ='🏠 INICIO'!C8 -> 0.1 | N35: =IF(I35<>"",I35-(G35/(1-H35)),"") | O35: =IF(I35<>"",L35,"")
B36: 31 | F36: ='COSTO UNITARIO'!#REF! -> #REF! | G36: =IF(E36<>"",E36+F36,"") | I36: =IF(G36<>"",G36/(1-H36)/(1-M36),"") | J36: =IF(G36<>"",G36,"") | L36: =IF(I36<>"",(G36/(1-H36))-G36,"") | M36: ='🏠 INICIO'!C8 -> 0.1 | N36: =IF(I36<>"",I36-(G36/(1-H36)),"") | O36: =IF(I36<>"",L36,"")
B37: 32 | F37: ='COSTO UNITARIO'!#REF! -> #REF! | G37: =IF(E37<>"",E37+F37,"") | I37: =IF(G37<>"",G37/(1-H37)/(1-M37),"") | J37: =IF(G37<>"",G37,"") | L37: =IF(I37<>"",(G37/(1-H37))-G37,"") | M37: ='🏠 INICIO'!C8 -> 0.1 | N37: =IF(I37<>"",I37-(G37/(1-H37)),"") | O37: =IF(I37<>"",L37,"")
B38: 33 | F38: ='COSTO UNITARIO'!#REF! -> #REF! | G38: =IF(E38<>"",E38+F38,"") | I38: =IF(G38<>"",G38/(1-H38)/(1-M38),"") | J38: =IF(G38<>"",G38,"") | L38: =IF(I38<>"",(G38/(1-H38))-G38,"") | M38: ='🏠 INICIO'!C8 -> 0.1 | N38: =IF(I38<>"",I38-(G38/(1-H38)),"") | O38: =IF(I38<>"",L38,"")
B39: 34 | F39: ='COSTO UNITARIO'!#REF! -> #REF! | G39: =IF(E39<>"",E39+F39,"") | I39: =IF(G39<>"",G39/(1-H39)/(1-M39),"") | J39: =IF(G39<>"",G39,"") | L39: =IF(I39<>"",(G39/(1-H39))-G39,"") | M39: ='🏠 INICIO'!C8 -> 0.1 | N39: =IF(I39<>"",I39-(G39/(1-H39)),"") | O39: =IF(I39<>"",L39,"")
B40: 35 | F40: ='COSTO UNITARIO'!#REF! -> #REF! | G40: =IF(E40<>"",E40+F40,"") | I40: =IF(G40<>"",G40/(1-H40)/(1-M40),"") | J40: =IF(G40<>"",G40,"") | L40: =IF(I40<>"",(G40/(1-H40))-G40,"") | M40: ='🏠 INICIO'!C8 -> 0.1 | N40: =IF(I40<>"",I40-(G40/(1-H40)),"") | O40: =IF(I40<>"",L40,"")
B41: 36 | F41: ='COSTO UNITARIO'!#REF! -> #REF! | G41: =IF(E41<>"",E41+F41,"") | I41: =IF(G41<>"",G41/(1-H41)/(1-M41),"") | J41: =IF(G41<>"",G41,"") | L41: =IF(I41<>"",(G41/(1-H41))-G41,"") | M41: ='🏠 INICIO'!C8 -> 0.1 | N41: =IF(I41<>"",I41-(G41/(1-H41)),"") | O41: =IF(I41<>"",L41,"")
B42: 37 | F42: ='COSTO UNITARIO'!#REF! -> #REF! | G42: =IF(E42<>"",E42+F42,"") | I42: =IF(G42<>"",G42/(1-H42)/(1-M42),"") | J42: =IF(G42<>"",G42,"") | L42: =IF(I42<>"",(G42/(1-H42))-G42,"") | M42: ='🏠 INICIO'!C8 -> 0.1 | N42: =IF(I42<>"",I42-(G42/(1-H42)),"") | O42: =IF(I42<>"",L42,"")
B43: 38 | F43: ='COSTO UNITARIO'!#REF! -> #REF! | G43: =IF(E43<>"",E43+F43,"") | I43: =IF(G43<>"",G43/(1-H43)/(1-M43),"") | J43: =IF(G43<>"",G43,"") | L43: =IF(I43<>"",(G43/(1-H43))-G43,"") | M43: ='🏠 INICIO'!C8 -> 0.1 | N43: =IF(I43<>"",I43-(G43/(1-H43)),"") | O43: =IF(I43<>"",L43,"")
B44: 39 | F44: ='COSTO UNITARIO'!#REF! -> #REF! | G44: =IF(E44<>"",E44+F44,"") | I44: =IF(G44<>"",G44/(1-H44)/(1-M44),"") | J44: =IF(G44<>"",G44,"") | L44: =IF(I44<>"",(G44/(1-H44))-G44,"") | M44: ='🏠 INICIO'!C8 -> 0.1 | N44: =IF(I44<>"",I44-(G44/(1-H44)),"") | O44: =IF(I44<>"",L44,"")
B45: 40 | F45: ='COSTO UNITARIO'!#REF! -> #REF! | G45: =IF(E45<>"",E45+F45,"") | I45: =IF(G45<>"",G45/(1-H45)/(1-M45),"") | J45: =IF(G45<>"",G45,"") | L45: =IF(I45<>"",(G45/(1-H45))-G45,"") | M45: ='🏠 INICIO'!C8 -> 0.1 | N45: =IF(I45<>"",I45-(G45/(1-H45)),"") | O45: =IF(I45<>"",L45,"")
B46: 41 | F46: ='COSTO UNITARIO'!#REF! -> #REF! | G46: =IF(E46<>"",E46+F46,"") | I46: =IF(G46<>"",G46/(1-H46)/(1-M46),"") | J46: =IF(G46<>"",G46,"") | L46: =IF(I46<>"",(G46/(1-H46))-G46,"") | M46: ='🏠 INICIO'!C8 -> 0.1 | N46: =IF(I46<>"",I46-(G46/(1-H46)),"") | O46: =IF(I46<>"",L46,"")
B47: 42 | F47: ='COSTO UNITARIO'!#REF! -> #REF! | G47: =IF(E47<>"",E47+F47,"") | I47: =IF(G47<>"",G47/(1-H47)/(1-M47),"") | J47: =IF(G47<>"",G47,"") | L47: =IF(I47<>"",(G47/(1-H47))-G47,"") | M47: ='🏠 INICIO'!C8 -> 0.1 | N47: =IF(I47<>"",I47-(G47/(1-H47)),"") | O47: =IF(I47<>"",L47,"")
B48: 43 | F48: ='COSTO UNITARIO'!#REF! -> #REF! | G48: =IF(E48<>"",E48+F48,"") | I48: =IF(G48<>"",G48/(1-H48)/(1-M48),"") | J48: =IF(G48<>"",G48,"") | L48: =IF(I48<>"",(G48/(1-H48))-G48,"") | M48: ='🏠 INICIO'!C8 -> 0.1 | N48: =IF(I48<>"",I48-(G48/(1-H48)),"") | O48: =IF(I48<>"",L48,"")
B49: 44 | F49: ='COSTO UNITARIO'!#REF! -> #REF! | G49: =IF(E49<>"",E49+F49,"") | I49: =IF(G49<>"",G49/(1-H49)/(1-M49),"") | J49: =IF(G49<>"",G49,"") | L49: =IF(I49<>"",(G49/(1-H49))-G49,"") | M49: ='🏠 INICIO'!C8 -> 0.1 | N49: =IF(I49<>"",I49-(G49/(1-H49)),"") | O49: =IF(I49<>"",L49,"")
B50: 45 | F50: ='COSTO UNITARIO'!#REF! -> #REF! | G50: =IF(E50<>"",E50+F50,"") | I50: =IF(G50<>"",G50/(1-H50)/(1-M50),"") | J50: =IF(G50<>"",G50,"") | L50: =IF(I50<>"",(G50/(1-H50))-G50,"") | M50: ='🏠 INICIO'!C8 -> 0.1 | N50: =IF(I50<>"",I50-(G50/(1-H50)),"") | O50: =IF(I50<>"",L50,"")
B51: 46 | F51: ='COSTO UNITARIO'!#REF! -> #REF! | G51: =IF(E51<>"",E51+F51,"") | I51: =IF(G51<>"",G51/(1-H51)/(1-M51),"") | J51: =IF(G51<>"",G51,"") | L51: =IF(I51<>"",(G51/(1-H51))-G51,"") | M51: ='🏠 INICIO'!C8 -> 0.1 | N51: =IF(I51<>"",I51-(G51/(1-H51)),"") | O51: =IF(I51<>"",L51,"")
B52: 47 | F52: ='COSTO UNITARIO'!#REF! -> #REF! | G52: =IF(E52<>"",E52+F52,"") | I52: =IF(G52<>"",G52/(1-H52)/(1-M52),"") | J52: =IF(G52<>"",G52,"") | L52: =IF(I52<>"",(G52/(1-H52))-G52,"") | M52: ='🏠 INICIO'!C8 -> 0.1 | N52: =IF(I52<>"",I52-(G52/(1-H52)),"") | O52: =IF(I52<>"",L52,"")
B53: 48 | F53: ='COSTO UNITARIO'!#REF! -> #REF! | G53: =IF(E53<>"",E53+F53,"") | I53: =IF(G53<>"",G53/(1-H53)/(1-M53),"") | J53: =IF(G53<>"",G53,"") | L53: =IF(I53<>"",(G53/(1-H53))-G53,"") | M53: ='🏠 INICIO'!C8 -> 0.1 | N53: =IF(I53<>"",I53-(G53/(1-H53)),"") | O53: =IF(I53<>"",L53,"")
B54: 49 | F54: ='COSTO UNITARIO'!#REF! -> #REF! | G54: =IF(E54<>"",E54+F54,"") | I54: =IF(G54<>"",G54/(1-H54)/(1-M54),"") | J54: =IF(G54<>"",G54,"") | L54: =IF(I54<>"",(G54/(1-H54))-G54,"") | M54: ='🏠 INICIO'!C8 -> 0.1 | N54: =IF(I54<>"",I54-(G54/(1-H54)),"") | O54: =IF(I54<>"",L54,"")
B55: 50 | F55: ='COSTO UNITARIO'!#REF! -> #REF! | G55: =IF(E55<>"",E55+F55,"") | I55: =IF(G55<>"",G55/(1-H55)/(1-M55),"") | J55: =IF(G55<>"",G55,"") | L55: =IF(I55<>"",(G55/(1-H55))-G55,"") | M55: ='🏠 INICIO'!C8 -> 0.1 | N55: =IF(I55<>"",I55-(G55/(1-H55)),"") | O55: =IF(I55<>"",L55,"")
B57: 📊 TOTALES | E57: =SUMIF(E6:E55,"<>",E6:E55) -> 36 | G57: =SUMIF(G6:G55,"<>",G6:G55) -> #REF! | I57: =SUMIF(I6:I55,"<>",I6:I55) -> #REF! | J57: =SUMIF(J6:J55,"<>",J6:J55) -> #REF! | L57: =SUMIF(L6:L55,"<>",L6:L55) -> #REF! | N57: =SUMIF(N6:N55,"<>",N6:N55) -> #REF! | O57: =SUMIF(O6:O55,"<>",O6:O55) -> #REF!
B59: 🟡 ¿CÓMO SE CALCULA TU PRECIO DE VENTA?
B61: PASO 1 → | C61: 💰 INVERSIÓN TOTAL = Precio costo del catálogo + Gastos fijos (empaque, bolsas, etc.)
B62: PASO 2 → | C62: 📈 PRECIO CON GANANCIA = Inversión ÷ (1 − 0.30) ← divide entre 0.70 para que el 30% quede DENTRO del precio
B63: PASO 3 → | C63: 🏷️ PRECIO FINAL DE VENTA = Precio con ganancia ÷ (1 − 0.10) ← divide entre 0.90 para que el 10% de comisión quede DENTRO
B65: ✅ EJEMPLO PRÁCTICO (costo S/13 + empaque S/2):
B66: Costo catálogo: | C66: S/ 13.00
B67: + Gastos fijos: | C67: S/ 2.00
B68: = Inversión total: | C68: S/ 15.00
B69: ÷ (1 − 0.30): | C69: S/ 15.00 ÷ 0.70 = S/ 21.43 ← ya incluye tu ganancia del 30%
B70: ÷ (1 − 0.10): | C70: S/ 21.43 ÷ 0.90 = S/ 23.81 ← PRECIO FINAL AL PÚBLICO
B72: 💵 TU GANANCIA NETA = S/ 21.43 − S/ 15.00 = S/ 6.43 (tu 30% sobre el precio)
B73: 💎 COMISIÓN VENDEDORA = S/ 23.81 − S/ 21.43 = S/ 2.38 (su 10% sobre el precio)
B75: 🔑 ¿QUÉ SIGNIFICA CADA COLUMNA?
B76: 📥 INVERSIÓN (col G): | C76: Lo que TÚ pagas: precio del catálogo + empaque. Este es tu costo real.
B77: 📈 % MARGEN (col H): | C77: Tu ganancia deseada. 30% significa que de cada S/100 que vendas, S/30 son tuyos.
B78: 🏷️ PRECIO VENTA (col I): | C78: Lo que le cobras al cliente. Ya incluye tu 30% de ganancia + 10% de comisión vendedora.
B79: 💵 MARGEN S/ (col K): | C79: Tu ganancia en soles: lo que ganas TÚ por cada producto (el 30% del precio).
B80: 💎 COMISIÓN S/ (col M): | C80: Lo que le pagas a tu vendedora por vender el producto (el 10% del precio).
B81: ✅ GANANCIA NETA (col N): | C81: Tu MARGEN S/ — Es lo que REALMENTE te queda a ti después de pagar la comisión.
B83: #VALUE!

Sheet 📊 CALCULADORA CAMPAÑA
B1: 📊 CALCULADORA DE CAMPAÑA — Registra lo que vendiste esta campaña | P1: #VALUE!
B2: ✅ ÚSALA CADA CAMPAÑA (cada ~3 semanas). Diferencia con PRECIOS BASE: aquí registras ventas reales, allá defines precios permanentes.
B3: CAMPAÑA N°: | C3: 1 | E3: MES: | F3: ENERO | H3: % COMISIÓN: | I3: ='🏠 INICIO'!C8 -> 0.1 | J3: ← Edita en hoja INICIO · Aquí se actualiza solo
B5: # | C5: MES | D5: CATÁLOGO | E5: PRODUCTO | F5: 💰 COSTO Producto | G5: 📦 COSTO UNITARIO | H5: 📥 COSTO TOTAL | I5: 📈 % Ganancia | J5: 🏷️ PRECIO Venta | K5: 💸 COSTO Total | L5: 💵 MARGEN S/ | M5: 🏆 COM. % | N5: 💎 COM. S/ | O5: ✅ GANANCIA NETA
B6: 1 | C6: JUNIO | D6: NATURA | E6: Crema Corporal Tododia | F6: 20 | G6: 3 | H6: =IF(F6<>"",F6+G6,"") -> 23 | I6: 0.36 | J6: =IF(AND(H6<>"",I6<1),H6/(1-I6),"") -> 35.9375 | K6: =IF(F6<>"",F6+G6,"") -> 23 | L6: =IF(J6<>"",J6-K6,"") -> 12.9375 | M6: ='🏠 INICIO'!C8 -> 0.1 | N6: =IF(J6<>"",J6*M6,"") -> 3.59375 | O6: =IF(L6<>"",L6-N6,"") -> 9.34375
B7: 2 | C7: JUNIO | D7: ESIKA | E7: Expression Magic | F7: 21 | G7: 3 | H7: =IF(F7<>"",F7+G7,"") -> 24 | I7: 0.35 | J7: =IF(AND(H7<>"",I7<1),H7/(1-I7),"") -> 36.923077 | K7: =IF(F7<>"",F7+G7,"") -> 24 | L7: =IF(J7<>"",J7-K7,"") -> 12.923077 | M7: ='🏠 INICIO'!C8 -> 0.1 | N7: =IF(J7<>"",J7*M7,"") -> 3.6923077 | O7: =IF(L7<>"",L7-N7,"") -> 9.2307692
B8: 3 | C8: JUNIO | D8: ESIKA | E8: Mini Chic Colonia | F8: 12 | G8: 3 | H8: =IF(F8<>"",F8+G8,"") -> 15 | I8: 0.3 | J8: =IF(AND(H8<>"",I8<1),H8/(1-I8),"") -> 21.428571 | K8: =IF(F8<>"",F8+G8,"") -> 15 | L8: =IF(J8<>"",J8-K8,"") -> 6.4285714 | M8: ='🏠 INICIO'!C8 -> 0.1 | N8: =IF(J8<>"",J8*M8,"") -> 2.1428571 | O8: =IF(L8<>"",L8-N8,"") -> 4.2857143
B9: 4 | C9: JUNIO | D9: YANBAL | E9: Kit Perfume Dulce Vanidad | F9: 65 | G9: 3 | H9: =IF(F9<>"",F9+G9,"") -> 68 | I9: 0.36 | J9: =IF(AND(H9<>"",I9<1),H9/(1-I9),"") -> 106.25 | K9: =IF(F9<>"",F9+G9,"") -> 68 | L9: =IF(J9<>"",J9-K9,"") -> 38.25 | M9: ='🏠 INICIO'!C8 -> 0.1 | N9: =IF(J9<>"",J9*M9,"") -> 10.625 | O9: =IF(L9<>"",L9-N9,"") -> 27.625
B10: 5 | C10: ENERO | D10: NATURA | E10: Beijo Humor Colonia | F10: 45 | G10: 3 | H10: =IF(F10<>"",F10+G10,"") -> 48 | I10: 0.35 | J10: =IF(AND(H10<>"",I10<1),H10/(1-I10),"") -> 73.846154 | K10: =IF(F10<>"",F10+G10,"") -> 48 | L10: =IF(J10<>"",J10-K10,"") -> 25.846154 | M10: ='🏠 INICIO'!C8 -> 0.1 | N10: =IF(J10<>"",J10*M10,"") -> 7.3846154 | O10: =IF(L10<>"",L10-N10,"") -> 18.461538
B11: 6 | C11: ENERO | D11: CYZONE | E11: Set de Brochas 5 piezas | F11: 30 | G11: 3 | H11: =IF(F11<>"",F11+G11,"") -> 33 | I11: 0.35 | J11: =IF(AND(H11<>"",I11<1),H11/(1-I11),"") -> 50.769231 | K11: =IF(F11<>"",F11+G11,"") -> 33 | L11: =IF(J11<>"",J11-K11,"") -> 17.769231 | M11: ='🏠 INICIO'!C8 -> 0.1 | N11: =IF(J11<>"",J11*M11,"") -> 5.0769231 | O11: =IF(L11<>"",L11-N11,"") -> 12.692308
B12: 7 | C12: ENERO | D12: AVON | E12: Anew Gold Crema Facial | F12: 35.5 | G12: 3 | H12: =IF(F12<>"",F12+G12,"") -> 38.5 | I12: 0.3 | J12: =IF(AND(H12<>"",I12<1),H12/(1-I12),"") -> 55 | K12: =IF(F12<>"",F12+G12,"") -> 38.5 | L12: =IF(J12<>"",J12-K12,"") -> 16.5 | M12: ='🏠 INICIO'!C8 -> 0.1 | N12: =IF(J12<>"",J12*M12,"") -> 5.5 | O12: =IF(L12<>"",L12-N12,"") -> 11
B13: 8 | C13: ENERO | D13: ESIKA | E13: Color Fix Barra Vino | F13: 18 | G13: 3 | H13: =IF(F13<>"",F13+G13,"") -> 21 | I13: 0.35 | J13: =IF(AND(H13<>"",I13<1),H13/(1-I13),"") -> 32.307692 | K13: =IF(F13<>"",F13+G13,"") -> 21 | L13: =IF(J13<>"",J13-K13,"") -> 11.307692 | M13: ='🏠 INICIO'!C8 -> 0.1 | N13: =IF(J13<>"",J13*M13,"") -> 3.2307692 | O13: =IF(L13<>"",L13-N13,"") -> 8.0769231
B14: 9 | C14: ENERO | D14: ORIFLAME | E14: Giordani Gold Serum | F14: 51 | G14: 3 | H14: =IF(F14<>"",F14+G14,"") -> 54 | I14: 0.3 | J14: =IF(AND(H14<>"",I14<1),H14/(1-I14),"") -> 77.142857 | K14: =IF(F14<>"",F14+G14,"") -> 54 | L14: =IF(J14<>"",J14-K14,"") -> 23.142857 | M14: ='🏠 INICIO'!C8 -> 0.1 | N14: =IF(J14<>"",J14*M14,"") -> 7.7142857 | O14: =IF(L14<>"",L14-N14,"") -> 15.428571
B15: 10 | C15: ENERO | D15: YANBAL | E15: Argollas Spiga Perle | F15: 55 | G15: 3 | H15: =IF(F15<>"",F15+G15,"") -> 58 | I15: 0.35 | J15: =IF(AND(H15<>"",I15<1),H15/(1-I15),"") -> 89.230769 | K15: =IF(F15<>"",F15+G15,"") -> 58 | L15: =IF(J15<>"",J15-K15,"") -> 31.230769 | M15: ='🏠 INICIO'!C8 -> 0.1 | N15: =IF(J15<>"",J15*M15,"") -> 8.9230769 | O15: =IF(L15<>"",L15-N15,"") -> 22.307692
B16: 11 | C16: ENERO | D16: FARMASI | E16: Labial Matte Stay 24h | F16: 18 | G16: 3 | H16: =IF(F16<>"",F16+G16,"") -> 21 | I16: 0.3 | J16: =IF(AND(H16<>"",I16<1),H16/(1-I16),"") -> 30 | K16: =IF(F16<>"",F16+G16,"") -> 21 | L16: =IF(J16<>"",J16-K16,"") -> 9 | M16: ='🏠 INICIO'!C8 -> 0.1 | N16: =IF(J16<>"",J16*M16,"") -> 3 | O16: =IF(L16<>"",L16-N16,"") -> 6
B17: 12 | C17: ENERO | D17: LBEL | E17: Serum Effet Parfait | F17: 59 | G17: 3 | H17: =IF(F17<>"",F17+G17,"") -> 62 | I17: 0.35 | J17: =IF(AND(H17<>"",I17<1),H17/(1-I17),"") -> 95.384615 | K17: =IF(F17<>"",F17+G17,"") -> 62 | L17: =IF(J17<>"",J17-K17,"") -> 33.384615 | M17: ='🏠 INICIO'!C8 -> 0.1 | N17: =IF(J17<>"",J17*M17,"") -> 9.5384615 | O17: =IF(L17<>"",L17-N17,"") -> 23.846154
B18: 13 | C18: ENERO | D18: CYZONE | E18: Pink Crush Colonia | F18: 28 | G18: 3 | H18: =IF(F18<>"",F18+G18,"") -> 31 | I18: 0.35 | J18: =IF(AND(H18<>"",I18<1),H18/(1-I18),"") -> 47.692308 | K18: =IF(F18<>"",F18+G18,"") -> 31 | L18: =IF(J18<>"",J18-K18,"") -> 16.692308 | M18: ='🏠 INICIO'!C8 -> 0.1 | N18: =IF(J18<>"",J18*M18,"") -> 4.7692308 | O18: =IF(L18<>"",L18-N18,"") -> 11.923077
B19: 14 | C19: ENERO | D19: NATURA | E19: Perfume Tododia Floral | F19: 34 | G19: 3 | H19: =IF(F19<>"",F19+G19,"") -> 37 | I19: 0.35 | J19: =IF(AND(H19<>"",I19<1),H19/(1-I19),"") -> 56.923077 | K19: =IF(F19<>"",F19+G19,"") -> 37 | L19: =IF(J19<>"",J19-K19,"") -> 19.923077 | M19: ='🏠 INICIO'!C8 -> 0.1 | N19: =IF(J19<>"",J19*M19,"") -> 5.6923077 | O19: =IF(L19<>"",L19-N19,"") -> 14.230769
B20: 15 | C20: ENERO | D20: ESIKA | E20: Rimel Esika Pro | F20: 22 | G20: 3 | H20: =IF(F20<>"",F20+G20,"") -> 25 | I20: 0.35 | J20: =IF(AND(H20<>"",I20<1),H20/(1-I20),"") -> 38.461538 | K20: =IF(F20<>"",F20+G20,"") -> 25 | L20: =IF(J20<>"",J20-K20,"") -> 13.461538 | M20: ='🏠 INICIO'!C8 -> 0.1 | N20: =IF(J20<>"",J20*M20,"") -> 3.8461538 | O20: =IF(L20<>"",L20-N20,"") -> 9.6153846
B21: 16 | H21: =IF(F21<>"",F21+G21,"") | J21: =IF(AND(H21<>"",I21<>0,I21<1),H21/(1-I21),"") | K21: =IF(F21<>"",F21+G21,"") | L21: =IF(J21<>"",J21-K21,"") | M21: ='🏠 INICIO'!C8 -> 0.1 | N21: =IF(J21<>"",J21*M21,"") | O21: =IF(L21<>"",L21-N21,"")
B22: 17 | H22: =IF(F22<>"",F22+G22,"") | J22: =IF(AND(H22<>"",I22<>0,I22<1),H22/(1-I22),"") | K22: =IF(F22<>"",F22+G22,"") | L22: =IF(J22<>"",J22-K22,"") | M22: ='🏠 INICIO'!C8 -> 0.1 | N22: =IF(J22<>"",J22*M22,"") | O22: =IF(L22<>"",L22-N22,"")
B23: 18 | H23: =IF(F23<>"",F23+G23,"") | J23: =IF(AND(H23<>"",I23<>0,I23<1),H23/(1-I23),"") | K23: =IF(F23<>"",F23+G23,"") | L23: =IF(J23<>"",J23-K23,"") | M23: ='🏠 INICIO'!C8 -> 0.1 | N23: =IF(J23<>"",J23*M23,"") | O23: =IF(L23<>"",L23-N23,"")
B24: 19 | H24: =IF(F24<>"",F24+G24,"") | J24: =IF(AND(H24<>"",I24<>0,I24<1),H24/(1-I24),"") | K24: =IF(F24<>"",F24+G24,"") | L24: =IF(J24<>"",J24-K24,"") | M24: ='🏠 INICIO'!C8 -> 0.1 | N24: =IF(J24<>"",J24*M24,"") | O24: =IF(L24<>"",L24-N24,"")
B25: 20 | H25: =IF(F25<>"",F25+G25,"") | J25: =IF(AND(H25<>"",I25<>0,I25<1),H25/(1-I25),"") | K25: =IF(F25<>"",F25+G25,"") | L25: =IF(J25<>"",J25-K25,"") | M25: ='🏠 INICIO'!C8 -> 0.1 | N25: =IF(J25<>"",J25*M25,"") | O25: =IF(L25<>"",L25-N25,"")
B26: 21 | H26: =IF(F26<>"",F26+G26,"") | J26: =IF(AND(H26<>"",I26<>0,I26<1),H26/(1-I26),"") | K26: =IF(F26<>"",F26+G26,"") | L26: =IF(J26<>"",J26-K26,"") | M26: ='🏠 INICIO'!C8 -> 0.1 | N26: =IF(J26<>"",J26*M26,"") | O26: =IF(L26<>"",L26-N26,"")
B27: 22 | H27: =IF(F27<>"",F27+G27,"") | J27: =IF(AND(H27<>"",I27<>0,I27<1),H27/(1-I27),"") | K27: =IF(F27<>"",F27+G27,"") | L27: =IF(J27<>"",J27-K27,"") | M27: ='🏠 INICIO'!C8 -> 0.1 | N27: =IF(J27<>"",J27*M27,"") | O27: =IF(L27<>"",L27-N27,"")
B28: 23 | H28: =IF(F28<>"",F28+G28,"") | J28: =IF(AND(H28<>"",I28<>0,I28<1),H28/(1-I28),"") | K28: =IF(F28<>"",F28+G28,"") | L28: =IF(J28<>"",J28-K28,"") | M28: ='🏠 INICIO'!C8 -> 0.1 | N28: =IF(J28<>"",J28*M28,"") | O28: =IF(L28<>"",L28-N28,"")
B29: 24 | H29: =IF(F29<>"",F29+G29,"") | J29: =IF(AND(H29<>"",I29<>0,I29<1),H29/(1-I29),"") | K29: =IF(F29<>"",F29+G29,"") | L29: =IF(J29<>"",J29-K29,"") | M29: ='🏠 INICIO'!C8 -> 0.1 | N29: =IF(J29<>"",J29*M29,"") | O29: =IF(L29<>"",L29-N29,"")
B30: 25 | H30: =IF(F30<>"",F30+G30,"") | J30: =IF(AND(H30<>"",I30<>0,I30<1),H30/(1-I30),"") | K30: =IF(F30<>"",F30+G30,"") | L30: =IF(J30<>"",J30-K30,"") | M30: ='🏠 INICIO'!C8 -> 0.1 | N30: =IF(J30<>"",J30*M30,"") | O30: =IF(L30<>"",L30-N30,"")
B31: 26 | H31: =IF(F31<>"",F31+G31,"") | J31: =IF(AND(H31<>"",I31<>0,I31<1),H31/(1-I31),"") | K31: =IF(F31<>"",F31+G31,"") | L31: =IF(J31<>"",J31-K31,"") | M31: ='🏠 INICIO'!C8 -> 0.1 | N31: =IF(J31<>"",J31*M31,"") | O31: =IF(L31<>"",L31-N31,"")
B32: 27 | H32: =IF(F32<>"",F32+G32,"") | J32: =IF(AND(H32<>"",I32<>0,I32<1),H32/(1-I32),"") | K32: =IF(F32<>"",F32+G32,"") | L32: =IF(J32<>"",J32-K32,"") | M32: ='🏠 INICIO'!C8 -> 0.1 | N32: =IF(J32<>"",J32*M32,"") | O32: =IF(L32<>"",L32-N32,"")
B33: 28 | H33: =IF(F33<>"",F33+G33,"") | J33: =IF(AND(H33<>"",I33<>0,I33<1),H33/(1-I33),"") | K33: =IF(F33<>"",F33+G33,"") | L33: =IF(J33<>"",J33-K33,"") | M33: ='🏠 INICIO'!C8 -> 0.1 | N33: =IF(J33<>"",J33*M33,"") | O33: =IF(L33<>"",L33-N33,"")
B34: 29 | H34: =IF(F34<>"",F34+G34,"") | J34: =IF(AND(H34<>"",I34<>0,I34<1),H34/(1-I34),"") | K34: =IF(F34<>"",F34+G34,"") | L34: =IF(J34<>"",J34-K34,"") | M34: ='🏠 INICIO'!C8 -> 0.1 | N34: =IF(J34<>"",J34*M34,"") | O34: =IF(L34<>"",L34-N34,"")
B35: 30 | H35: =IF(F35<>"",F35+G35,"") | J35: =IF(AND(H35<>"",I35<>0,I35<1),H35/(1-I35),"") | K35: =IF(F35<>"",F35+G35,"") | L35: =IF(J35<>"",J35-K35,"") | M35: ='🏠 INICIO'!C8 -> 0.1 | N35: =IF(J35<>"",J35*M35,"") | O35: =IF(L35<>"",L35-N35,"")
B36: 31 | H36: =IF(F36<>"",F36+G36,"") | J36: =IF(AND(H36<>"",I36<>0,I36<1),H36/(1-I36),"") | K36: =IF(F36<>"",F36+G36,"") | L36: =IF(J36<>"",J36-K36,"") | M36: ='🏠 INICIO'!C8 -> 0.1 | N36: =IF(J36<>"",J36*M36,"") | O36: =IF(L36<>"",L36-N36,"")
B37: 32 | H37: =IF(F37<>"",F37+G37,"") | J37: =IF(AND(H37<>"",I37<>0,I37<1),H37/(1-I37),"") | K37: =IF(F37<>"",F37+G37,"") | L37: =IF(J37<>"",J37-K37,"") | M37: ='🏠 INICIO'!C8 -> 0.1 | N37: =IF(J37<>"",J37*M37,"") | O37: =IF(L37<>"",L37-N37,"")
B38: 33 | H38: =IF(F38<>"",F38+G38,"") | J38: =IF(AND(H38<>"",I38<>0,I38<1),H38/(1-I38),"") | K38: =IF(F38<>"",F38+G38,"") | L38: =IF(J38<>"",J38-K38,"") | M38: ='🏠 INICIO'!C8 -> 0.1 | N38: =IF(J38<>"",J38*M38,"") | O38: =IF(L38<>"",L38-N38,"")
B39: 34 | H39: =IF(F39<>"",F39+G39,"") | J39: =IF(AND(H39<>"",I39<>0,I39<1),H39/(1-I39),"") | K39: =IF(F39<>"",F39+G39,"") | L39: =IF(J39<>"",J39-K39,"") | M39: ='🏠 INICIO'!C8 -> 0.1 | N39: =IF(J39<>"",J39*M39,"") | O39: =IF(L39<>"",L39-N39,"")
B40: 35 | H40: =IF(F40<>"",F40+G40,"") | J40: =IF(AND(H40<>"",I40<>0,I40<1),H40/(1-I40),"") | K40: =IF(F40<>"",F40+G40,"") | L40: =IF(J40<>"",J40-K40,"") | M40: ='🏠 INICIO'!C8 -> 0.1 | N40: =IF(J40<>"",J40*M40,"") | O40: =IF(L40<>"",L40-N40,"")
B41: 36 | H41: =IF(F41<>"",F41+G41,"") | J41: =IF(AND(H41<>"",I41<>0,I41<1),H41/(1-I41),"") | K41: =IF(F41<>"",F41+G41,"") | L41: =IF(J41<>"",J41-K41,"") | M41: ='🏠 INICIO'!C8 -> 0.1 | N41: =IF(J41<>"",J41*M41,"") | O41: =IF(L41<>"",L41-N41,"")
B42: 37 | H42: =IF(F42<>"",F42+G42,"") | J42: =IF(AND(H42<>"",I42<>0,I42<1),H42/(1-I42),"") | K42: =IF(F42<>"",F42+G42,"") | L42: =IF(J42<>"",J42-K42,"") | M42: ='🏠 INICIO'!C8 -> 0.1 | N42: =IF(J42<>"",J42*M42,"") | O42: =IF(L42<>"",L42-N42,"")
B43: 38 | H43: =IF(F43<>"",F43+G43,"") | J43: =IF(AND(H43<>"",I43<>0,I43<1),H43/(1-I43),"") | K43: =IF(F43<>"",F43+G43,"") | L43: =IF(J43<>"",J43-K43,"") | M43: ='🏠 INICIO'!C8 -> 0.1 | N43: =IF(J43<>"",J43*M43,"") | O43: =IF(L43<>"",L43-N43,"")
B44: 39 | H44: =IF(F44<>"",F44+G44,"") | J44: =IF(AND(H44<>"",I44<>0,I44<1),H44/(1-I44),"") | K44: =IF(F44<>"",F44+G44,"") | L44: =IF(J44<>"",J44-K44,"") | M44: ='🏠 INICIO'!C8 -> 0.1 | N44: =IF(J44<>"",J44*M44,"") | O44: =IF(L44<>"",L44-N44,"")
B45: 40 | H45: =IF(F45<>"",F45+G45,"") | J45: =IF(AND(H45<>"",I45<>0,I45<1),H45/(1-I45),"") | K45: =IF(F45<>"",F45+G45,"") | L45: =IF(J45<>"",J45-K45,"") | M45: ='🏠 INICIO'!C8 -> 0.1 | N45: =IF(J45<>"",J45*M45,"") | O45: =IF(L45<>"",L45-N45,"")
B46: 41 | H46: =IF(F46<>"",F46+G46,"") | J46: =IF(AND(H46<>"",I46<>0,I46<1),H46/(1-I46),"") | K46: =IF(F46<>"",F46+G46,"") | L46: =IF(J46<>"",J46-K46,"") | M46: ='🏠 INICIO'!C8 -> 0.1 | N46: =IF(J46<>"",J46*M46,"") | O46: =IF(L46<>"",L46-N46,"")
B47: 42 | H47: =IF(F47<>"",F47+G47,"") | J47: =IF(AND(H47<>"",I47<>0,I47<1),H47/(1-I47),"") | K47: =IF(F47<>"",F47+G47,"") | L47: =IF(J47<>"",J47-K47,"") | M47: ='🏠 INICIO'!C8 -> 0.1 | N47: =IF(J47<>"",J47*M47,"") | O47: =IF(L47<>"",L47-N47,"")
B48: 43 | H48: =IF(F48<>"",F48+G48,"") | J48: =IF(AND(H48<>"",I48<>0,I48<1),H48/(1-I48),"") | K48: =IF(F48<>"",F48+G48,"") | L48: =IF(J48<>"",J48-K48,"") | M48: ='🏠 INICIO'!C8 -> 0.1 | N48: =IF(J48<>"",J48*M48,"") | O48: =IF(L48<>"",L48-N48,"")
B49: 44 | H49: =IF(F49<>"",F49+G49,"") | J49: =IF(AND(H49<>"",I49<>0,I49<1),H49/(1-I49),"") | K49: =IF(F49<>"",F49+G49,"") | L49: =IF(J49<>"",J49-K49,"") | M49: ='🏠 INICIO'!C8 -> 0.1 | N49: =IF(J49<>"",J49*M49,"") | O49: =IF(L49<>"",L49-N49,"")
B50: 45 | H50: =IF(F50<>"",F50+G50,"") | J50: =IF(AND(H50<>"",I50<>0,I50<1),H50/(1-I50),"") | K50: =IF(F50<>"",F50+G50,"") | L50: =IF(J50<>"",J50-K50,"") | M50: ='🏠 INICIO'!C8 -> 0.1 | N50: =IF(J50<>"",J50*M50,"") | O50: =IF(L50<>"",L50-N50,"")
B51: 46 | H51: =IF(F51<>"",F51+G51,"") | J51: =IF(AND(H51<>"",I51<>0,I51<1),H51/(1-I51),"") | K51: =IF(F51<>"",F51+G51,"") | L51: =IF(J51<>"",J51-K51,"") | M51: ='🏠 INICIO'!C8 -> 0.1 | N51: =IF(J51<>"",J51*M51,"") | O51: =IF(L51<>"",L51-N51,"")
B52: 47 | H52: =IF(F52<>"",F52+G52,"") | J52: =IF(AND(H52<>"",I52<>0,I52<1),H52/(1-I52),"") | K52: =IF(F52<>"",F52+G52,"") | L52: =IF(J52<>"",J52-K52,"") | M52: ='🏠 INICIO'!C8 -> 0.1 | N52: =IF(J52<>"",J52*M52,"") | O52: =IF(L52<>"",L52-N52,"")
B53: 48 | H53: =IF(F53<>"",F53+G53,"") | J53: =IF(AND(H53<>"",I53<>0,I53<1),H53/(1-I53),"") | K53: =IF(F53<>"",F53+G53,"") | L53: =IF(J53<>"",J53-K53,"") | M53: ='🏠 INICIO'!C8 -> 0.1 | N53: =IF(J53<>"",J53*M53,"") | O53: =IF(L53<>"",L53-N53,"")
B54: 49 | H54: =IF(F54<>"",F54+G54,"") | J54: =IF(AND(H54<>"",I54<>0,I54<1),H54/(1-I54),"") | K54: =IF(F54<>"",F54+G54,"") | L54: =IF(J54<>"",J54-K54,"") | M54: ='🏠 INICIO'!C8 -> 0.1 | N54: =IF(J54<>"",J54*M54,"") | O54: =IF(L54<>"",L54-N54,"")
B55: 50 | H55: =IF(F55<>"",F55+G55,"") | J55: =IF(AND(H55<>"",I55<>0,I55<1),H55/(1-I55),"") | K55: =IF(F55<>"",F55+G55,"") | L55: =IF(J55<>"",J55-K55,"") | M55: ='🏠 INICIO'!C8 -> 0.1 | N55: =IF(J55<>"",J55*M55,"") | O55: =IF(L55<>"",L55-N55,"")
B56: 51 | H56: =IF(F56<>"",F56+G56,"") | J56: =IF(AND(H56<>"",I56<>0,I56<1),H56/(1-I56),"") | K56: =IF(F56<>"",F56+G56,"") | L56: =IF(J56<>"",J56-K56,"") | M56: ='🏠 INICIO'!C8 -> 0.1 | N56: =IF(J56<>"",J56*M56,"") | O56: =IF(L56<>"",L56-N56,"")
B57: 52 | H57: =IF(F57<>"",F57+G57,"") | J57: =IF(AND(H57<>"",I57<>0,I57<1),H57/(1-I57),"") | K57: =IF(F57<>"",F57+G57,"") | L57: =IF(J57<>"",J57-K57,"") | M57: ='🏠 INICIO'!C8 -> 0.1 | N57: =IF(J57<>"",J57*M57,"") | O57: =IF(L57<>"",L57-N57,"")
B58: 53 | H58: =IF(F58<>"",F58+G58,"") | J58: =IF(AND(H58<>"",I58<>0,I58<1),H58/(1-I58),"") | K58: =IF(F58<>"",F58+G58,"") | L58: =IF(J58<>"",J58-K58,"") | M58: ='🏠 INICIO'!C8 -> 0.1 | N58: =IF(J58<>"",J58*M58,"") | O58: =IF(L58<>"",L58-N58,"")
B59: 54 | H59: =IF(F59<>"",F59+G59,"") | J59: =IF(AND(H59<>"",I59<>0,I59<1),H59/(1-I59),"") | K59: =IF(F59<>"",F59+G59,"") | L59: =IF(J59<>"",J59-K59,"") | M59: ='🏠 INICIO'!C8 -> 0.1 | N59: =IF(J59<>"",J59*M59,"") | O59: =IF(L59<>"",L59-N59,"")
B60: 55 | H60: =IF(F60<>"",F60+G60,"") | J60: =IF(AND(H60<>"",I60<>0,I60<1),H60/(1-I60),"") | K60: =IF(F60<>"",F60+G60,"") | L60: =IF(J60<>"",J60-K60,"") | M60: ='🏠 INICIO'!C8 -> 0.1 | N60: =IF(J60<>"",J60*M60,"") | O60: =IF(L60<>"",L60-N60,"")
B61: 56 | H61: =IF(F61<>"",F61+G61,"") | J61: =IF(AND(H61<>"",I61<>0,I61<1),H61/(1-I61),"") | K61: =IF(F61<>"",F61+G61,"") | L61: =IF(J61<>"",J61-K61,"") | M61: ='🏠 INICIO'!C8 -> 0.1 | N61: =IF(J61<>"",J61*M61,"") | O61: =IF(L61<>"",L61-N61,"")
B62: 57 | H62: =IF(F62<>"",F62+G62,"") | J62: =IF(AND(H62<>"",I62<>0,I62<1),H62/(1-I62),"") | K62: =IF(F62<>"",F62+G62,"") | L62: =IF(J62<>"",J62-K62,"") | M62: ='🏠 INICIO'!C8 -> 0.1 | N62: =IF(J62<>"",J62*M62,"") | O62: =IF(L62<>"",L62-N62,"")
B63: 58 | H63: =IF(F63<>"",F63+G63,"") | J63: =IF(AND(H63<>"",I63<>0,I63<1),H63/(1-I63),"") | K63: =IF(F63<>"",F63+G63,"") | L63: =IF(J63<>"",J63-K63,"") | M63: ='🏠 INICIO'!C8 -> 0.1 | N63: =IF(J63<>"",J63*M63,"") | O63: =IF(L63<>"",L63-N63,"")
B64: 59 | H64: =IF(F64<>"",F64+G64,"") | J64: =IF(AND(H64<>"",I64<>0,I64<1),H64/(1-I64),"") | K64: =IF(F64<>"",F64+G64,"") | L64: =IF(J64<>"",J64-K64,"") | M64: ='🏠 INICIO'!C8 -> 0.1 | N64: =IF(J64<>"",J64*M64,"") | O64: =IF(L64<>"",L64-N64,"")
B65: 60 | H65: =IF(F65<>"",F65+G65,"") | J65: =IF(AND(H65<>"",I65<>0,I65<1),H65/(1-I65),"") | K65: =IF(F65<>"",F65+G65,"") | L65: =IF(J65<>"",J65-K65,"") | M65: ='🏠 INICIO'!C8 -> 0.1 | N65: =IF(J65<>"",J65*M65,"") | O65: =IF(L65<>"",L65-N65,"")
B66: 61 | H66: =IF(F66<>"",F66+G66,"") | J66: =IF(AND(H66<>"",I66<>0,I66<1),H66/(1-I66),"") | K66: =IF(F66<>"",F66+G66,"") | L66: =IF(J66<>"",J66-K66,"") | M66: ='🏠 INICIO'!C8 -> 0.1 | N66: =IF(J66<>"",J66*M66,"") | O66: =IF(L66<>"",L66-N66,"")
B67: 62 | H67: =IF(F67<>"",F67+G67,"") | J67: =IF(AND(H67<>"",I67<>0,I67<1),H67/(1-I67),"") | K67: =IF(F67<>"",F67+G67,"") | L67: =IF(J67<>"",J67-K67,"") | M67: ='🏠 INICIO'!C8 -> 0.1 | N67: =IF(J67<>"",J67*M67,"") | O67: =IF(L67<>"",L67-N67,"")
B68: 63 | H68: =IF(F68<>"",F68+G68,"") | J68: =IF(AND(H68<>"",I68<>0,I68<1),H68/(1-I68),"") | K68: =IF(F68<>"",F68+G68,"") | L68: =IF(J68<>"",J68-K68,"") | M68: ='🏠 INICIO'!C8 -> 0.1 | N68: =IF(J68<>"",J68*M68,"") | O68: =IF(L68<>"",L68-N68,"")
B69: 64 | H69: =IF(F69<>"",F69+G69,"") | J69: =IF(AND(H69<>"",I69<>0,I69<1),H69/(1-I69),"") | K69: =IF(F69<>"",F69+G69,"") | L69: =IF(J69<>"",J69-K69,"") | M69: ='🏠 INICIO'!C8 -> 0.1 | N69: =IF(J69<>"",J69*M69,"") | O69: =IF(L69<>"",L69-N69,"")
B70: 65 | H70: =IF(F70<>"",F70+G70,"") | J70: =IF(AND(H70<>"",I70<>0,I70<1),H70/(1-I70),"") | K70: =IF(F70<>"",F70+G70,"") | L70: =IF(J70<>"",J70-K70,"") | M70: ='🏠 INICIO'!C8 -> 0.1 | N70: =IF(J70<>"",J70*M70,"") | O70: =IF(L70<>"",L70-N70,"")
B71: 66 | H71: =IF(F71<>"",F71+G71,"") | J71: =IF(AND(H71<>"",I71<>0,I71<1),H71/(1-I71),"") | K71: =IF(F71<>"",F71+G71,"") | L71: =IF(J71<>"",J71-K71,"") | M71: ='🏠 INICIO'!C8 -> 0.1 | N71: =IF(J71<>"",J71*M71,"") | O71: =IF(L71<>"",L71-N71,"")
B72: 67 | H72: =IF(F72<>"",F72+G72,"") | J72: =IF(AND(H72<>"",I72<>0,I72<1),H72/(1-I72),"") | K72: =IF(F72<>"",F72+G72,"") | L72: =IF(J72<>"",J72-K72,"") | M72: ='🏠 INICIO'!C8 -> 0.1 | N72: =IF(J72<>"",J72*M72,"") | O72: =IF(L72<>"",L72-N72,"")
B73: 68 | H73: =IF(F73<>"",F73+G73,"") | J73: =IF(AND(H73<>"",I73<>0,I73<1),H73/(1-I73),"") | K73: =IF(F73<>"",F73+G73,"") | L73: =IF(J73<>"",J73-K73,"") | M73: ='🏠 INICIO'!C8 -> 0.1 | N73: =IF(J73<>"",J73*M73,"") | O73: =IF(L73<>"",L73-N73,"")
B74: 69 | H74: =IF(F74<>"",F74+G74,"") | J74: =IF(AND(H74<>"",I74<>0,I74<1),H74/(1-I74),"") | K74: =IF(F74<>"",F74+G74,"") | L74: =IF(J74<>"",J74-K74,"") | M74: ='🏠 INICIO'!C8 -> 0.1 | N74: =IF(J74<>"",J74*M74,"") | O74: =IF(L74<>"",L74-N74,"")
B75: 70 | H75: =IF(F75<>"",F75+G75,"") | J75: =IF(AND(H75<>"",I75<>0,I75<1),H75/(1-I75),"") | K75: =IF(F75<>"",F75+G75,"") | L75: =IF(J75<>"",J75-K75,"") | M75: ='🏠 INICIO'!C8 -> 0.1 | N75: =IF(J75<>"",J75*M75,"") | O75: =IF(L75<>"",L75-N75,"")
B76: 71 | H76: =IF(F76<>"",F76+G76,"") | J76: =IF(AND(H76<>"",I76<>0,I76<1),H76/(1-I76),"") | K76: =IF(F76<>"",F76+G76,"") | L76: =IF(J76<>"",J76-K76,"") | M76: ='🏠 INICIO'!C8 -> 0.1 | N76: =IF(J76<>"",J76*M76,"") | O76: =IF(L76<>"",L76-N76,"")
B77: 72 | H77: =IF(F77<>"",F77+G77,"") | J77: =IF(AND(H77<>"",I77<>0,I77<1),H77/(1-I77),"") | K77: =IF(F77<>"",F77+G77,"") | L77: =IF(J77<>"",J77-K77,"") | M77: ='🏠 INICIO'!C8 -> 0.1 | N77: =IF(J77<>"",J77*M77,"") | O77: =IF(L77<>"",L77-N77,"")
B78: 73 | H78: =IF(F78<>"",F78+G78,"") | J78: =IF(AND(H78<>"",I78<>0,I78<1),H78/(1-I78),"") | K78: =IF(F78<>"",F78+G78,"") | L78: =IF(J78<>"",J78-K78,"") | M78: ='🏠 INICIO'!C8 -> 0.1 | N78: =IF(J78<>"",J78*M78,"") | O78: =IF(L78<>"",L78-N78,"")
B79: 74 | H79: =IF(F79<>"",F79+G79,"") | J79: =IF(AND(H79<>"",I79<>0,I79<1),H79/(1-I79),"") | K79: =IF(F79<>"",F79+G79,"") | L79: =IF(J79<>"",J79-K79,"") | M79: ='🏠 INICIO'!C8 -> 0.1 | N79: =IF(J79<>"",J79*M79,"") | O79: =IF(L79<>"",L79-N79,"")
B80: 75 | H80: =IF(F80<>"",F80+G80,"") | J80: =IF(AND(H80<>"",I80<>0,I80<1),H80/(1-I80),"") | K80: =IF(F80<>"",F80+G80,"") | L80: =IF(J80<>"",J80-K80,"") | M80: ='🏠 INICIO'!C8 -> 0.1 | N80: =IF(J80<>"",J80*M80,"") | O80: =IF(L80<>"",L80-N80,"")
B81: 76 | H81: =IF(F81<>"",F81+G81,"") | J81: =IF(AND(H81<>"",I81<>0,I81<1),H81/(1-I81),"") | K81: =IF(F81<>"",F81+G81,"") | L81: =IF(J81<>"",J81-K81,"") | M81: ='🏠 INICIO'!C8 -> 0.1 | N81: =IF(J81<>"",J81*M81,"") | O81: =IF(L81<>"",L81-N81,"")
B82: 77 | H82: =IF(F82<>"",F82+G82,"") | J82: =IF(AND(H82<>"",I82<>0,I82<1),H82/(1-I82),"") | K82: =IF(F82<>"",F82+G82,"") | L82: =IF(J82<>"",J82-K82,"") | M82: ='🏠 INICIO'!C8 -> 0.1 | N82: =IF(J82<>"",J82*M82,"") | O82: =IF(L82<>"",L82-N82,"")
B83: 78 | H83: =IF(F83<>"",F83+G83,"") | J83: =IF(AND(H83<>"",I83<>0,I83<1),H83/(1-I83),"") | K83: =IF(F83<>"",F83+G83,"") | L83: =IF(J83<>"",J83-K83,"") | M83: ='🏠 INICIO'!C8 -> 0.1 | N83: =IF(J83<>"",J83*M83,"") | O83: =IF(L83<>"",L83-N83,"")
B84: 79 | H84: =IF(F84<>"",F84+G84,"") | J84: =IF(AND(H84<>"",I84<>0,I84<1),H84/(1-I84),"") | K84: =IF(F84<>"",F84+G84,"") | L84: =IF(J84<>"",J84-K84,"") | M84: ='🏠 INICIO'!C8 -> 0.1 | N84: =IF(J84<>"",J84*M84,"") | O84: =IF(L84<>"",L84-N84,"")
B85: 80 | H85: =IF(F85<>"",F85+G85,"") | J85: =IF(AND(H85<>"",I85<>0,I85<1),H85/(1-I85),"") | K85: =IF(F85<>"",F85+G85,"") | L85: =IF(J85<>"",J85-K85,"") | M85: ='🏠 INICIO'!C8 -> 0.1 | N85: =IF(J85<>"",J85*M85,"") | O85: =IF(L85<>"",L85-N85,"")
B86: 81 | H86: =IF(F86<>"",F86+G86,"") | J86: =IF(AND(H86<>"",I86<>0,I86<1),H86/(1-I86),"") | K86: =IF(F86<>"",F86+G86,"") | L86: =IF(J86<>"",J86-K86,"") | M86: ='🏠 INICIO'!C8 -> 0.1 | N86: =IF(J86<>"",J86*M86,"") | O86: =IF(L86<>"",L86-N86,"")
B87: 82 | H87: =IF(F87<>"",F87+G87,"") | J87: =IF(AND(H87<>"",I87<>0,I87<1),H87/(1-I87),"") | K87: =IF(F87<>"",F87+G87,"") | L87: =IF(J87<>"",J87-K87,"") | M87: ='🏠 INICIO'!C8 -> 0.1 | N87: =IF(J87<>"",J87*M87,"") | O87: =IF(L87<>"",L87-N87,"")
B88: 83 | H88: =IF(F88<>"",F88+G88,"") | J88: =IF(AND(H88<>"",I88<>0,I88<1),H88/(1-I88),"") | K88: =IF(F88<>"",F88+G88,"") | L88: =IF(J88<>"",J88-K88,"") | M88: ='🏠 INICIO'!C8 -> 0.1 | N88: =IF(J88<>"",J88*M88,"") | O88: =IF(L88<>"",L88-N88,"")
B89: 84 | H89: =IF(F89<>"",F89+G89,"") | J89: =IF(AND(H89<>"",I89<>0,I89<1),H89/(1-I89),"") | K89: =IF(F89<>"",F89+G89,"") | L89: =IF(J89<>"",J89-K89,"") | M89: ='🏠 INICIO'!C8 -> 0.1 | N89: =IF(J89<>"",J89*M89,"") | O89: =IF(L89<>"",L89-N89,"")
B90: 85 | H90: =IF(F90<>"",F90+G90,"") | J90: =IF(AND(H90<>"",I90<>0,I90<1),H90/(1-I90),"") | K90: =IF(F90<>"",F90+G90,"") | L90: =IF(J90<>"",J90-K90,"") | M90: ='🏠 INICIO'!C8 -> 0.1 | N90: =IF(J90<>"",J90*M90,"") | O90: =IF(L90<>"",L90-N90,"")
B91: 86 | H91: =IF(F91<>"",F91+G91,"") | J91: =IF(AND(H91<>"",I91<>0,I91<1),H91/(1-I91),"") | K91: =IF(F91<>"",F91+G91,"") | L91: =IF(J91<>"",J91-K91,"") | M91: ='🏠 INICIO'!C8 -> 0.1 | N91: =IF(J91<>"",J91*M91,"") | O91: =IF(L91<>"",L91-N91,"")
B92: 87 | H92: =IF(F92<>"",F92+G92,"") | J92: =IF(AND(H92<>"",I92<>0,I92<1),H92/(1-I92),"") | K92: =IF(F92<>"",F92+G92,"") | L92: =IF(J92<>"",J92-K92,"") | M92: ='🏠 INICIO'!C8 -> 0.1 | N92: =IF(J92<>"",J92*M92,"") | O92: =IF(L92<>"",L92-N92,"")
B93: 88 | H93: =IF(F93<>"",F93+G93,"") | J93: =IF(AND(H93<>"",I93<>0,I93<1),H93/(1-I93),"") | K93: =IF(F93<>"",F93+G93,"") | L93: =IF(J93<>"",J93-K93,"") | M93: ='🏠 INICIO'!C8 -> 0.1 | N93: =IF(J93<>"",J93*M93,"") | O93: =IF(L93<>"",L93-N93,"")
B94: 89 | H94: =IF(F94<>"",F94+G94,"") | J94: =IF(AND(H94<>"",I94<>0,I94<1),H94/(1-I94),"") | K94: =IF(F94<>"",F94+G94,"") | L94: =IF(J94<>"",J94-K94,"") | M94: ='🏠 INICIO'!C8 -> 0.1 | N94: =IF(J94<>"",J94*M94,"") | O94: =IF(L94<>"",L94-N94,"")
B95: 90 | H95: =IF(F95<>"",F95+G95,"") | J95: =IF(AND(H95<>"",I95<>0,I95<1),H95/(1-I95),"") | K95: =IF(F95<>"",F95+G95,"") | L95: =IF(J95<>"",J95-K95,"") | M95: ='🏠 INICIO'!C8 -> 0.1 | N95: =IF(J95<>"",J95*M95,"") | O95: =IF(L95<>"",L95-N95,"")
B96: 91 | H96: =IF(F96<>"",F96+G96,"") | J96: =IF(AND(H96<>"",I96<>0,I96<1),H96/(1-I96),"") | K96: =IF(F96<>"",F96+G96,"") | L96: =IF(J96<>"",J96-K96,"") | M96: ='🏠 INICIO'!C8 -> 0.1 | N96: =IF(J96<>"",J96*M96,"") | O96: =IF(L96<>"",L96-N96,"")
B97: 92 | H97: =IF(F97<>"",F97+G97,"") | J97: =IF(AND(H97<>"",I97<>0,I97<1),H97/(1-I97),"") | K97: =IF(F97<>"",F97+G97,"") | L97: =IF(J97<>"",J97-K97,"") | M97: ='🏠 INICIO'!C8 -> 0.1 | N97: =IF(J97<>"",J97*M97,"") | O97: =IF(L97<>"",L97-N97,"")
B98: 93 | H98: =IF(F98<>"",F98+G98,"") | J98: =IF(AND(H98<>"",I98<>0,I98<1),H98/(1-I98),"") | K98: =IF(F98<>"",F98+G98,"") | L98: =IF(J98<>"",J98-K98,"") | M98: ='🏠 INICIO'!C8 -> 0.1 | N98: =IF(J98<>"",J98*M98,"") | O98: =IF(L98<>"",L98-N98,"")
B99: 94 | H99: =IF(F99<>"",F99+G99,"") | J99: =IF(AND(H99<>"",I99<>0,I99<1),H99/(1-I99),"") | K99: =IF(F99<>"",F99+G99,"") | L99: =IF(J99<>"",J99-K99,"") | M99: ='🏠 INICIO'!C8 -> 0.1 | N99: =IF(J99<>"",J99*M99,"") | O99: =IF(L99<>"",L99-N99,"")
B100: 95 | H100: =IF(F100<>"",F100+G100,"") | J100: =IF(AND(H100<>"",I100<>0,I100<1),H100/(1-I100),"") | K100: =IF(F100<>"",F100+G100,"") | L100: =IF(J100<>"",J100-K100,"") | M100: ='🏠 INICIO'!C8 -> 0.1 | N100: =IF(J100<>"",J100*M100,"") | O100: =IF(L100<>"",L100-N100,"")
B101: 96 | H101: =IF(F101<>"",F101+G101,"") | J101: =IF(AND(H101<>"",I101<>0,I101<1),H101/(1-I101),"") | K101: =IF(F101<>"",F101+G101,"") | L101: =IF(J101<>"",J101-K101,"") | M101: ='🏠 INICIO'!C8 -> 0.1 | N101: =IF(J101<>"",J101*M101,"") | O101: =IF(L101<>"",L101-N101,"")
...

Sheet 💵 CUANTO ME PAGO
B1: 💵 ¿CUÁNTO ME PAGO? — Tu Sueldo Real y Rentabilidad del Negocio
B2: 🎯 Revisa esta hoja al cerrar cada campaña. Aquí sabes si tu negocio te paga bien o solo estás trabajando gratis.
G3: ='📊 CALCULADORA CAMPAÑA'!O113 -> 0
B4: 📥 PASO 1: Ingresa los ingresos de tu campaña | F4: 🚦 ¿Es rentable tu negocio este mes?
B5: 💰 Total ventas cobradas (S/) | C5: 1500 | D5: ← ingresa el total cobrado en la campaña | F5: 🟢 Ganancia bruta > S/ 300 | G5: =IF(C21>=300,"✅ ¡Excelente campaña!","") -> ✅ ¡Excelente campaña!
B6: 💸 Comisión a vendedoras (10%) — se descuenta en gastos ↓ | C6: =ROUND(C5*0.1,2) -> 150 | D6: ← referencia — el descuento real está en Paso 2 | F6: 🟡 Ganancia bruta entre S/ 100 y S/ 299 | G6: =IF(AND(C21>=100,C21<300),"⚠️ Campaña regular, puedes mejorar","")
B7: ➕ Otros ingresos (bonos, etc.) | C7: 0 | D7: ← ingresa el total real de la campaña | F7: 🔴 Ganancia bruta < S/ 100 | G7: =IF(C21<100,"🚨 Ojo: casi no ganaste. Revisa tus precios","")
B8: 📊 TOTAL INGRESOS CAMPAÑA | C8: =C5+C7 -> 1500
F9: 🎯 Meta de sueldo mensual
B10: 📤 PASO 2: ¿Cuánto gastaste para vender? | F10: ¿Cuánto quieres ganar este mes? (S/) | G10: 750 | H10: ← ingresa tu meta
B11: 📦 Costo de productos (lo que le pagaste al catálogo) | C11: 600 | F11: Ventas necesarias para llegar a tu meta: | G11: =IF(AND(C5>0,C18>0),(G10/(C5-C18))*C5,"Llena los datos") -> 1500
B12: 💸 Comisión pagada a vendedoras (10%) | C12: =C6 -> 150 | D12: ← lo que le pagas a tu vendedora por vender
B13: 🚚 Delivery / envíos pagados | C13: 0 | F13: ¿Llegaste a tu meta este mes? | G13: =IF(C25>=G10,"✅ ¡Sí! Meta cumplida 🎉","❌ Aún no. Faltan S/ "&TEXT(G10-C25,"#,##0.00")) -> ❌ Aún no. Faltan S/ 375,000
B14: 📣 Publicidad (Redes, Impresiones) | C14: 0
B15: 📱 Internet / celular (parte del negocio) | C15: 0 | F15: 🏗️ Mis costos fijos mensuales
B16: 🛍️ Empaque y materiales | C16: 0 | F16: 💡 Luz / internet / celular | G16: 50
B17: 📋 Otros gastos del negocio | C17: 0 | F17: 📣 Publicidad mensual | G17: 100
B18: 📊 TOTAL GASTOS CAMPAÑA | C18: =SUM(C11:C17) -> 750 | F18: 🛍️ Empaque promedio mensual | G18: 30
F19: 📋 Otros costos fijos | G19: 0
B20: 🧮 PASO 3: ¿Cómo distribuir lo que te queda? | F20: 💸 TOTAL COSTOS FIJOS / MES: | G20: =SUM(G15:G18) -> 180
B21: 💵 Ganancia bruta (ventas − costos − comisión vendedora): | C21: =C8-C18 -> 750 | D21: Siempre se recomienda llegar o traspasar tu meta | F21: ⚡ Costo fijo por producto (aprox): | G21: =IF(C3<>0,G19/C3,"Llena productos") -> Llena productos
B22: 💡 Esta es tu ganancia REAL como dueña, ya descontando el pago a vendedoras. | F22: #VALUE!
B23: 🔁 Para reinvertir en próxima campaña (30%) | C23: =IF(C21>0,C21*0.3,0) -> 225
B24: 🛡️ Para fondo de emergencia / ahorro (20%) | C24: =IF(C21>0,C21*0.2,0) -> 150
B25: 💵 TU SUELDO como dueña — lo que te llevas (50%) | C25: =IF(C21>0,C21*0.5,0) -> 375
B27: 💡 Nota: Los % son una guía de referencia. Puedes ajustarlos según tu situación.

Sheet 🗂️ MONITOREO CATÁLOGOS
A1: 🗂️ MONITOREO DE CATÁLOGOS — RESULTADO POR CAMPAÑA | P1: #VALUE!
B2: I | D2: ingresa por cada catálogo: tu factura del mes, total de ventas, campaña. El sistema calcula ganancia real, comisión y reinversión.
C3: % COMISIÓN (editable en INICIO): | E3: ='🏠 INICIO'!D23 -> 0 | F3: ← Cámbialo en hoja INICIO
B4: 🔵 Ingresa tú | E4: ⚫ Calculado auto | H4: 🟡 % comisión | K4: 🟢 Ganancia
B6: 📌 YANBAL | K6: 📌 ESIKA
B7: CAMPAÑA N° | C7: MES | D7: 💰 MI FACTURA (lo que debo pagar) | E7: 📦 MIS VENTAS TOTALES (S/) | F7: 💵 GANANCIA BRUTA (S/) | G7: 🏆 COMISIÓN SEGÚN % | H7: ♻️ PARA REINVERTIR | I7: ✅ GANANCIA NETA REAL | K7: CAMPAÑA N° | L7: MES | M7: 💰 MI FACTURA (lo que debo pagar) | N7: 📦 MIS VENTAS TOTALES (S/) | O7: 💵 GANANCIA BRUTA (S/) | P7: 🏆 COMISIÓN SEGÚN % | Q7: ♻️ PARA REINVERTIR | R7: ✅ GANANCIA NETA REAL
B8: 1 | C8: ENERO | D8: 420 | E8: 650 | F8: =IFERROR(IF(E8="","",E8-D8),"") -> 230 | G8: =IFERROR(IF(E8="","",E8*$E$3),"") -> 0 | H8: =IFERROR(IF(D8="","",D8*0.5),"") -> 210 | I8: =IFERROR(IF(F8="","",F8-G8),"") -> 230 | K8: 1 | L8: ENERO | M8: 280 | N8: 435 | O8: =IFERROR(IF(N8="","",N8-M8),"") -> 155 | P8: =IFERROR(IF(N8="","",N8*$E$3),"") -> 0 | Q8: =IFERROR(IF(M8="","",M8*0.5),"") -> 140 | R8: =IFERROR(IF(O8="","",O8-P8),"") -> 155
B9: 2 | C9: FEBRERO | D9: 380 | E9: 590 | F9: =IFERROR(IF(E9="","",E9-D9),"") -> 210 | G9: =IFERROR(IF(E9="","",E9*$E$3),"") -> 0 | H9: =IFERROR(IF(D9="","",D9*0.5),"") -> 190 | I9: =IFERROR(IF(F9="","",F9-G9),"") -> 210 | K9: 2 | L9: FEBRERO | M9: 310 | N9: 480 | O9: =IFERROR(IF(N9="","",N9-M9),"") -> 170 | P9: =IFERROR(IF(N9="","",N9*$E$3),"") -> 0 | Q9: =IFERROR(IF(M9="","",M9*0.5),"") -> 155 | R9: =IFERROR(IF(O9="","",O9-P9),"") -> 170
B10: 3 | C10: MARZO | D10: 510 | E10: 790 | F10: =IFERROR(IF(E10="","",E10-D10),"") -> 280 | G10: =IFERROR(IF(E10="","",E10*$E$3),"") -> 0 | H10: =IFERROR(IF(D10="","",D10*0.5),"") -> 255 | I10: =IFERROR(IF(F10="","",F10-G10),"") -> 280 | K10: 3 | L10: MARZO | M10: 265 | N10: 410 | O10: =IFERROR(IF(N10="","",N10-M10),"") -> 145 | P10: =IFERROR(IF(N10="","",N10*$E$3),"") -> 0 | Q10: =IFERROR(IF(M10="","",M10*0.5),"") -> 132.5 | R10: =IFERROR(IF(O10="","",O10-P10),"") -> 145
B11: 4 | C11: ABRIL | D11: 460 | E11: 720 | F11: =IFERROR(IF(E11="","",E11-D11),"") -> 260 | G11: =IFERROR(IF(E11="","",E11*$E$3),"") -> 0 | H11: =IFERROR(IF(D11="","",D11*0.5),"") -> 230 | I11: =IFERROR(IF(F11="","",F11-G11),"") -> 260 | K11: 4 | L11: ABRIL | M11: 330 | N11: 510 | O11: =IFERROR(IF(N11="","",N11-M11),"") -> 180 | P11: =IFERROR(IF(N11="","",N11*$E$3),"") -> 0 | Q11: =IFERROR(IF(M11="","",M11*0.5),"") -> 165 | R11: =IFERROR(IF(O11="","",O11-P11),"") -> 180
B12: 5 | C12: MAYO | D12: 395 | E12: 615 | F12: =IFERROR(IF(E12="","",E12-D12),"") -> 220 | G12: =IFERROR(IF(E12="","",E12*$E$3),"") -> 0 | H12: =IFERROR(IF(D12="","",D12*0.5),"") -> 197.5 | I12: =IFERROR(IF(F12="","",F12-G12),"") -> 220 | K12: 5 | L12: MAYO | M12: 295 | N12: 460 | O12: =IFERROR(IF(N12="","",N12-M12),"") -> 165 | P12: =IFERROR(IF(N12="","",N12*$E$3),"") -> 0 | Q12: =IFERROR(IF(M12="","",M12*0.5),"") -> 147.5 | R12: =IFERROR(IF(O12="","",O12-P12),"") -> 165
B13: 6 | C13: JUNIO | D13: 480 | E13: 745 | F13: =IFERROR(IF(E13="","",E13-D13),"") -> 265 | G13: =IFERROR(IF(E13="","",E13*$E$3),"") -> 0 | H13: =IFERROR(IF(D13="","",D13*0.5),"") -> 240 | I13: =IFERROR(IF(F13="","",F13-G13),"") -> 265 | K13: 6 | L13: JUNIO | M13: 350 | N13: 540 | O13: =IFERROR(IF(N13="","",N13-M13),"") -> 190 | P13: =IFERROR(IF(N13="","",N13*$E$3),"") -> 0 | Q13: =IFERROR(IF(M13="","",M13*0.5),"") -> 175 | R13: =IFERROR(IF(O13="","",O13-P13),"") -> 190
B14: 7 | F14: =IFERROR(IF(E14="","",E14-D14),"") | G14: =IFERROR(IF(E14="","",E14*$E$3),"") | H14: =IFERROR(IF(D14="","",D14*0.5),"") | I14: =IFERROR(IF(F14="","",F14-G14),"") | K14: 7 | O14: =IFERROR(IF(N14="","",N14-M14),"") | P14: =IFERROR(IF(N14="","",N14*$E$3),"") | Q14: =IFERROR(IF(M14="","",M14*0.5),"") | R14: =IFERROR(IF(O14="","",O14-P14),"")
B15: 1 | F15: =IFERROR(IF(E15="","",E15-D15),"") | G15: =IFERROR(IF(E15="","",E15*$E$3),"") | H15: =IFERROR(IF(D15="","",D15*0.5),"") | I15: =IFERROR(IF(F15="","",F15-G15),"") | K15: 8 | O15: =IFERROR(IF(N15="","",N15-M15),"") | P15: =IFERROR(IF(N15="","",N15*$E$3),"") | Q15: =IFERROR(IF(M15="","",M15*0.5),"") | R15: =IFERROR(IF(O15="","",O15-P15),"")
B16: 2 | F16: =IFERROR(IF(E16="","",E16-D16),"") | G16: =IFERROR(IF(E16="","",E16*$E$3),"") | H16: =IFERROR(IF(D16="","",D16*0.5),"") | I16: =IFERROR(IF(F16="","",F16-G16),"") | K16: 9 | O16: =IFERROR(IF(N16="","",N16-M16),"") | P16: =IFERROR(IF(N16="","",N16*$E$3),"") | Q16: =IFERROR(IF(M16="","",M16*0.5),"") | R16: =IFERROR(IF(O16="","",O16-P16),"")
B17: 10 | F17: =IFERROR(IF(E17="","",E17-D17),"") | G17: =IFERROR(IF(E17="","",E17*$E$3),"") | H17: =IFERROR(IF(D17="","",D17*0.5),"") | I17: =IFERROR(IF(F17="","",F17-G17),"") | K17: 10 | O17: =IFERROR(IF(N17="","",N17-M17),"") | P17: =IFERROR(IF(N17="","",N17*$E$3),"") | Q17: =IFERROR(IF(M17="","",M17*0.5),"") | R17: =IFERROR(IF(O17="","",O17-P17),"")
B18: 11 | F18: =IFERROR(IF(E18="","",E18-D18),"") | G18: =IFERROR(IF(E18="","",E18*$E$3),"") | H18: =IFERROR(IF(D18="","",D18*0.5),"") | I18: =IFERROR(IF(F18="","",F18-G18),"") | K18: 11 | O18: =IFERROR(IF(N18="","",N18-M18),"") | P18: =IFERROR(IF(N18="","",N18*$E$3),"") | Q18: =IFERROR(IF(M18="","",M18*0.5),"") | R18: =IFERROR(IF(O18="","",O18-P18),"")
B19: 12 | F19: =IFERROR(IF(E19="","",E19-D19),"") | G19: =IFERROR(IF(E19="","",E19*$E$3),"") | H19: =IFERROR(IF(D19="","",D19*0.5),"") | I19: =IFERROR(IF(F19="","",F19-G19),"") | K19: 12 | O19: =IFERROR(IF(N19="","",N19-M19),"") | P19: =IFERROR(IF(N19="","",N19*$E$3),"") | Q19: =IFERROR(IF(M19="","",M19*0.5),"") | R19: =IFERROR(IF(O19="","",O19-P19),"")
B20: 13 | F20: =IFERROR(IF(E20="","",E20-D20),"") | G20: =IFERROR(IF(E20="","",E20*$E$3),"") | H20: =IFERROR(IF(D20="","",D20*0.5),"") | I20: =IFERROR(IF(F20="","",F20-G20),"") | K20: 13 | O20: =IFERROR(IF(N20="","",N20-M20),"") | P20: =IFERROR(IF(N20="","",N20*$E$3),"") | Q20: =IFERROR(IF(M20="","",M20*0.5),"") | R20: =IFERROR(IF(O20="","",O20-P20),"")
B21: TOTAL | D21: =IFERROR(SUM(D8:D20),0) -> 2645 | E21: =IFERROR(SUM(E8:E20),0) -> 4110 | F21: =IFERROR(SUM(F8:F20),0) -> 1465 | G21: =IFERROR(SUM(G8:G20),0) -> 0 | H21: =IFERROR(SUM(H8:H20),0) -> 1322.5 | I21: =IFERROR(SUM(I8:I20),0) -> 1465 | K21: TOTAL | M21: =IFERROR(SUM(M8:M20),0) -> 1830 | N21: =IFERROR(SUM(N8:N20),0) -> 2835 | O21: =IFERROR(SUM(O8:O20),0) -> 1005 | P21: =IFERROR(SUM(P8:P20),0) -> 0 | Q21: =IFERROR(SUM(Q8:Q20),0) -> 915 | R21: =IFERROR(SUM(R8:R20),0) -> 1005
B22: 💡 Ganancia bruta = Ventas − Factura | Comisión = Ventas × % | Reinversión = 50% de Factura | Ganancia neta = Bruta − Comisión | K22: 💡 Ganancia bruta = Ventas − Factura | Comisión = Ventas × % | Reinversión = 50% de Factura | Ganancia neta = Bruta − Comisión
B24: 📌 CYZONE | K24: 📌 LBEL
B25: CAMPAÑA N° | C25: MES | D25: 💰 MI FACTURA (lo que debo pagar) | E25: 📦 MIS VENTAS TOTALES (S/) | F25: 💵 GANANCIA BRUTA (S/) | G25: 🏆 COMISIÓN SEGÚN % | H25: ♻️ PARA REINVERTIR | I25: ✅ GANANCIA NETA REAL | K25: CAMPAÑA N° | L25: MES | M25: 💰 MI FACTURA (lo que debo pagar) | N25: 📦 MIS VENTAS TOTALES (S/) | O25: 💵 GANANCIA BRUTA (S/) | P25: 🏆 COMISIÓN SEGÚN % | Q25: ♻️ PARA REINVERTIR | R25: ✅ GANANCIA NETA REAL
B26: 1 | C26: ENERO | D26: 150 | E26: 235 | F26: =IFERROR(IF(E26="","",E26-D26),"") -> 85 | G26: =IFERROR(IF(E26="","",E26*$E$3),"") -> 0 | H26: =IFERROR(IF(D26="","",D26*0.5),"") -> 75 | I26: =IFERROR(IF(F26="","",F26-G26),"") -> 85 | K26: 1 | L26: ENERO | M26: 120 | N26: 188 | O26: =IFERROR(IF(N26="","",N26-M26),"") -> 68 | P26: =IFERROR(IF(N26="","",N26*$E$3),"") -> 0 | Q26: =IFERROR(IF(M26="","",M26*0.5),"") -> 60 | R26: =IFERROR(IF(O26="","",O26-P26),"") -> 68
B27: 2 | C27: FEBRERO | D27: 180 | E27: 280 | F27: =IFERROR(IF(E27="","",E27-D27),"") -> 100 | G27: =IFERROR(IF(E27="","",E27*$E$3),"") -> 0 | H27: =IFERROR(IF(D27="","",D27*0.5),"") -> 90 | I27: =IFERROR(IF(F27="","",F27-G27),"") -> 100 | K27: 2 | L27: FEBRERO | M27: 145 | N27: 227 | O27: =IFERROR(IF(N27="","",N27-M27),"") -> 82 | P27: =IFERROR(IF(N27="","",N27*$E$3),"") -> 0 | Q27: =IFERROR(IF(M27="","",M27*0.5),"") -> 72.5 | R27: =IFERROR(IF(O27="","",O27-P27),"") -> 82
B28: 3 | C28: MARZO | D28: 165 | E28: 258 | F28: =IFERROR(IF(E28="","",E28-D28),"") -> 93 | G28: =IFERROR(IF(E28="","",E28*$E$3),"") -> 0 | H28: =IFERROR(IF(D28="","",D28*0.5),"") -> 82.5 | I28: =IFERROR(IF(F28="","",F28-G28),"") -> 93 | K28: 3 | L28: MARZO | M28: 130 | N28: 204 | O28: =IFERROR(IF(N28="","",N28-M28),"") -> 74 | P28: =IFERROR(IF(N28="","",N28*$E$3),"") -> 0 | Q28: =IFERROR(IF(M28="","",M28*0.5),"") -> 65 | R28: =IFERROR(IF(O28="","",O28-P28),"") -> 74
B29: 4 | C29: ABRIL | D29: 200 | E29: 312 | F29: =IFERROR(IF(E29="","",E29-D29),"") -> 112 | G29: =IFERROR(IF(E29="","",E29*$E$3),"") -> 0 | H29: =IFERROR(IF(D29="","",D29*0.5),"") -> 100 | I29: =IFERROR(IF(F29="","",F29-G29),"") -> 112 | K29: 4 | L29: ABRIL | M29: 160 | N29: 251 | O29: =IFERROR(IF(N29="","",N29-M29),"") -> 91 | P29: =IFERROR(IF(N29="","",N29*$E$3),"") -> 0 | Q29: =IFERROR(IF(M29="","",M29*0.5),"") -> 80 | R29: =IFERROR(IF(O29="","",O29-P29),"") -> 91
B30: 1 | C30: MAYO | D30: 175 | E30: 274 | F30: =IFERROR(IF(E30="","",E30-D30),"") -> 99 | G30: =IFERROR(IF(E30="","",E30*$E$3),"") -> 0 | H30: =IFERROR(IF(D30="","",D30*0.5),"") -> 87.5 | I30: =IFERROR(IF(F30="","",F30-G30),"") -> 99 | K30: 5 | L30: MAYO | M30: 135 | N30: 212 | O30: =IFERROR(IF(N30="","",N30-M30),"") -> 77 | P30: =IFERROR(IF(N30="","",N30*$E$3),"") -> 0 | Q30: =IFERROR(IF(M30="","",M30*0.5),"") -> 67.5 | R30: =IFERROR(IF(O30="","",O30-P30),"") -> 77
B31: 6 | C31: JUNIO | D31: 210 | E31: 328 | F31: =IFERROR(IF(E31="","",E31-D31),"") -> 118 | G31: =IFERROR(IF(E31="","",E31*$E$3),"") -> 0 | H31: =IFERROR(IF(D31="","",D31*0.5),"") -> 105 | I31: =IFERROR(IF(F31="","",F31-G31),"") -> 118 | K31: 6 | L31: JUNIO | M31: 155 | N31: 243 | O31: =IFERROR(IF(N31="","",N31-M31),"") -> 88 | P31: =IFERROR(IF(N31="","",N31*$E$3),"") -> 0 | Q31: =IFERROR(IF(M31="","",M31*0.5),"") -> 77.5 | R31: =IFERROR(IF(O31="","",O31-P31),"") -> 88
B32: 7 | F32: =IFERROR(IF(E32="","",E32-D32),"") | G32: =IFERROR(IF(E32="","",E32*$E$3),"") | H32: =IFERROR(IF(D32="","",D32*0.5),"") | I32: =IFERROR(IF(F32="","",F32-G32),"") | K32: 7 | O32: =IFERROR(IF(N32="","",N32-M32),"") | P32: =IFERROR(IF(N32="","",N32*$E$3),"") | Q32: =IFERROR(IF(M32="","",M32*0.5),"") | R32: =IFERROR(IF(O32="","",O32-P32),"")
B33: 8 | F33: =IFERROR(IF(E33="","",E33-D33),"") | G33: =IFERROR(IF(E33="","",E33*$E$3),"") | H33: =IFERROR(IF(D33="","",D33*0.5),"") | I33: =IFERROR(IF(F33="","",F33-G33),"") | K33: 8 | O33: =IFERROR(IF(N33="","",N33-M33),"") | P33: =IFERROR(IF(N33="","",N33*$E$3),"") | Q33: =IFERROR(IF(M33="","",M33*0.5),"") | R33: =IFERROR(IF(O33="","",O33-P33),"")
B34: 9 | F34: =IFERROR(IF(E34="","",E34-D34),"") | G34: =IFERROR(IF(E34="","",E34*$E$3),"") | H34: =IFERROR(IF(D34="","",D34*0.5),"") | I34: =IFERROR(IF(F34="","",F34-G34),"") | K34: 9 | O34: =IFERROR(IF(N34="","",N34-M34),"") | P34: =IFERROR(IF(N34="","",N34*$E$3),"") | Q34: =IFERROR(IF(M34="","",M34*0.5),"") | R34: =IFERROR(IF(O34="","",O34-P34),"")
B35: 10 | F35: =IFERROR(IF(E35="","",E35-D35),"") | G35: =IFERROR(IF(E35="","",E35*$E$3),"") | H35: =IFERROR(IF(D35="","",D35*0.5),"") | I35: =IFERROR(IF(F35="","",F35-G35),"") | K35: 10 | O35: =IFERROR(IF(N35="","",N35-M35),"") | P35: =IFERROR(IF(N35="","",N35*$E$3),"") | Q35: =IFERROR(IF(M35="","",M35*0.5),"") | R35: =IFERROR(IF(O35="","",O35-P35),"")
B36: 11 | F36: =IFERROR(IF(E36="","",E36-D36),"") | G36: =IFERROR(IF(E36="","",E36*$E$3),"") | H36: =IFERROR(IF(D36="","",D36*0.5),"") | I36: =IFERROR(IF(F36="","",F36-G36),"") | K36: 11 | O36: =IFERROR(IF(N36="","",N36-M36),"") | P36: =IFERROR(IF(N36="","",N36*$E$3),"") | Q36: =IFERROR(IF(M36="","",M36*0.5),"") | R36: =IFERROR(IF(O36="","",O36-P36),"")
B37: 12 | F37: =IFERROR(IF(E37="","",E37-D37),"") | G37: =IFERROR(IF(E37="","",E37*$E$3),"") | H37: =IFERROR(IF(D37="","",D37*0.5),"") | I37: =IFERROR(IF(F37="","",F37-G37),"") | K37: 12 | O37: =IFERROR(IF(N37="","",N37-M37),"") | P37: =IFERROR(IF(N37="","",N37*$E$3),"") | Q37: =IFERROR(IF(M37="","",M37*0.5),"") | R37: =IFERROR(IF(O37="","",O37-P37),"")
B38: 13 | F38: =IFERROR(IF(E38="","",E38-D38),"") | G38: =IFERROR(IF(E38="","",E38*$E$3),"") | H38: =IFERROR(IF(D38="","",D38*0.5),"") | I38: =IFERROR(IF(F38="","",F38-G38),"") | K38: 13 | O38: =IFERROR(IF(N38="","",N38-M38),"") | P38: =IFERROR(IF(N38="","",N38*$E$3),"") | Q38: =IFERROR(IF(M38="","",M38*0.5),"") | R38: =IFERROR(IF(O38="","",O38-P38),"")
B39: TOTAL | D39: =IFERROR(SUM(D26:D38),0) -> 1080 | E39: =IFERROR(SUM(E26:E38),0) -> 1687 | F39: =IFERROR(SUM(F26:F38),0) -> 607 | G39: =IFERROR(SUM(G26:G38),0) -> 0 | H39: =IFERROR(SUM(H26:H38),0) -> 540 | I39: =IFERROR(SUM(I26:I38),0) -> 607 | K39: TOTAL | M39: =IFERROR(SUM(M26:M38),0) -> 845 | N39: =IFERROR(SUM(N26:N38),0) -> 1325 | O39: =IFERROR(SUM(O26:O38),0) -> 480 | P39: =IFERROR(SUM(P26:P38),0) -> 0 | Q39: =IFERROR(SUM(Q26:Q38),0) -> 422.5 | R39: =IFERROR(SUM(R26:R38),0) -> 480
B40: 💡 Ganancia bruta = Ventas − Factura | Comisión = Ventas × % | Reinversión = 50% de Factura | Ganancia neta = Bruta − Comisión | K40: 💡 Ganancia bruta = Ventas − Factura | Comisión = Ventas × % | Reinversión = 50% de Factura | Ganancia neta = Bruta − Comisión
B42: 📌 NATURA | K42: 📌 AVON
B43: CAMPAÑA N° | C43: MES | D43: 💰 MI FACTURA (lo que debo pagar) | E43: 📦 MIS VENTAS TOTALES (S/) | F43: 💵 GANANCIA BRUTA (S/) | G43: 🏆 COMISIÓN SEGÚN % | H43: ♻️ PARA REINVERTIR | I43: ✅ GANANCIA NETA REAL | K43: CAMPAÑA N° | L43: MES | M43: 💰 MI FACTURA (lo que debo pagar) | N43: 📦 MIS VENTAS TOTALES (S/) | O43: 💵 GANANCIA BRUTA (S/) | P43: 🏆 COMISIÓN SEGÚN % | Q43: ♻️ PARA REINVERTIR | R43: ✅ GANANCIA NETA REAL
B44: 1 | C44: ENERO | D44: 200 | E44: 312 | F44: =IFERROR(IF(E44="","",E44-D44),"") -> 112 | G44: =IFERROR(IF(E44="","",E44*$E$3),"") -> 0 | H44: =IFERROR(IF(D44="","",D44*0.5),"") -> 100 | I44: =IFERROR(IF(F44="","",F44-G44),"") -> 112 | K44: 1 | L44: ENERO | M44: 160 | N44: 250 | O44: =IFERROR(IF(N44="","",N44-M44),"") -> 90 | P44: =IFERROR(IF(N44="","",N44*$E$3),"") -> 0 | Q44: =IFERROR(IF(M44="","",M44*0.5),"") -> 80 | R44: =IFERROR(IF(O44="","",O44-P44),"") -> 90
B45: 2 | C45: FEBRERO | D45: 225 | E45: 351 | F45: =IFERROR(IF(E45="","",E45-D45),"") -> 126 | G45: =IFERROR(IF(E45="","",E45*$E$3),"") -> 0 | H45: =IFERROR(IF(D45="","",D45*0.5),"") -> 112.5 | I45: =IFERROR(IF(F45="","",F45-G45),"") -> 126 | K45: 2 | L45: FEBRERO | M45: 175 | N45: 273 | O45: =IFERROR(IF(N45="","",N45-M45),"") -> 98 | P45: =IFERROR(IF(N45="","",N45*$E$3),"") -> 0 | Q45: =IFERROR(IF(M45="","",M45*0.5),"") -> 87.5 | R45: =IFERROR(IF(O45="","",O45-P45),"") -> 98
B46: 3 | C46: MARZO | D46: 185 | E46: 289 | F46: =IFERROR(IF(E46="","",E46-D46),"") -> 104 | G46: =IFERROR(IF(E46="","",E46*$E$3),"") -> 0 | H46: =IFERROR(IF(D46="","",D46*0.5),"") -> 92.5 | I46: =IFERROR(IF(F46="","",F46-G46),"") -> 104 | K46: 3 | L46: MARZO | M46: 145 | N46: 226 | O46: =IFERROR(IF(N46="","",N46-M46),"") -> 81 | P46: =IFERROR(IF(N46="","",N46*$E$3),"") -> 0 | Q46: =IFERROR(IF(M46="","",M46*0.5),"") -> 72.5 | R46: =IFERROR(IF(O46="","",O46-P46),"") -> 81
B47: 4 | C47: ABRIL | D47: 240 | E47: 375 | F47: =IFERROR(IF(E47="","",E47-D47),"") -> 135 | G47: =IFERROR(IF(E47="","",E47*$E$3),"") -> 0 | H47: =IFERROR(IF(D47="","",D47*0.5),"") -> 120 | I47: =IFERROR(IF(F47="","",F47-G47),"") -> 135 | K47: 4 | L47: ABRIL | M47: 190 | N47: 297 | O47: =IFERROR(IF(N47="","",N47-M47),"") -> 107 | P47: =IFERROR(IF(N47="","",N47*$E$3),"") -> 0 | Q47: =IFERROR(IF(M47="","",M47*0.5),"") -> 95 | R47: =IFERROR(IF(O47="","",O47-P47),"") -> 107
B48: 5 | C48: MAYO | D48: 210 | E48: 328 | F48: =IFERROR(IF(E48="","",E48-D48),"") -> 118 | G48: =IFERROR(IF(E48="","",E48*$E$3),"") -> 0 | H48: =IFERROR(IF(D48="","",D48*0.5),"") -> 105 | I48: =IFERROR(IF(F48="","",F48-G48),"") -> 118 | K48: 5 | L48: MAYO | M48: 165 | N48: 258 | O48: =IFERROR(IF(N48="","",N48-M48),"") -> 93 | P48: =IFERROR(IF(N48="","",N48*$E$3),"") -> 0 | Q48: =IFERROR(IF(M48="","",M48*0.5),"") -> 82.5 | R48: =IFERROR(IF(O48="","",O48-P48),"") -> 93
B49: 6 | C49: JUNIO | D49: 255 | E49: 398 | F49: =IFERROR(IF(E49="","",E49-D49),"") -> 143 | G49: =IFERROR(IF(E49="","",E49*$E$3),"") -> 0 | H49: =IFERROR(IF(D49="","",D49*0.5),"") -> 127.5 | I49: =IFERROR(IF(F49="","",F49-G49),"") -> 143 | K49: 6 | L49: JUNIO | M49: 200 | N49: 312 | O49: =IFERROR(IF(N49="","",N49-M49),"") -> 112 | P49: =IFERROR(IF(N49="","",N49*$E$3),"") -> 0 | Q49: =IFERROR(IF(M49="","",M49*0.5),"") -> 100 | R49: =IFERROR(IF(O49="","",O49-P49),"") -> 112
B50: 7 | F50: =IFERROR(IF(E50="","",E50-D50),"") | G50: =IFERROR(IF(E50="","",E50*$E$3),"") | H50: =IFERROR(IF(D50="","",D50*0.5),"") | I50: =IFERROR(IF(F50="","",F50-G50),"") | K50: 7 | O50: =IFERROR(IF(N50="","",N50-M50),"") | P50: =IFERROR(IF(N50="","",N50*$E$3),"") | Q50: =IFERROR(IF(M50="","",M50*0.5),"") | R50: =IFERROR(IF(O50="","",O50-P50),"")
B51: 8 | F51: =IFERROR(IF(E51="","",E51-D51),"") | G51: =IFERROR(IF(E51="","",E51*$E$3),"") | H51: =IFERROR(IF(D51="","",D51*0.5),"") | I51: =IFERROR(IF(F51="","",F51-G51),"") | K51: 8 | O51: =IFERROR(IF(N51="","",N51-M51),"") | P51: =IFERROR(IF(N51="","",N51*$E$3),"") | Q51: =IFERROR(IF(M51="","",M51*0.5),"") | R51: =IFERROR(IF(O51="","",O51-P51),"")
B52: 9 | F52: =IFERROR(IF(E52="","",E52-D52),"") | G52: =IFERROR(IF(E52="","",E52*$E$3),"") | H52: =IFERROR(IF(D52="","",D52*0.5),"") | I52: =IFERROR(IF(F52="","",F52-G52),"") | K52: 9 | O52: =IFERROR(IF(N52="","",N52-M52),"") | P52: =IFERROR(IF(N52="","",N52*$E$3),"") | Q52: =IFERROR(IF(M52="","",M52*0.5),"") | R52: =IFERROR(IF(O52="","",O52-P52),"")
B53: 10 | F53: =IFERROR(IF(E53="","",E53-D53),"") | G53: =IFERROR(IF(E53="","",E53*$E$3),"") | H53: =IFERROR(IF(D53="","",D53*0.5),"") | I53: =IFERROR(IF(F53="","",F53-G53),"") | K53: 10 | O53: =IFERROR(IF(N53="","",N53-M53),"") | P53: =IFERROR(IF(N53="","",N53*$E$3),"") | Q53: =IFERROR(IF(M53="","",M53*0.5),"") | R53: =IFERROR(IF(O53="","",O53-P53),"")
B54: 11 | F54: =IFERROR(IF(E54="","",E54-D54),"") | G54: =IFERROR(IF(E54="","",E54*$E$3),"") | H54: =IFERROR(IF(D54="","",D54*0.5),"") | I54: =IFERROR(IF(F54="","",F54-G54),"") | K54: 11 | O54: =IFERROR(IF(N54="","",N54-M54),"") | P54: =IFERROR(IF(N54="","",N54*$E$3),"") | Q54: =IFERROR(IF(M54="","",M54*0.5),"") | R54: =IFERROR(IF(O54="","",O54-P54),"")
B55: 12 | F55: =IFERROR(IF(E55="","",E55-D55),"") | G55: =IFERROR(IF(E55="","",E55*$E$3),"") | H55: =IFERROR(IF(D55="","",D55*0.5),"") | I55: =IFERROR(IF(F55="","",F55-G55),"") | K55: 12 | O55: =IFERROR(IF(N55="","",N55-M55),"") | P55: =IFERROR(IF(N55="","",N55*$E$3),"") | Q55: =IFERROR(IF(M55="","",M55*0.5),"") | R55: =IFERROR(IF(O55="","",O55-P55),"")
B56: 13 | F56: =IFERROR(IF(E56="","",E56-D56),"") | G56: =IFERROR(IF(E56="","",E56*$E$3),"") | H56: =IFERROR(IF(D56="","",D56*0.5),"") | I56: =IFERROR(IF(F56="","",F56-G56),"") | K56: 13 | O56: =IFERROR(IF(N56="","",N56-M56),"") | P56: =IFERROR(IF(N56="","",N56*$E$3),"") | Q56: =IFERROR(IF(M56="","",M56*0.5),"") | R56: =IFERROR(IF(O56="","",O56-P56),"")
B57: TOTAL | D57: =IFERROR(SUM(D44:D56),0) -> 1315 | E57: =IFERROR(SUM(E44:E56),0) -> 2053 | F57: =IFERROR(SUM(F44:F56),0) -> 738 | G57: =IFERROR(SUM(G44:G56),0) -> 0 | H57: =IFERROR(SUM(H44:H56),0) -> 657.5 | I57: =IFERROR(SUM(I44:I56),0) -> 738 | K57: TOTAL | M57: =IFERROR(SUM(M44:M56),0) -> 1035 | N57: =IFERROR(SUM(N44:N56),0) -> 1616 | O57: =IFERROR(SUM(O44:O56),0) -> 581 | P57: =IFERROR(SUM(P44:P56),0) -> 0 | Q57: =IFERROR(SUM(Q44:Q56),0) -> 517.5 | R57: =IFERROR(SUM(R44:R56),0) -> 581
B58: 💡 Ganancia bruta = Ventas − Factura | Comisión = Ventas × % | Reinversión = 50% de Factura | Ganancia neta = Bruta − Comisión | K58: 💡 Ganancia bruta = Ventas − Factura | Comisión = Ventas × % | Reinversión = 50% de Factura | Ganancia neta = Bruta − Comisión
B60: 📌 FARMASI | K60: 📌 ORIFLAME
B61: CAMPAÑA N° | C61: MES | D61: 💰 MI FACTURA (lo que debo pagar) | E61: 📦 MIS VENTAS TOTALES (S/) | F61: 💵 GANANCIA BRUTA (S/) | G61: 🏆 COMISIÓN SEGÚN % | H61: ♻️ PARA REINVERTIR | I61: ✅ GANANCIA NETA REAL | K61: CAMPAÑA N° | L61: MES | M61: 💰 MI FACTURA (lo que debo pagar) | N61: 📦 MIS VENTAS TOTALES (S/) | O61: 💵 GANANCIA BRUTA (S/) | P61: 🏆 COMISIÓN SEGÚN % | Q61: ♻️ PARA REINVERTIR | R61: ✅ GANANCIA NETA REAL
B62: 1 | C62: ENERO | D62: 80 | E62: 125 | F62: =IFERROR(IF(E62="","",E62-D62),"") -> 45 | G62: =IFERROR(IF(E62="","",E62*$E$3),"") -> 0 | H62: =IFERROR(IF(D62="","",D62*0.5),"") -> 40 | I62: =IFERROR(IF(F62="","",F62-G62),"") -> 45 | K62: 1 | L62: ENERO | M62: 250 | N62: 390 | O62: =IFERROR(IF(N62="","",N62-M62),"") -> 140 | P62: =IFERROR(IF(N62="","",N62*$E$3),"") -> 0 | Q62: =IFERROR(IF(M62="","",M62*0.5),"") -> 125 | R62: =IFERROR(IF(O62="","",O62-P62),"") -> 140
B63: 2 | C63: FEBRERO | D63: 95 | E63: 148 | F63: =IFERROR(IF(E63="","",E63-D63),"") -> 53 | G63: =IFERROR(IF(E63="","",E63*$E$3),"") -> 0 | H63: =IFERROR(IF(D63="","",D63*0.5),"") -> 47.5 | I63: =IFERROR(IF(F63="","",F63-G63),"") -> 53 | K63: 2 | L63: FEBRERO | M63: 280 | N63: 437 | O63: =IFERROR(IF(N63="","",N63-M63),"") -> 157 | P63: =IFERROR(IF(N63="","",N63*$E$3),"") -> 0 | Q63: =IFERROR(IF(M63="","",M63*0.5),"") -> 140 | R63: =IFERROR(IF(O63="","",O63-P63),"") -> 157
B64: 3 | C64: MARZO | D64: 75 | E64: 117 | F64: =IFERROR(IF(E64="","",E64-D64),"") -> 42 | G64: =IFERROR(IF(E64="","",E64*$E$3),"") -> 0 | H64: =IFERROR(IF(D64="","",D64*0.5),"") -> 37.5 | I64: =IFERROR(IF(F64="","",F64-G64),"") -> 42 | K64: 3 | L64: MARZO | M64: 265 | N64: 413 | O64: =IFERROR(IF(N64="","",N64-M64),"") -> 148 | P64: =IFERROR(IF(N64="","",N64*$E$3),"") -> 0 | Q64: =IFERROR(IF(M64="","",M64*0.5),"") -> 132.5 | R64: =IFERROR(IF(O64="","",O64-P64),"") -> 148
B65: 4 | C65: ABRIL | D65: 110 | E65: 172 | F65: =IFERROR(IF(E65="","",E65-D65),"") -> 62 | G65: =IFERROR(IF(E65="","",E65*$E$3),"") -> 0 | H65: =IFERROR(IF(D65="","",D65*0.5),"") -> 55 | I65: =IFERROR(IF(F65="","",F65-G65),"") -> 62 | K65: 4 | L65: ABRIL | M65: 310 | N65: 484 | O65: =IFERROR(IF(N65="","",N65-M65),"") -> 174 | P65: =IFERROR(IF(N65="","",N65*$E$3),"") -> 0 | Q65: =IFERROR(IF(M65="","",M65*0.5),"") -> 155 | R65: =IFERROR(IF(O65="","",O65-P65),"") -> 174
B66: 5 | C66: MAYO | D66: 85 | E66: 133 | F66: =IFERROR(IF(E66="","",E66-D66),"") -> 48 | G66: =IFERROR(IF(E66="","",E66*$E$3),"") -> 0 | H66: =IFERROR(IF(D66="","",D66*0.5),"") -> 42.5 | I66: =IFERROR(IF(F66="","",F66-G66),"") -> 48 | K66: 5 | L66: MAYO | M66: 290 | N66: 453 | O66: =IFERROR(IF(N66="","",N66-M66),"") -> 163 | P66: =IFERROR(IF(N66="","",N66*$E$3),"") -> 0 | Q66: =IFERROR(IF(M66="","",M66*0.5),"") -> 145 | R66: =IFERROR(IF(O66="","",O66-P66),"") -> 163
B67: 6 | C67: JUNIO | D67: 100 | E67: 156 | F67: =IFERROR(IF(E67="","",E67-D67),"") -> 56 | G67: =IFERROR(IF(E67="","",E67*$E$3),"") -> 0 | H67: =IFERROR(IF(D67="","",D67*0.5),"") -> 50 | I67: =IFERROR(IF(F67="","",F67-G67),"") -> 56 | K67: 6 | L67: JUNIO | M67: 320 | N67: 500 | O67: =IFERROR(IF(N67="","",N67-M67),"") -> 180 | P67: =IFERROR(IF(N67="","",N67*$E$3),"") -> 0 | Q67: =IFERROR(IF(M67="","",M67*0.5),"") -> 160 | R67: =IFERROR(IF(O67="","",O67-P67),"") -> 180
B68: 7 | F68: =IFERROR(IF(E68="","",E68-D68),"") | G68: =IFERROR(IF(E68="","",E68*$E$3),"") | H68: =IFERROR(IF(D68="","",D68*0.5),"") | I68: =IFERROR(IF(F68="","",F68-G68),"") | K68: 7 | O68: =IFERROR(IF(N68="","",N68-M68),"") | P68: =IFERROR(IF(N68="","",N68*$E$3),"") | Q68: =IFERROR(IF(M68="","",M68*0.5),"") | R68: =IFERROR(IF(O68="","",O68-P68),"")
B69: 8 | F69: =IFERROR(IF(E69="","",E69-D69),"") | G69: =IFERROR(IF(E69="","",E69*$E$3),"") | H69: =IFERROR(IF(D69="","",D69*0.5),"") | I69: =IFERROR(IF(F69="","",F69-G69),"") | K69: 8 | O69: =IFERROR(IF(N69="","",N69-M69),"") | P69: =IFERROR(IF(N69="","",N69*$E$3),"") | Q69: =IFERROR(IF(M69="","",M69*0.5),"") | R69: =IFERROR(IF(O69="","",O69-P69),"")
B70: 9 | F70: =IFERROR(IF(E70="","",E70-D70),"") | G70: =IFERROR(IF(E70="","",E70*$E$3),"") | H70: =IFERROR(IF(D70="","",D70*0.5),"") | I70: =IFERROR(IF(F70="","",F70-G70),"") | K70: 9 | O70: =IFERROR(IF(N70="","",N70-M70),"") | P70: =IFERROR(IF(N70="","",N70*$E$3),"") | Q70: =IFERROR(IF(M70="","",M70*0.5),"") | R70: =IFERROR(IF(O70="","",O70-P70),"")
B71: 10 | F71: =IFERROR(IF(E71="","",E71-D71),"") | G71: =IFERROR(IF(E71="","",E71*$E$3),"") | H71: =IFERROR(IF(D71="","",D71*0.5),"") | I71: =IFERROR(IF(F71="","",F71-G71),"") | K71: 10 | O71: =IFERROR(IF(N71="","",N71-M71),"") | P71: =IFERROR(IF(N71="","",N71*$E$3),"") | Q71: =IFERROR(IF(M71="","",M71*0.5),"") | R71: =IFERROR(IF(O71="","",O71-P71),"")
B72: 11 | F72: =IFERROR(IF(E72="","",E72-D72),"") | G72: =IFERROR(IF(E72="","",E72*$E$3),"") | H72: =IFERROR(IF(D72="","",D72*0.5),"") | I72: =IFERROR(IF(F72="","",F72-G72),"") | K72: 11 | O72: =IFERROR(IF(N72="","",N72-M72),"") | P72: =IFERROR(IF(N72="","",N72*$E$3),"") | Q72: =IFERROR(IF(M72="","",M72*0.5),"") | R72: =IFERROR(IF(O72="","",O72-P72),"")
B73: 12 | F73: =IFERROR(IF(E73="","",E73-D73),"") | G73: =IFERROR(IF(E73="","",E73*$E$3),"") | H73: =IFERROR(IF(D73="","",D73*0.5),"") | I73: =IFERROR(IF(F73="","",F73-G73),"") | K73: 12 | O73: =IFERROR(IF(N73="","",N73-M73),"") | P73: =IFERROR(IF(N73="","",N73*$E$3),"") | Q73: =IFERROR(IF(M73="","",M73*0.5),"") | R73: =IFERROR(IF(O73="","",O73-P73),"")
B74: 13 | F74: =IFERROR(IF(E74="","",E74-D74),"") | G74: =IFERROR(IF(E74="","",E74*$E$3),"") | H74: =IFERROR(IF(D74="","",D74*0.5),"") | I74: =IFERROR(IF(F74="","",F74-G74),"") | K74: 13 | O74: =IFERROR(IF(N74="","",N74-M74),"") | P74: =IFERROR(IF(N74="","",N74*$E$3),"") | Q74: =IFERROR(IF(M74="","",M74*0.5),"") | R74: =IFERROR(IF(O74="","",O74-P74),"")
B75: TOTAL | D75: =IFERROR(SUM(D62:D74),0) -> 545 | E75: =IFERROR(SUM(E62:E74),0) -> 851 | F75: =IFERROR(SUM(F62:F74),0) -> 306 | G75: =IFERROR(SUM(G62:G74),0) -> 0 | H75: =IFERROR(SUM(H62:H74),0) -> 272.5 | I75: =IFERROR(SUM(I62:I74),0) -> 306 | K75: TOTAL | M75: =IFERROR(SUM(M62:M74),0) -> 1715 | N75: =IFERROR(SUM(N62:N74),0) -> 2677 | O75: =IFERROR(SUM(O62:O74),0) -> 962 | P75: =IFERROR(SUM(P62:P74),0) -> 0 | Q75: =IFERROR(SUM(Q62:Q74),0) -> 857.5 | R75: =IFERROR(SUM(R62:R74),0) -> 962
B76: 💡 Ganancia bruta = Ventas − Factura | Comisión = Ventas × % | Reinversión = 50% de Factura | Ganancia neta = Bruta − Comisión | K76: 💡 Ganancia bruta = Ventas − Factura | Comisión = Ventas × % | Reinversión = 50% de Factura | Ganancia neta = Bruta − Comisión
B79: 📊 DASHBOARD: ¿QUÉ CATÁLOGO VENDES MÁS?
B81: CATÁLOGO | C81: VENTAS TOTALES S/ | D81: FACTURAS TOTALES S/ | E81: GANANCIA BRUTA S/ | F81: COMISIÓN S/ | G81: GANANCIA NETA S/
B82: Yanbal | C82: =E21 -> 4110 | D82: =D21 -> 2645 | E82: =F21 -> 1465 | F82: =G21 -> 0 | G82: =I21 -> 1465
B83: Esika | C83: =N21 -> 2835 | D83: =M21 -> 1830 | E83: =O21 -> 1005 | F83: =P21 -> 0 | G83: =R21 -> 1005
B84: Cyzone | C84: =E39 -> 1687 | D84: =D39 -> 1080 | E84: =F39 -> 607 | F84: =G39 -> 0 | G84: =I39 -> 607
B85: LBel | C85: =N39 -> 1325 | D85: =M39 -> 845 | E85: =O39 -> 480 | F85: =P39 -> 0 | G85: =R39 -> 480
B86: Natura | C86: =E57 -> 2053 | D86: =D57 -> 1315 | E86: =F57 -> 738 | F86: =G57 -> 0 | G86: =I57 -> 738
B87: Avon | C87: =N57 -> 1616 | D87: =M57 -> 1035 | E87: =O57 -> 581 | F87: =P57 -> 0 | G87: =R57 -> 581
B88: Farmasi | C88: =E75 -> 851 | D88: =D75 -> 545 | E88: =F75 -> 306 | F88: =G75 -> 0 | G88: =I75 -> 306
B89: Oriflame | C89: =N75 -> 2677 | D89: =M75 -> 1715 | E89: =O75 -> 962 | F89: =P75 -> 0 | G89: =R75 -> 962
B90: TOTAL | C90: =SUM(C82:C89) -> 17154 | D90: =SUM(D82:D89) -> 11010 | E90: =SUM(E82:E89) -> 6144 | F90: =SUM(F82:F89) -> 0 | G90: =SUM(G82:G89) -> 6144

Sheet SEG - ENERO
A1: #VALUE! | B1: ✅ SEGUIMIENTO DE VENTAS — ENERO
B2: Registra tus ventas del mes. Usa los desplegables para catálogo, método de pago y estado.
B3: 🔍 Filtros (▼): Campaña · Catálogo · Método de pago · Estado | 🟢 PAGADO 🔴 FALTA CANCELAR 🟡 ADELANTO
A4: CAMPAÑA N° | B4: # | C4: CLIENTE | D4: PRODUCTO | E4: CATÁLOGO | F4: PRECIO (S/) | G4: MÉTODO PAGO | H4: ESTADO PAGO | I4: ADELANTO S/ | J4: NOTAS | K4: COMISIÓN (S/)
A5: 2 | B5: 1 | C5: PAOLA | D5: OHM NOW | E5: YANBAL | F5: 90 | G5: EFECTIVO | H5: PAGADO | K5: =IF(F5="","",F5*'🏠 INICIO'!C8) -> 9
A6: 5 | B6: 2 | K6: =IF(F6="","",F6*'🏠 INICIO'!C8)
B7: 3 | K7: =IF(F7="","",F7*'🏠 INICIO'!C8)
B8: 4 | K8: =IF(F8="","",F8*'🏠 INICIO'!C8)
B9: 5 | K9: =IF(F9="","",F9*'🏠 INICIO'!C8)
B10: 6 | K10: =IF(F10="","",F10*'🏠 INICIO'!C8)
B11: 7 | K11: =IF(F11="","",F11*'🏠 INICIO'!C8)
B12: 8 | K12: =IF(F12="","",F12*'🏠 INICIO'!C8)
B13: 9 | K13: =IF(F13="","",F13*'🏠 INICIO'!C8)
B14: 10 | K14: =IF(F14="","",F14*'🏠 INICIO'!C8)
B15: 11 | K15: =IF(F15="","",F15*'🏠 INICIO'!C8)
B16: 12 | K16: =IF(F16="","",F16*'🏠 INICIO'!C8)
B17: 13 | K17: =IF(F17="","",F17*'🏠 INICIO'!C8)
B18: 14 | K18: =IF(F18="","",F18*'🏠 INICIO'!C8)
B19: 15 | K19: =IF(F19="","",F19*'🏠 INICIO'!C8)
B20: 16 | K20: =IF(F20="","",F20*'🏠 INICIO'!C8)
B21: 17 | K21: =IF(F21="","",F21*'🏠 INICIO'!C8)
B22: 18 | K22: =IF(F22="","",F22*'🏠 INICIO'!C8)
B23: 19 | K23: =IF(F23="","",F23*'🏠 INICIO'!C8)
B24: 20 | K24: =IF(F24="","",F24*'🏠 INICIO'!C8)
B25: 21 | K25: =IF(F25="","",F25*'🏠 INICIO'!C8)
B26: 22 | K26: =IF(F26="","",F26*'🏠 INICIO'!C8)
B27: 23 | K27: =IF(F27="","",F27*'🏠 INICIO'!C8)
B28: 24 | K28: =IF(F28="","",F28*'🏠 INICIO'!C8)
B29: 25 | K29: =IF(F29="","",F29*'🏠 INICIO'!C8)
B30: 26 | K30: =IF(F30="","",F30*'🏠 INICIO'!C8)
B31: 27 | K31: =IF(F31="","",F31*'🏠 INICIO'!C8)
B32: 28 | K32: =IF(F32="","",F32*'🏠 INICIO'!C8)
B33: 29 | K33: =IF(F33="","",F33*'🏠 INICIO'!C8)
B34: 30 | K34: =IF(F34="","",F34*'🏠 INICIO'!C8)
B35: 31 | K35: =IF(F35="","",F35*'🏠 INICIO'!C8)
B36: 32 | K36: =IF(F36="","",F36*'🏠 INICIO'!C8)
B37: 33 | K37: =IF(F37="","",F37*'🏠 INICIO'!C8)
B38: 34 | K38: =IF(F38="","",F38*'🏠 INICIO'!C8)
B39: 35 | K39: =IF(F39="","",F39*'🏠 INICIO'!C8)
B40: 36 | K40: =IF(F40="","",F40*'🏠 INICIO'!C8)
B41: 37 | K41: =IF(F41="","",F41*'🏠 INICIO'!C8)
B42: 38 | K42: =IF(F42="","",F42*'🏠 INICIO'!C8)
B43: 39 | K43: =IF(F43="","",F43*'🏠 INICIO'!C8)
B44: 40 | K44: =IF(F44="","",F44*'🏠 INICIO'!C8)
B45: 41 | K45: =IF(F45="","",F45*'🏠 INICIO'!C8)
B46: 42 | K46: =IF(F46="","",F46*'🏠 INICIO'!C8)
B47: 43 | K47: =IF(F47="","",F47*'🏠 INICIO'!C8)
B48: 44 | K48: =IF(F48="","",F48*'🏠 INICIO'!C8)
B49: 45 | K49: =IF(F49="","",F49*'🏠 INICIO'!C8)
B50: 46 | K50: =IF(F50="","",F50*'🏠 INICIO'!C8)
B51: 47 | K51: =IF(F51="","",F51*'🏠 INICIO'!C8)
B52: 48 | K52: =IF(F52="","",F52*'🏠 INICIO'!C8)
B53: 49 | K53: =IF(F53="","",F53*'🏠 INICIO'!C8)
B54: 50 | K54: =IF(F54="","",F54*'🏠 INICIO'!C8)
B55: 51 | K55: =IF(F55="","",F55*'🏠 INICIO'!C8)
B56: 52 | K56: =IF(F56="","",F56*'🏠 INICIO'!C8)
B57: 53 | K57: =IF(F57="","",F57*'🏠 INICIO'!C8)
B58: 54 | K58: =IF(F58="","",F58*'🏠 INICIO'!C8)
B59: 55 | K59: =IF(F59="","",F59*'🏠 INICIO'!C8)
B60: 56 | K60: =IF(F60="","",F60*'🏠 INICIO'!C8)
B61: 57 | K61: =IF(F61="","",F61*'🏠 INICIO'!C8)
B62: 58 | K62: =IF(F62="","",F62*'🏠 INICIO'!C8)
B63: 59 | K63: =IF(F63="","",F63*'🏠 INICIO'!C8)
B64: 60 | K64: =IF(F64="","",F64*'🏠 INICIO'!C8)
B65: 61 | K65: =IF(F65="","",F65*'🏠 INICIO'!C8)
B66: 62 | K66: =IF(F66="","",F66*'🏠 INICIO'!C8)
B67: 63 | K67: =IF(F67="","",F67*'🏠 INICIO'!C8)
B68: 64 | K68: =IF(F68="","",F68*'🏠 INICIO'!C8)
B69: 65 | K69: =IF(F69="","",F69*'🏠 INICIO'!C8)
B70: 66 | K70: =IF(F70="","",F70*'🏠 INICIO'!C8)
B71: 67 | K71: =IF(F71="","",F71*'🏠 INICIO'!C8)
B72: 68 | K72: =IF(F72="","",F72*'🏠 INICIO'!C8)
B73: 69 | K73: =IF(F73="","",F73*'🏠 INICIO'!C8)
B74: 70 | K74: =IF(F74="","",F74*'🏠 INICIO'!C8)
B75: 71 | K75: =IF(F75="","",F75*'🏠 INICIO'!C8)
B76: 72 | K76: =IF(F76="","",F76*'🏠 INICIO'!C8)
B77: 73 | K77: =IF(F77="","",F77*'🏠 INICIO'!C8)
B78: 74 | K78: =IF(F78="","",F78*'🏠 INICIO'!C8)
B79: 75 | K79: =IF(F79="","",F79*'🏠 INICIO'!C8)
B80: 76 | K80: =IF(F80="","",F80*'🏠 INICIO'!C8)
B81: 77 | K81: =IF(F81="","",F81*'🏠 INICIO'!C8)
B82: 78 | K82: =IF(F82="","",F82*'🏠 INICIO'!C8)
B83: 79 | K83: =IF(F83="","",F83*'🏠 INICIO'!C8)
B84: 80 | K84: =IF(F84="","",F84*'🏠 INICIO'!C8)
B85: 81 | K85: =IF(F85="","",F85*'🏠 INICIO'!C8)
B86: 82 | K86: =IF(F86="","",F86*'🏠 INICIO'!C8)
B87: 83 | K87: =IF(F87="","",F87*'🏠 INICIO'!C8)
B88: 84 | K88: =IF(F88="","",F88*'🏠 INICIO'!C8)
B89: 85 | K89: =IF(F89="","",F89*'🏠 INICIO'!C8)
B90: 86 | K90: =IF(F90="","",F90*'🏠 INICIO'!C8)
B91: 87 | K91: =IF(F91="","",F91*'🏠 INICIO'!C8)
B92: 88 | K92: =IF(F92="","",F92*'🏠 INICIO'!C8)
B93: 89 | K93: =IF(F93="","",F93*'🏠 INICIO'!C8)
B94: 90 | K94: =IF(F94="","",F94*'🏠 INICIO'!C8)
B95: 91 | K95: =IF(F95="","",F95*'🏠 INICIO'!C8)
B96: 92 | K96: =IF(F96="","",F96*'🏠 INICIO'!C8)
B97: 93 | K97: =IF(F97="","",F97*'🏠 INICIO'!C8)
B98: 94 | K98: =IF(F98="","",F98*'🏠 INICIO'!C8)
B99: 95 | K99: =IF(F99="","",F99*'🏠 INICIO'!C8)
B100: 96 | K100: =IF(F100="","",F100*'🏠 INICIO'!C8)
...

Sheet SEG - FEBRERO
A1: #VALUE! | B1: ✅ SEGUIMIENTO DE VENTAS — FEBRERO
B2: Registra tus ventas del mes. Usa los desplegables para catálogo, método de pago y estado.
B3: 🔍 Filtros (▼): Campaña · Catálogo · Método de pago · Estado | 🟢 PAGADO 🔴 FALTA CANCELAR 🟡 ADELANTO
A4: CAMPAÑA N° | B4: # | C4: CLIENTE | D4: PRODUCTO | E4: CATÁLOGO | F4: PRECIO (S/) | G4: MÉTODO PAGO | H4: ESTADO PAGO | I4: ADELANTO S/ | J4: NOTAS | K4: COMISIÓN (S/)
A5: 2 | B5: 1 | C5: PAOLA | D5: OHM NOW | E5: YANBAL | F5: 90 | G5: EFECTIVO | H5: PAGADO | K5: =IF(F5="","",F5*'🏠 INICIO'!C8) -> 9
A6: 5 | B6: 2 | K6: =IF(F6="","",F6*'🏠 INICIO'!C8)
B7: 3 | K7: =IF(F7="","",F7*'🏠 INICIO'!C8)
B8: 4 | K8: =IF(F8="","",F8*'🏠 INICIO'!C8)
B9: 5 | K9: =IF(F9="","",F9*'🏠 INICIO'!C8)
B10: 6 | K10: =IF(F10="","",F10*'🏠 INICIO'!C8)
B11: 7 | K11: =IF(F11="","",F11*'🏠 INICIO'!C8)
B12: 8 | K12: =IF(F12="","",F12*'🏠 INICIO'!C8)
B13: 9 | K13: =IF(F13="","",F13*'🏠 INICIO'!C8)
B14: 10 | K14: =IF(F14="","",F14*'🏠 INICIO'!C8)
B15: 11 | K15: =IF(F15="","",F15*'🏠 INICIO'!C8)
B16: 12 | K16: =IF(F16="","",F16*'🏠 INICIO'!C8)
B17: 13 | K17: =IF(F17="","",F17*'🏠 INICIO'!C8)
B18: 14 | K18: =IF(F18="","",F18*'🏠 INICIO'!C8)
B19: 15 | K19: =IF(F19="","",F19*'🏠 INICIO'!C8)
B20: 16 | K20: =IF(F20="","",F20*'🏠 INICIO'!C8)
B21: 17 | K21: =IF(F21="","",F21*'🏠 INICIO'!C8)
B22: 18 | K22: =IF(F22="","",F22*'🏠 INICIO'!C8)
B23: 19 | K23: =IF(F23="","",F23*'🏠 INICIO'!C8)
B24: 20 | K24: =IF(F24="","",F24*'🏠 INICIO'!C8)
B25: 21 | K25: =IF(F25="","",F25*'🏠 INICIO'!C8)
B26: 22 | K26: =IF(F26="","",F26*'🏠 INICIO'!C8)
B27: 23 | K27: =IF(F27="","",F27*'🏠 INICIO'!C8)
B28: 24 | K28: =IF(F28="","",F28*'🏠 INICIO'!C8)
B29: 25 | K29: =IF(F29="","",F29*'🏠 INICIO'!C8)
B30: 26 | K30: =IF(F30="","",F30*'🏠 INICIO'!C8)
B31: 27 | K31: =IF(F31="","",F31*'🏠 INICIO'!C8)
B32: 28 | K32: =IF(F32="","",F32*'🏠 INICIO'!C8)
B33: 29 | K33: =IF(F33="","",F33*'🏠 INICIO'!C8)
B34: 30 | K34: =IF(F34="","",F34*'🏠 INICIO'!C8)
B35: 31 | K35: =IF(F35="","",F35*'🏠 INICIO'!C8)
B36: 32 | K36: =IF(F36="","",F36*'🏠 INICIO'!C8)
B37: 33 | K37: =IF(F37="","",F37*'🏠 INICIO'!C8)
B38: 34 | K38: =IF(F38="","",F38*'🏠 INICIO'!C8)
B39: 35 | K39: =IF(F39="","",F39*'🏠 INICIO'!C8)
B40: 36 | K40: =IF(F40="","",F40*'🏠 INICIO'!C8)
B41: 37 | K41: =IF(F41="","",F41*'🏠 INICIO'!C8)
B42: 38 | K42: =IF(F42="","",F42*'🏠 INICIO'!C8)
B43: 39 | K43: =IF(F43="","",F43*'🏠 INICIO'!C8)
B44: 40 | K44: =IF(F44="","",F44*'🏠 INICIO'!C8)
B45: 41 | K45: =IF(F45="","",F45*'🏠 INICIO'!C8)
B46: 42 | K46: =IF(F46="","",F46*'🏠 INICIO'!C8)
B47: 43 | K47: =IF(F47="","",F47*'🏠 INICIO'!C8)
B48: 44 | K48: =IF(F48="","",F48*'🏠 INICIO'!C8)
B49: 45 | K49: =IF(F49="","",F49*'🏠 INICIO'!C8)
B50: 46 | K50: =IF(F50="","",F50*'🏠 INICIO'!C8)
B51: 47 | K51: =IF(F51="","",F51*'🏠 INICIO'!C8)
B52: 48 | K52: =IF(F52="","",F52*'🏠 INICIO'!C8)
B53: 49 | K53: =IF(F53="","",F53*'🏠 INICIO'!C8)
B54: 50 | K54: =IF(F54="","",F54*'🏠 INICIO'!C8)
B55: 51 | K55: =IF(F55="","",F55*'🏠 INICIO'!C8)
B56: 52 | K56: =IF(F56="","",F56*'🏠 INICIO'!C8)
B57: 53 | K57: =IF(F57="","",F57*'🏠 INICIO'!C8)
B58: 54 | K58: =IF(F58="","",F58*'🏠 INICIO'!C8)
B59: 55 | K59: =IF(F59="","",F59*'🏠 INICIO'!C8)
B60: 56 | K60: =IF(F60="","",F60*'🏠 INICIO'!C8)
B61: 57 | K61: =IF(F61="","",F61*'🏠 INICIO'!C8)
B62: 58 | K62: =IF(F62="","",F62*'🏠 INICIO'!C8)
B63: 59 | K63: =IF(F63="","",F63*'🏠 INICIO'!C8)
B64: 60 | K64: =IF(F64="","",F64*'🏠 INICIO'!C8)
B65: 61 | K65: =IF(F65="","",F65*'🏠 INICIO'!C8)
B66: 62 | K66: =IF(F66="","",F66*'🏠 INICIO'!C8)
B67: 63 | K67: =IF(F67="","",F67*'🏠 INICIO'!C8)
B68: 64 | K68: =IF(F68="","",F68*'🏠 INICIO'!C8)
B69: 65 | K69: =IF(F69="","",F69*'🏠 INICIO'!C8)
B70: 66 | K70: =IF(F70="","",F70*'🏠 INICIO'!C8)
B71: 67 | K71: =IF(F71="","",F71*'🏠 INICIO'!C8)
B72: 68 | K72: =IF(F72="","",F72*'🏠 INICIO'!C8)
B73: 69 | K73: =IF(F73="","",F73*'🏠 INICIO'!C8)
B74: 70 | K74: =IF(F74="","",F74*'🏠 INICIO'!C8)
B75: 71 | K75: =IF(F75="","",F75*'🏠 INICIO'!C8)
B76: 72 | K76: =IF(F76="","",F76*'🏠 INICIO'!C8)
B77: 73 | K77: =IF(F77="","",F77*'🏠 INICIO'!C8)
B78: 74 | K78: =IF(F78="","",F78*'🏠 INICIO'!C8)
B79: 75 | K79: =IF(F79="","",F79*'🏠 INICIO'!C8)
B80: 76 | K80: =IF(F80="","",F80*'🏠 INICIO'!C8)
B81: 77 | K81: =IF(F81="","",F81*'🏠 INICIO'!C8)
B82: 78 | K82: =IF(F82="","",F82*'🏠 INICIO'!C8)
B83: 79 | K83: =IF(F83="","",F83*'🏠 INICIO'!C8)
B84: 80 | K84: =IF(F84="","",F84*'🏠 INICIO'!C8)
B85: 81 | K85: =IF(F85="","",F85*'🏠 INICIO'!C8)
B86: 82 | K86: =IF(F86="","",F86*'🏠 INICIO'!C8)
B87: 83 | K87: =IF(F87="","",F87*'🏠 INICIO'!C8)
B88: 84 | K88: =IF(F88="","",F88*'🏠 INICIO'!C8)
B89: 85 | K89: =IF(F89="","",F89*'🏠 INICIO'!C8)
B90: 86 | K90: =IF(F90="","",F90*'🏠 INICIO'!C8)
B91: 87 | K91: =IF(F91="","",F91*'🏠 INICIO'!C8)
B92: 88 | K92: =IF(F92="","",F92*'🏠 INICIO'!C8)
B93: 89 | K93: =IF(F93="","",F93*'🏠 INICIO'!C8)
B94: 90 | K94: =IF(F94="","",F94*'🏠 INICIO'!C8)
B95: 91 | K95: =IF(F95="","",F95*'🏠 INICIO'!C8)
B96: 92 | K96: =IF(F96="","",F96*'🏠 INICIO'!C8)
B97: 93 | K97: =IF(F97="","",F97*'🏠 INICIO'!C8)
B98: 94 | K98: =IF(F98="","",F98*'🏠 INICIO'!C8)
B99: 95 | K99: =IF(F99="","",F99*'🏠 INICIO'!C8)
B100: 96 | K100: =IF(F100="","",F100*'🏠 INICIO'!C8)
...

Sheet SEG - MARZO
A1: #VALUE! | B1: ✅ SEGUIMIENTO DE VENTAS — MARZO
B2: Registra tus ventas del mes. Usa los desplegables para catálogo, método de pago y estado.
B3: 🔍 Filtros (▼): Campaña · Catálogo · Método de pago · Estado | 🟢 PAGADO 🔴 FALTA CANCELAR 🟡 ADELANTO
A4: CAMPAÑA N° | B4: # | C4: CLIENTE | D4: PRODUCTO | E4: CATÁLOGO | F4: PRECIO (S/) | G4: MÉTODO PAGO | H4: ESTADO PAGO | I4: ADELANTO S/ | J4: NOTAS | K4: COMISIÓN (S/)
A5: 2 | B5: 1 | C5: PAOLA | D5: OHM NOW | E5: YANBAL | F5: 90 | G5: EFECTIVO | H5: PAGADO | K5: =IF(F5="","",F5*'🏠 INICIO'!C8) -> 9
A6: 5 | B6: 2 | K6: =IF(F6="","",F6*'🏠 INICIO'!C8)
B7: 3 | K7: =IF(F7="","",F7*'🏠 INICIO'!C8)
B8: 4 | K8: =IF(F8="","",F8*'🏠 INICIO'!C8)
B9: 5 | K9: =IF(F9="","",F9*'🏠 INICIO'!C8)
B10: 6 | K10: =IF(F10="","",F10*'🏠 INICIO'!C8)
B11: 7 | K11: =IF(F11="","",F11*'🏠 INICIO'!C8)
B12: 8 | K12: =IF(F12="","",F12*'🏠 INICIO'!C8)
B13: 9 | K13: =IF(F13="","",F13*'🏠 INICIO'!C8)
B14: 10 | K14: =IF(F14="","",F14*'🏠 INICIO'!C8)
B15: 11 | K15: =IF(F15="","",F15*'🏠 INICIO'!C8)
B16: 12 | K16: =IF(F16="","",F16*'🏠 INICIO'!C8)
B17: 13 | K17: =IF(F17="","",F17*'🏠 INICIO'!C8)
B18: 14 | K18: =IF(F18="","",F18*'🏠 INICIO'!C8)
B19: 15 | K19: =IF(F19="","",F19*'🏠 INICIO'!C8)
B20: 16 | K20: =IF(F20="","",F20*'🏠 INICIO'!C8)
B21: 17 | K21: =IF(F21="","",F21*'🏠 INICIO'!C8)
B22: 18 | K22: =IF(F22="","",F22*'🏠 INICIO'!C8)
B23: 19 | K23: =IF(F23="","",F23*'🏠 INICIO'!C8)
B24: 20 | K24: =IF(F24="","",F24*'🏠 INICIO'!C8)
B25: 21 | K25: =IF(F25="","",F25*'🏠 INICIO'!C8)
B26: 22 | K26: =IF(F26="","",F26*'🏠 INICIO'!C8)
B27: 23 | K27: =IF(F27="","",F27*'🏠 INICIO'!C8)
B28: 24 | K28: =IF(F28="","",F28*'🏠 INICIO'!C8)
B29: 25 | K29: =IF(F29="","",F29*'🏠 INICIO'!C8)
B30: 26 | K30: =IF(F30="","",F30*'🏠 INICIO'!C8)
B31: 27 | K31: =IF(F31="","",F31*'🏠 INICIO'!C8)
B32: 28 | K32: =IF(F32="","",F32*'🏠 INICIO'!C8)
B33: 29 | K33: =IF(F33="","",F33*'🏠 INICIO'!C8)
B34: 30 | K34: =IF(F34="","",F34*'🏠 INICIO'!C8)
B35: 31 | K35: =IF(F35="","",F35*'🏠 INICIO'!C8)
B36: 32 | K36: =IF(F36="","",F36*'🏠 INICIO'!C8)
B37: 33 | K37: =IF(F37="","",F37*'🏠 INICIO'!C8)
B38: 34 | K38: =IF(F38="","",F38*'🏠 INICIO'!C8)
B39: 35 | K39: =IF(F39="","",F39*'🏠 INICIO'!C8)
B40: 36 | K40: =IF(F40="","",F40*'🏠 INICIO'!C8)
B41: 37 | K41: =IF(F41="","",F41*'🏠 INICIO'!C8)
B42: 38 | K42: =IF(F42="","",F42*'🏠 INICIO'!C8)
B43: 39 | K43: =IF(F43="","",F43*'🏠 INICIO'!C8)
B44: 40 | K44: =IF(F44="","",F44*'🏠 INICIO'!C8)
B45: 41 | K45: =IF(F45="","",F45*'🏠 INICIO'!C8)
B46: 42 | K46: =IF(F46="","",F46*'🏠 INICIO'!C8)
B47: 43 | K47: =IF(F47="","",F47*'🏠 INICIO'!C8)
B48: 44 | K48: =IF(F48="","",F48*'🏠 INICIO'!C8)
B49: 45 | K49: =IF(F49="","",F49*'🏠 INICIO'!C8)
B50: 46 | K50: =IF(F50="","",F50*'🏠 INICIO'!C8)
B51: 47 | K51: =IF(F51="","",F51*'🏠 INICIO'!C8)
B52: 48 | K52: =IF(F52="","",F52*'🏠 INICIO'!C8)
B53: 49 | K53: =IF(F53="","",F53*'🏠 INICIO'!C8)
B54: 50 | K54: =IF(F54="","",F54*'🏠 INICIO'!C8)
B55: 51 | K55: =IF(F55="","",F55*'🏠 INICIO'!C8)
B56: 52 | K56: =IF(F56="","",F56*'🏠 INICIO'!C8)
B57: 53 | K57: =IF(F57="","",F57*'🏠 INICIO'!C8)
B58: 54 | K58: =IF(F58="","",F58*'🏠 INICIO'!C8)
B59: 55 | K59: =IF(F59="","",F59*'🏠 INICIO'!C8)
B60: 56 | K60: =IF(F60="","",F60*'🏠 INICIO'!C8)
B61: 57 | K61: =IF(F61="","",F61*'🏠 INICIO'!C8)
B62: 58 | K62: =IF(F62="","",F62*'🏠 INICIO'!C8)
B63: 59 | K63: =IF(F63="","",F63*'🏠 INICIO'!C8)
B64: 60 | K64: =IF(F64="","",F64*'🏠 INICIO'!C8)
B65: 61 | K65: =IF(F65="","",F65*'🏠 INICIO'!C8)
B66: 62 | K66: =IF(F66="","",F66*'🏠 INICIO'!C8)
B67: 63 | K67: =IF(F67="","",F67*'🏠 INICIO'!C8)
B68: 64 | K68: =IF(F68="","",F68*'🏠 INICIO'!C8)
B69: 65 | K69: =IF(F69="","",F69*'🏠 INICIO'!C8)
B70: 66 | K70: =IF(F70="","",F70*'🏠 INICIO'!C8)
B71: 67 | K71: =IF(F71="","",F71*'🏠 INICIO'!C8)
B72: 68 | K72: =IF(F72="","",F72*'🏠 INICIO'!C8)
B73: 69 | K73: =IF(F73="","",F73*'🏠 INICIO'!C8)
B74: 70 | K74: =IF(F74="","",F74*'🏠 INICIO'!C8)
B75: 71 | K75: =IF(F75="","",F75*'🏠 INICIO'!C8)
B76: 72 | K76: =IF(F76="","",F76*'🏠 INICIO'!C8)
B77: 73 | K77: =IF(F77="","",F77*'🏠 INICIO'!C8)
B78: 74 | K78: =IF(F78="","",F78*'🏠 INICIO'!C8)
B79: 75 | K79: =IF(F79="","",F79*'🏠 INICIO'!C8)
B80: 76 | K80: =IF(F80="","",F80*'🏠 INICIO'!C8)
B81: 77 | K81: =IF(F81="","",F81*'🏠 INICIO'!C8)
B82: 78 | K82: =IF(F82="","",F82*'🏠 INICIO'!C8)
B83: 79 | K83: =IF(F83="","",F83*'🏠 INICIO'!C8)
B84: 80 | K84: =IF(F84="","",F84*'🏠 INICIO'!C8)
B85: 81 | K85: =IF(F85="","",F85*'🏠 INICIO'!C8)
B86: 82 | K86: =IF(F86="","",F86*'🏠 INICIO'!C8)
B87: 83 | K87: =IF(F87="","",F87*'🏠 INICIO'!C8)
B88: 84 | K88: =IF(F88="","",F88*'🏠 INICIO'!C8)
B89: 85 | K89: =IF(F89="","",F89*'🏠 INICIO'!C8)
B90: 86 | K90: =IF(F90="","",F90*'🏠 INICIO'!C8)
B91: 87 | K91: =IF(F91="","",F91*'🏠 INICIO'!C8)
B92: 88 | K92: =IF(F92="","",F92*'🏠 INICIO'!C8)
B93: 89 | K93: =IF(F93="","",F93*'🏠 INICIO'!C8)
B94: 90 | K94: =IF(F94="","",F94*'🏠 INICIO'!C8)
B95: 91 | K95: =IF(F95="","",F95*'🏠 INICIO'!C8)
B96: 92 | K96: =IF(F96="","",F96*'🏠 INICIO'!C8)
B97: 93 | K97: =IF(F97="","",F97*'🏠 INICIO'!C8)
B98: 94 | K98: =IF(F98="","",F98*'🏠 INICIO'!C8)
B99: 95 | K99: =IF(F99="","",F99*'🏠 INICIO'!C8)
B100: 96 | K100: =IF(F100="","",F100*'🏠 INICIO'!C8)
...

Sheet SEG - ABRIL
A1: #VALUE! | B1: ✅ SEGUIMIENTO DE VENTAS — ABRIL
B2: Registra tus ventas del mes. Usa los desplegables para catálogo, método de pago y estado.
B3: 🔍 Filtros (▼): Campaña · Catálogo · Método de pago · Estado | 🟢 PAGADO 🔴 FALTA CANCELAR 🟡 ADELANTO
A4: CAMPAÑA N° | B4: # | C4: CLIENTE | D4: PRODUCTO | E4: CATÁLOGO | F4: PRECIO (S/) | G4: MÉTODO PAGO | H4: ESTADO PAGO | I4: ADELANTO S/ | J4: NOTAS | K4: COMISIÓN (S/)
A5: 2 | B5: 1 | C5: PAOLA | D5: OHM NOW | E5: YANBAL | F5: 90 | G5: EFECTIVO | H5: ADELANTO | I5: 50 | K5: =IF(F5="","",F5*'🏠 INICIO'!C8) -> 9
A6: 5 | B6: 2 | K6: =IF(F6="","",F6*'🏠 INICIO'!C8)
B7: 3 | K7: =IF(F7="","",F7*'🏠 INICIO'!C8)
B8: 4 | K8: =IF(F8="","",F8*'🏠 INICIO'!C8)
B9: 5 | K9: =IF(F9="","",F9*'🏠 INICIO'!C8)
B10: 6 | K10: =IF(F10="","",F10*'🏠 INICIO'!C8)
B11: 7 | K11: =IF(F11="","",F11*'🏠 INICIO'!C8)
B12: 8 | K12: =IF(F12="","",F12*'🏠 INICIO'!C8)
B13: 9 | K13: =IF(F13="","",F13*'🏠 INICIO'!C8)
B14: 10 | K14: =IF(F14="","",F14*'🏠 INICIO'!C8)
B15: 11 | K15: =IF(F15="","",F15*'🏠 INICIO'!C8)
B16: 12 | K16: =IF(F16="","",F16*'🏠 INICIO'!C8)
B17: 13 | K17: =IF(F17="","",F17*'🏠 INICIO'!C8)
B18: 14 | K18: =IF(F18="","",F18*'🏠 INICIO'!C8)
B19: 15 | K19: =IF(F19="","",F19*'🏠 INICIO'!C8)
B20: 16 | K20: =IF(F20="","",F20*'🏠 INICIO'!C8)
B21: 17 | K21: =IF(F21="","",F21*'🏠 INICIO'!C8)
B22: 18 | K22: =IF(F22="","",F22*'🏠 INICIO'!C8)
B23: 19 | K23: =IF(F23="","",F23*'🏠 INICIO'!C8)
B24: 20 | K24: =IF(F24="","",F24*'🏠 INICIO'!C8)
B25: 21 | K25: =IF(F25="","",F25*'🏠 INICIO'!C8)
B26: 22 | K26: =IF(F26="","",F26*'🏠 INICIO'!C8)
B27: 23 | K27: =IF(F27="","",F27*'🏠 INICIO'!C8)
B28: 24 | K28: =IF(F28="","",F28*'🏠 INICIO'!C8)
B29: 25 | K29: =IF(F29="","",F29*'🏠 INICIO'!C8)
B30: 26 | K30: =IF(F30="","",F30*'🏠 INICIO'!C8)
B31: 27 | K31: =IF(F31="","",F31*'🏠 INICIO'!C8)
B32: 28 | K32: =IF(F32="","",F32*'🏠 INICIO'!C8)
B33: 29 | K33: =IF(F33="","",F33*'🏠 INICIO'!C8)
B34: 30 | K34: =IF(F34="","",F34*'🏠 INICIO'!C8)
B35: 31 | K35: =IF(F35="","",F35*'🏠 INICIO'!C8)
B36: 32 | K36: =IF(F36="","",F36*'🏠 INICIO'!C8)
B37: 33 | K37: =IF(F37="","",F37*'🏠 INICIO'!C8)
B38: 34 | K38: =IF(F38="","",F38*'🏠 INICIO'!C8)
B39: 35 | K39: =IF(F39="","",F39*'🏠 INICIO'!C8)
B40: 36 | K40: =IF(F40="","",F40*'🏠 INICIO'!C8)
B41: 37 | K41: =IF(F41="","",F41*'🏠 INICIO'!C8)
B42: 38 | K42: =IF(F42="","",F42*'🏠 INICIO'!C8)
B43: 39 | K43: =IF(F43="","",F43*'🏠 INICIO'!C8)
B44: 40 | K44: =IF(F44="","",F44*'🏠 INICIO'!C8)
B45: 41 | K45: =IF(F45="","",F45*'🏠 INICIO'!C8)
B46: 42 | K46: =IF(F46="","",F46*'🏠 INICIO'!C8)
B47: 43 | K47: =IF(F47="","",F47*'🏠 INICIO'!C8)
B48: 44 | K48: =IF(F48="","",F48*'🏠 INICIO'!C8)
B49: 45 | K49: =IF(F49="","",F49*'🏠 INICIO'!C8)
B50: 46 | K50: =IF(F50="","",F50*'🏠 INICIO'!C8)
B51: 47 | K51: =IF(F51="","",F51*'🏠 INICIO'!C8)
B52: 48 | K52: =IF(F52="","",F52*'🏠 INICIO'!C8)
B53: 49 | K53: =IF(F53="","",F53*'🏠 INICIO'!C8)
B54: 50 | K54: =IF(F54="","",F54*'🏠 INICIO'!C8)
B55: 51 | K55: =IF(F55="","",F55*'🏠 INICIO'!C8)
B56: 52 | K56: =IF(F56="","",F56*'🏠 INICIO'!C8)
B57: 53 | K57: =IF(F57="","",F57*'🏠 INICIO'!C8)
B58: 54 | K58: =IF(F58="","",F58*'🏠 INICIO'!C8)
B59: 55 | K59: =IF(F59="","",F59*'🏠 INICIO'!C8)
B60: 56 | K60: =IF(F60="","",F60*'🏠 INICIO'!C8)
B61: 57 | K61: =IF(F61="","",F61*'🏠 INICIO'!C8)
B62: 58 | K62: =IF(F62="","",F62*'🏠 INICIO'!C8)
B63: 59 | K63: =IF(F63="","",F63*'🏠 INICIO'!C8)
B64: 60 | K64: =IF(F64="","",F64*'🏠 INICIO'!C8)
B65: 61 | K65: =IF(F65="","",F65*'🏠 INICIO'!C8)
B66: 62 | K66: =IF(F66="","",F66*'🏠 INICIO'!C8)
B67: 63 | K67: =IF(F67="","",F67*'🏠 INICIO'!C8)
B68: 64 | K68: =IF(F68="","",F68*'🏠 INICIO'!C8)
B69: 65 | K69: =IF(F69="","",F69*'🏠 INICIO'!C8)
B70: 66 | K70: =IF(F70="","",F70*'🏠 INICIO'!C8)
B71: 67 | K71: =IF(F71="","",F71*'🏠 INICIO'!C8)
B72: 68 | K72: =IF(F72="","",F72*'🏠 INICIO'!C8)
B73: 69 | K73: =IF(F73="","",F73*'🏠 INICIO'!C8)
B74: 70 | K74: =IF(F74="","",F74*'🏠 INICIO'!C8)
B75: 71 | K75: =IF(F75="","",F75*'🏠 INICIO'!C8)
B76: 72 | K76: =IF(F76="","",F76*'🏠 INICIO'!C8)
B77: 73 | K77: =IF(F77="","",F77*'🏠 INICIO'!C8)
B78: 74 | K78: =IF(F78="","",F78*'🏠 INICIO'!C8)
B79: 75 | K79: =IF(F79="","",F79*'🏠 INICIO'!C8)
B80: 76 | K80: =IF(F80="","",F80*'🏠 INICIO'!C8)
B81: 77 | K81: =IF(F81="","",F81*'🏠 INICIO'!C8)
B82: 78 | K82: =IF(F82="","",F82*'🏠 INICIO'!C8)
B83: 79 | K83: =IF(F83="","",F83*'🏠 INICIO'!C8)
B84: 80 | K84: =IF(F84="","",F84*'🏠 INICIO'!C8)
B85: 81 | K85: =IF(F85="","",F85*'🏠 INICIO'!C8)
B86: 82 | K86: =IF(F86="","",F86*'🏠 INICIO'!C8)
B87: 83 | K87: =IF(F87="","",F87*'🏠 INICIO'!C8)
B88: 84 | K88: =IF(F88="","",F88*'🏠 INICIO'!C8)
B89: 85 | K89: =IF(F89="","",F89*'🏠 INICIO'!C8)
B90: 86 | K90: =IF(F90="","",F90*'🏠 INICIO'!C8)
B91: 87 | K91: =IF(F91="","",F91*'🏠 INICIO'!C8)
B92: 88 | K92: =IF(F92="","",F92*'🏠 INICIO'!C8)
B93: 89 | K93: =IF(F93="","",F93*'🏠 INICIO'!C8)
B94: 90 | K94: =IF(F94="","",F94*'🏠 INICIO'!C8)
B95: 91 | K95: =IF(F95="","",F95*'🏠 INICIO'!C8)
B96: 92 | K96: =IF(F96="","",F96*'🏠 INICIO'!C8)
B97: 93 | K97: =IF(F97="","",F97*'🏠 INICIO'!C8)
B98: 94 | K98: =IF(F98="","",F98*'🏠 INICIO'!C8)
B99: 95 | K99: =IF(F99="","",F99*'🏠 INICIO'!C8)
B100: 96 | K100: =IF(F100="","",F100*'🏠 INICIO'!C8)
...

Sheet SEG - MAYO
A1: #VALUE! | B1: ✅ SEGUIMIENTO DE VENTAS — MAYO
B2: Registra tus ventas del mes. Usa los desplegables para catálogo, método de pago y estado.
B3: 🔍 Filtros (▼): Campaña · Catálogo · Método de pago · Estado | 🟢 PAGADO 🔴 FALTA CANCELAR 🟡 ADELANTO
A4: CAMPAÑA N° | B4: # | C4: CLIENTE | D4: PRODUCTO | E4: CATÁLOGO | F4: PRECIO (S/) | G4: MÉTODO PAGO | H4: ESTADO PAGO | I4: ADELANTO S/ | J4: NOTAS | K4: COMISIÓN (S/)
A5: 2 | B5: 1 | C5: PAOLA | D5: OHM NOW | E5: YANBAL | F5: 90 | G5: EFECTIVO | H5: PAGADO | K5: =IF(F5="","",F5*'🏠 INICIO'!C8) -> 9
A6: 5 | B6: 2 | K6: =IF(F6="","",F6*'🏠 INICIO'!C8)
B7: 3 | K7: =IF(F7="","",F7*'🏠 INICIO'!C8)
B8: 4 | K8: =IF(F8="","",F8*'🏠 INICIO'!C8)
B9: 5 | K9: =IF(F9="","",F9*'🏠 INICIO'!C8)
B10: 6 | K10: =IF(F10="","",F10*'🏠 INICIO'!C8)
B11: 7 | K11: =IF(F11="","",F11*'🏠 INICIO'!C8)
B12: 8 | K12: =IF(F12="","",F12*'🏠 INICIO'!C8)
B13: 9 | K13: =IF(F13="","",F13*'🏠 INICIO'!C8)
B14: 10 | K14: =IF(F14="","",F14*'🏠 INICIO'!C8)
B15: 11 | K15: =IF(F15="","",F15*'🏠 INICIO'!C8)
B16: 12 | K16: =IF(F16="","",F16*'🏠 INICIO'!C8)
B17: 13 | K17: =IF(F17="","",F17*'🏠 INICIO'!C8)
B18: 14 | K18: =IF(F18="","",F18*'🏠 INICIO'!C8)
B19: 15 | K19: =IF(F19="","",F19*'🏠 INICIO'!C8)
B20: 16 | K20: =IF(F20="","",F20*'🏠 INICIO'!C8)
B21: 17 | K21: =IF(F21="","",F21*'🏠 INICIO'!C8)
B22: 18 | K22: =IF(F22="","",F22*'🏠 INICIO'!C8)
B23: 19 | K23: =IF(F23="","",F23*'🏠 INICIO'!C8)
B24: 20 | K24: =IF(F24="","",F24*'🏠 INICIO'!C8)
B25: 21 | K25: =IF(F25="","",F25*'🏠 INICIO'!C8)
B26: 22 | K26: =IF(F26="","",F26*'🏠 INICIO'!C8)
B27: 23 | K27: =IF(F27="","",F27*'🏠 INICIO'!C8)
B28: 24 | K28: =IF(F28="","",F28*'🏠 INICIO'!C8)
B29: 25 | K29: =IF(F29="","",F29*'🏠 INICIO'!C8)
B30: 26 | K30: =IF(F30="","",F30*'🏠 INICIO'!C8)
B31: 27 | K31: =IF(F31="","",F31*'🏠 INICIO'!C8)
B32: 28 | K32: =IF(F32="","",F32*'🏠 INICIO'!C8)
B33: 29 | K33: =IF(F33="","",F33*'🏠 INICIO'!C8)
B34: 30 | K34: =IF(F34="","",F34*'🏠 INICIO'!C8)
B35: 31 | K35: =IF(F35="","",F35*'🏠 INICIO'!C8)
B36: 32 | K36: =IF(F36="","",F36*'🏠 INICIO'!C8)
B37: 33 | K37: =IF(F37="","",F37*'🏠 INICIO'!C8)
B38: 34 | K38: =IF(F38="","",F38*'🏠 INICIO'!C8)
B39: 35 | K39: =IF(F39="","",F39*'🏠 INICIO'!C8)
B40: 36 | K40: =IF(F40="","",F40*'🏠 INICIO'!C8)
B41: 37 | K41: =IF(F41="","",F41*'🏠 INICIO'!C8)
B42: 38 | K42: =IF(F42="","",F42*'🏠 INICIO'!C8)
B43: 39 | K43: =IF(F43="","",F43*'🏠 INICIO'!C8)
B44: 40 | K44: =IF(F44="","",F44*'🏠 INICIO'!C8)
B45: 41 | K45: =IF(F45="","",F45*'🏠 INICIO'!C8)
B46: 42 | K46: =IF(F46="","",F46*'🏠 INICIO'!C8)
B47: 43 | K47: =IF(F47="","",F47*'🏠 INICIO'!C8)
B48: 44 | K48: =IF(F48="","",F48*'🏠 INICIO'!C8)
B49: 45 | K49: =IF(F49="","",F49*'🏠 INICIO'!C8)
B50: 46 | K50: =IF(F50="","",F50*'🏠 INICIO'!C8)
B51: 47 | K51: =IF(F51="","",F51*'🏠 INICIO'!C8)
B52: 48 | K52: =IF(F52="","",F52*'🏠 INICIO'!C8)
B53: 49 | K53: =IF(F53="","",F53*'🏠 INICIO'!C8)
B54: 50 | K54: =IF(F54="","",F54*'🏠 INICIO'!C8)
B55: 51 | K55: =IF(F55="","",F55*'🏠 INICIO'!C8)
B56: 52 | K56: =IF(F56="","",F56*'🏠 INICIO'!C8)
B57: 53 | K57: =IF(F57="","",F57*'🏠 INICIO'!C8)
B58: 54 | K58: =IF(F58="","",F58*'🏠 INICIO'!C8)
B59: 55 | K59: =IF(F59="","",F59*'🏠 INICIO'!C8)
B60: 56 | K60: =IF(F60="","",F60*'🏠 INICIO'!C8)
B61: 57 | K61: =IF(F61="","",F61*'🏠 INICIO'!C8)
B62: 58 | K62: =IF(F62="","",F62*'🏠 INICIO'!C8)
B63: 59 | K63: =IF(F63="","",F63*'🏠 INICIO'!C8)
B64: 60 | K64: =IF(F64="","",F64*'🏠 INICIO'!C8)
B65: 61 | K65: =IF(F65="","",F65*'🏠 INICIO'!C8)
B66: 62 | K66: =IF(F66="","",F66*'🏠 INICIO'!C8)
B67: 63 | K67: =IF(F67="","",F67*'🏠 INICIO'!C8)
B68: 64 | K68: =IF(F68="","",F68*'🏠 INICIO'!C8)
B69: 65 | K69: =IF(F69="","",F69*'🏠 INICIO'!C8)
B70: 66 | K70: =IF(F70="","",F70*'🏠 INICIO'!C8)
B71: 67 | K71: =IF(F71="","",F71*'🏠 INICIO'!C8)
B72: 68 | K72: =IF(F72="","",F72*'🏠 INICIO'!C8)
B73: 69 | K73: =IF(F73="","",F73*'🏠 INICIO'!C8)
B74: 70 | K74: =IF(F74="","",F74*'🏠 INICIO'!C8)
B75: 71 | K75: =IF(F75="","",F75*'🏠 INICIO'!C8)
B76: 72 | K76: =IF(F76="","",F76*'🏠 INICIO'!C8)
B77: 73 | K77: =IF(F77="","",F77*'🏠 INICIO'!C8)
B78: 74 | K78: =IF(F78="","",F78*'🏠 INICIO'!C8)
B79: 75 | K79: =IF(F79="","",F79*'🏠 INICIO'!C8)
B80: 76 | K80: =IF(F80="","",F80*'🏠 INICIO'!C8)
B81: 77 | K81: =IF(F81="","",F81*'🏠 INICIO'!C8)
B82: 78 | K82: =IF(F82="","",F82*'🏠 INICIO'!C8)
B83: 79 | K83: =IF(F83="","",F83*'🏠 INICIO'!C8)
B84: 80 | K84: =IF(F84="","",F84*'🏠 INICIO'!C8)
B85: 81 | K85: =IF(F85="","",F85*'🏠 INICIO'!C8)
B86: 82 | K86: =IF(F86="","",F86*'🏠 INICIO'!C8)
B87: 83 | K87: =IF(F87="","",F87*'🏠 INICIO'!C8)
B88: 84 | K88: =IF(F88="","",F88*'🏠 INICIO'!C8)
B89: 85 | K89: =IF(F89="","",F89*'🏠 INICIO'!C8)
B90: 86 | K90: =IF(F90="","",F90*'🏠 INICIO'!C8)
B91: 87 | K91: =IF(F91="","",F91*'🏠 INICIO'!C8)
B92: 88 | K92: =IF(F92="","",F92*'🏠 INICIO'!C8)
B93: 89 | K93: =IF(F93="","",F93*'🏠 INICIO'!C8)
B94: 90 | K94: =IF(F94="","",F94*'🏠 INICIO'!C8)
B95: 91 | K95: =IF(F95="","",F95*'🏠 INICIO'!C8)
B96: 92 | K96: =IF(F96="","",F96*'🏠 INICIO'!C8)
B97: 93 | K97: =IF(F97="","",F97*'🏠 INICIO'!C8)
B98: 94 | K98: =IF(F98="","",F98*'🏠 INICIO'!C8)
B99: 95 | K99: =IF(F99="","",F99*'🏠 INICIO'!C8)
B100: 96 | K100: =IF(F100="","",F100*'🏠 INICIO'!C8)
...

Sheet SEG - JUNIO
A1: #VALUE! | B1: ✅ SEGUIMIENTO DE VENTAS — JUNIO
B2: Registra tus ventas del mes. Usa los desplegables para catálogo, método de pago y estado.
B3: 🔍 Filtros (▼): Campaña · Catálogo · Método de pago · Estado | 🟢 PAGADO 🔴 FALTA CANCELAR 🟡 ADELANTO
A4: CAMPAÑA N° | B4: # | C4: CLIENTE | D4: PRODUCTO | E4: CATÁLOGO | F4: PRECIO (S/) | G4: MÉTODO PAGO | H4: ESTADO PAGO | I4: ADELANTO S/ | J4: NOTAS | K4: COMISIÓN (S/)
A5: 2 | B5: 1 | C5: PAOLA | D5: OHM NOW | E5: YANBAL | F5: 90 | G5: EFECTIVO | H5: PAGADO | K5: =IF(F5="","",F5*'🏠 INICIO'!C8) -> 9
A6: 5 | B6: 2 | K6: =IF(F6="","",F6*'🏠 INICIO'!C8)
B7: 3 | K7: =IF(F7="","",F7*'🏠 INICIO'!C8)
B8: 4 | K8: =IF(F8="","",F8*'🏠 INICIO'!C8)
B9: 5 | K9: =IF(F9="","",F9*'🏠 INICIO'!C8)
B10: 6 | K10: =IF(F10="","",F10*'🏠 INICIO'!C8)
B11: 7 | K11: =IF(F11="","",F11*'🏠 INICIO'!C8)
B12: 8 | K12: =IF(F12="","",F12*'🏠 INICIO'!C8)
B13: 9 | K13: =IF(F13="","",F13*'🏠 INICIO'!C8)
B14: 10 | K14: =IF(F14="","",F14*'🏠 INICIO'!C8)
B15: 11 | K15: =IF(F15="","",F15*'🏠 INICIO'!C8)
B16: 12 | K16: =IF(F16="","",F16*'🏠 INICIO'!C8)
B17: 13 | K17: =IF(F17="","",F17*'🏠 INICIO'!C8)
B18: 14 | K18: =IF(F18="","",F18*'🏠 INICIO'!C8)
B19: 15 | K19: =IF(F19="","",F19*'🏠 INICIO'!C8)
B20: 16 | K20: =IF(F20="","",F20*'🏠 INICIO'!C8)
B21: 17 | K21: =IF(F21="","",F21*'🏠 INICIO'!C8)
B22: 18 | K22: =IF(F22="","",F22*'🏠 INICIO'!C8)
B23: 19 | K23: =IF(F23="","",F23*'🏠 INICIO'!C8)
B24: 20 | K24: =IF(F24="","",F24*'🏠 INICIO'!C8)
B25: 21 | K25: =IF(F25="","",F25*'🏠 INICIO'!C8)
B26: 22 | K26: =IF(F26="","",F26*'🏠 INICIO'!C8)
B27: 23 | K27: =IF(F27="","",F27*'🏠 INICIO'!C8)
B28: 24 | K28: =IF(F28="","",F28*'🏠 INICIO'!C8)
B29: 25 | K29: =IF(F29="","",F29*'🏠 INICIO'!C8)
B30: 26 | K30: =IF(F30="","",F30*'🏠 INICIO'!C8)
B31: 27 | K31: =IF(F31="","",F31*'🏠 INICIO'!C8)
B32: 28 | K32: =IF(F32="","",F32*'🏠 INICIO'!C8)
B33: 29 | K33: =IF(F33="","",F33*'🏠 INICIO'!C8)
B34: 30 | K34: =IF(F34="","",F34*'🏠 INICIO'!C8)
B35: 31 | K35: =IF(F35="","",F35*'🏠 INICIO'!C8)
B36: 32 | K36: =IF(F36="","",F36*'🏠 INICIO'!C8)
B37: 33 | K37: =IF(F37="","",F37*'🏠 INICIO'!C8)
B38: 34 | K38: =IF(F38="","",F38*'🏠 INICIO'!C8)
B39: 35 | K39: =IF(F39="","",F39*'🏠 INICIO'!C8)
B40: 36 | K40: =IF(F40="","",F40*'🏠 INICIO'!C8)
B41: 37 | K41: =IF(F41="","",F41*'🏠 INICIO'!C8)
B42: 38 | K42: =IF(F42="","",F42*'🏠 INICIO'!C8)
B43: 39 | K43: =IF(F43="","",F43*'🏠 INICIO'!C8)
B44: 40 | K44: =IF(F44="","",F44*'🏠 INICIO'!C8)
B45: 41 | K45: =IF(F45="","",F45*'🏠 INICIO'!C8)
B46: 42 | K46: =IF(F46="","",F46*'🏠 INICIO'!C8)
B47: 43 | K47: =IF(F47="","",F47*'🏠 INICIO'!C8)
B48: 44 | K48: =IF(F48="","",F48*'🏠 INICIO'!C8)
B49: 45 | K49: =IF(F49="","",F49*'🏠 INICIO'!C8)
B50: 46 | K50: =IF(F50="","",F50*'🏠 INICIO'!C8)
B51: 47 | K51: =IF(F51="","",F51*'🏠 INICIO'!C8)
B52: 48 | K52: =IF(F52="","",F52*'🏠 INICIO'!C8)
B53: 49 | K53: =IF(F53="","",F53*'🏠 INICIO'!C8)
B54: 50 | K54: =IF(F54="","",F54*'🏠 INICIO'!C8)
B55: 51 | K55: =IF(F55="","",F55*'🏠 INICIO'!C8)
B56: 52 | K56: =IF(F56="","",F56*'🏠 INICIO'!C8)
B57: 53 | K57: =IF(F57="","",F57*'🏠 INICIO'!C8)
B58: 54 | K58: =IF(F58="","",F58*'🏠 INICIO'!C8)
B59: 55 | K59: =IF(F59="","",F59*'🏠 INICIO'!C8)
B60: 56 | K60: =IF(F60="","",F60*'🏠 INICIO'!C8)
B61: 57 | K61: =IF(F61="","",F61*'🏠 INICIO'!C8)
B62: 58 | K62: =IF(F62="","",F62*'🏠 INICIO'!C8)
B63: 59 | K63: =IF(F63="","",F63*'🏠 INICIO'!C8)
B64: 60 | K64: =IF(F64="","",F64*'🏠 INICIO'!C8)
B65: 61 | K65: =IF(F65="","",F65*'🏠 INICIO'!C8)
B66: 62 | K66: =IF(F66="","",F66*'🏠 INICIO'!C8)
B67: 63 | K67: =IF(F67="","",F67*'🏠 INICIO'!C8)
B68: 64 | K68: =IF(F68="","",F68*'🏠 INICIO'!C8)
B69: 65 | K69: =IF(F69="","",F69*'🏠 INICIO'!C8)
B70: 66 | K70: =IF(F70="","",F70*'🏠 INICIO'!C8)
B71: 67 | K71: =IF(F71="","",F71*'🏠 INICIO'!C8)
B72: 68 | K72: =IF(F72="","",F72*'🏠 INICIO'!C8)
B73: 69 | K73: =IF(F73="","",F73*'🏠 INICIO'!C8)
B74: 70 | K74: =IF(F74="","",F74*'🏠 INICIO'!C8)
B75: 71 | K75: =IF(F75="","",F75*'🏠 INICIO'!C8)
B76: 72 | K76: =IF(F76="","",F76*'🏠 INICIO'!C8)
B77: 73 | K77: =IF(F77="","",F77*'🏠 INICIO'!C8)
B78: 74 | K78: =IF(F78="","",F78*'🏠 INICIO'!C8)
B79: 75 | K79: =IF(F79="","",F79*'🏠 INICIO'!C8)
B80: 76 | K80: =IF(F80="","",F80*'🏠 INICIO'!C8)
B81: 77 | K81: =IF(F81="","",F81*'🏠 INICIO'!C8)
B82: 78 | K82: =IF(F82="","",F82*'🏠 INICIO'!C8)
B83: 79 | K83: =IF(F83="","",F83*'🏠 INICIO'!C8)
B84: 80 | K84: =IF(F84="","",F84*'🏠 INICIO'!C8)
B85: 81 | K85: =IF(F85="","",F85*'🏠 INICIO'!C8)
B86: 82 | K86: =IF(F86="","",F86*'🏠 INICIO'!C8)
B87: 83 | K87: =IF(F87="","",F87*'🏠 INICIO'!C8)
B88: 84 | K88: =IF(F88="","",F88*'🏠 INICIO'!C8)
B89: 85 | K89: =IF(F89="","",F89*'🏠 INICIO'!C8)
B90: 86 | K90: =IF(F90="","",F90*'🏠 INICIO'!C8)
B91: 87 | K91: =IF(F91="","",F91*'🏠 INICIO'!C8)
B92: 88 | K92: =IF(F92="","",F92*'🏠 INICIO'!C8)
B93: 89 | K93: =IF(F93="","",F93*'🏠 INICIO'!C8)
B94: 90 | K94: =IF(F94="","",F94*'🏠 INICIO'!C8)
B95: 91 | K95: =IF(F95="","",F95*'🏠 INICIO'!C8)
B96: 92 | K96: =IF(F96="","",F96*'🏠 INICIO'!C8)
B97: 93 | K97: =IF(F97="","",F97*'🏠 INICIO'!C8)
B98: 94 | K98: =IF(F98="","",F98*'🏠 INICIO'!C8)
B99: 95 | K99: =IF(F99="","",F99*'🏠 INICIO'!C8)
B100: 96 | K100: =IF(F100="","",F100*'🏠 INICIO'!C8)
...

Sheet SEG - JULIO
A1: #VALUE! | B1: ✅ SEGUIMIENTO DE VENTAS — JULIO
B2: Registra tus ventas del mes. Usa los desplegables para catálogo, método de pago y estado.
B3: 🔍 Filtros (▼): Campaña · Catálogo · Método de pago · Estado | 🟢 PAGADO 🔴 FALTA CANCELAR 🟡 ADELANTO
A4: CAMPAÑA N° | B4: # | C4: CLIENTE | D4: PRODUCTO | E4: CATÁLOGO | F4: PRECIO (S/) | G4: MÉTODO PAGO | H4: ESTADO PAGO | I4: ADELANTO S/ | J4: NOTAS | K4: COMISIÓN (S/)
A5: 2 | B5: 1 | C5: PAOLA | D5: OHM NOW | E5: YANBAL | F5: 90 | G5: EFECTIVO | H5: PAGADO | K5: =IF(F5="","",F5*'🏠 INICIO'!C8) -> 9
A6: 5 | B6: 2 | K6: =IF(F6="","",F6*'🏠 INICIO'!C8)
B7: 3 | K7: =IF(F7="","",F7*'🏠 INICIO'!C8)
B8: 4 | K8: =IF(F8="","",F8*'🏠 INICIO'!C8)
B9: 5 | K9: =IF(F9="","",F9*'🏠 INICIO'!C8)
B10: 6 | K10: =IF(F10="","",F10*'🏠 INICIO'!C8)
B11: 7 | K11: =IF(F11="","",F11*'🏠 INICIO'!C8)
B12: 8 | K12: =IF(F12="","",F12*'🏠 INICIO'!C8)
B13: 9 | K13: =IF(F13="","",F13*'🏠 INICIO'!C8)
B14: 10 | K14: =IF(F14="","",F14*'🏠 INICIO'!C8)
B15: 11 | K15: =IF(F15="","",F15*'🏠 INICIO'!C8)
B16: 12 | K16: =IF(F16="","",F16*'🏠 INICIO'!C8)
B17: 13 | K17: =IF(F17="","",F17*'🏠 INICIO'!C8)
B18: 14 | K18: =IF(F18="","",F18*'🏠 INICIO'!C8)
B19: 15 | K19: =IF(F19="","",F19*'🏠 INICIO'!C8)
B20: 16 | K20: =IF(F20="","",F20*'🏠 INICIO'!C8)
B21: 17 | K21: =IF(F21="","",F21*'🏠 INICIO'!C8)
B22: 18 | K22: =IF(F22="","",F22*'🏠 INICIO'!C8)
B23: 19 | K23: =IF(F23="","",F23*'🏠 INICIO'!C8)
B24: 20 | K24: =IF(F24="","",F24*'🏠 INICIO'!C8)
B25: 21 | K25: =IF(F25="","",F25*'🏠 INICIO'!C8)
B26: 22 | K26: =IF(F26="","",F26*'🏠 INICIO'!C8)
B27: 23 | K27: =IF(F27="","",F27*'🏠 INICIO'!C8)
B28: 24 | K28: =IF(F28="","",F28*'🏠 INICIO'!C8)
B29: 25 | K29: =IF(F29="","",F29*'🏠 INICIO'!C8)
B30: 26 | K30: =IF(F30="","",F30*'🏠 INICIO'!C8)
B31: 27 | K31: =IF(F31="","",F31*'🏠 INICIO'!C8)
B32: 28 | K32: =IF(F32="","",F32*'🏠 INICIO'!C8)
B33: 29 | K33: =IF(F33="","",F33*'🏠 INICIO'!C8)
B34: 30 | K34: =IF(F34="","",F34*'🏠 INICIO'!C8)
B35: 31 | K35: =IF(F35="","",F35*'🏠 INICIO'!C8)
B36: 32 | K36: =IF(F36="","",F36*'🏠 INICIO'!C8)
B37: 33 | K37: =IF(F37="","",F37*'🏠 INICIO'!C8)
B38: 34 | K38: =IF(F38="","",F38*'🏠 INICIO'!C8)
B39: 35 | K39: =IF(F39="","",F39*'🏠 INICIO'!C8)
B40: 36 | K40: =IF(F40="","",F40*'🏠 INICIO'!C8)
B41: 37 | K41: =IF(F41="","",F41*'🏠 INICIO'!C8)
B42: 38 | K42: =IF(F42="","",F42*'🏠 INICIO'!C8)
B43: 39 | K43: =IF(F43="","",F43*'🏠 INICIO'!C8)
B44: 40 | K44: =IF(F44="","",F44*'🏠 INICIO'!C8)
B45: 41 | K45: =IF(F45="","",F45*'🏠 INICIO'!C8)
B46: 42 | K46: =IF(F46="","",F46*'🏠 INICIO'!C8)
B47: 43 | K47: =IF(F47="","",F47*'🏠 INICIO'!C8)
B48: 44 | K48: =IF(F48="","",F48*'🏠 INICIO'!C8)
B49: 45 | K49: =IF(F49="","",F49*'🏠 INICIO'!C8)
B50: 46 | K50: =IF(F50="","",F50*'🏠 INICIO'!C8)
B51: 47 | K51: =IF(F51="","",F51*'🏠 INICIO'!C8)
B52: 48 | K52: =IF(F52="","",F52*'🏠 INICIO'!C8)
B53: 49 | K53: =IF(F53="","",F53*'🏠 INICIO'!C8)
B54: 50 | K54: =IF(F54="","",F54*'🏠 INICIO'!C8)
B55: 51 | K55: =IF(F55="","",F55*'🏠 INICIO'!C8)
B56: 52 | K56: =IF(F56="","",F56*'🏠 INICIO'!C8)
B57: 53 | K57: =IF(F57="","",F57*'🏠 INICIO'!C8)
B58: 54 | K58: =IF(F58="","",F58*'🏠 INICIO'!C8)
B59: 55 | K59: =IF(F59="","",F59*'🏠 INICIO'!C8)
B60: 56 | K60: =IF(F60="","",F60*'🏠 INICIO'!C8)
B61: 57 | K61: =IF(F61="","",F61*'🏠 INICIO'!C8)
B62: 58 | K62: =IF(F62="","",F62*'🏠 INICIO'!C8)
B63: 59 | K63: =IF(F63="","",F63*'🏠 INICIO'!C8)
B64: 60 | K64: =IF(F64="","",F64*'🏠 INICIO'!C8)
B65: 61 | K65: =IF(F65="","",F65*'🏠 INICIO'!C8)
B66: 62 | K66: =IF(F66="","",F66*'🏠 INICIO'!C8)
B67: 63 | K67: =IF(F67="","",F67*'🏠 INICIO'!C8)
B68: 64 | K68: =IF(F68="","",F68*'🏠 INICIO'!C8)
B69: 65 | K69: =IF(F69="","",F69*'🏠 INICIO'!C8)
B70: 66 | K70: =IF(F70="","",F70*'🏠 INICIO'!C8)
B71: 67 | K71: =IF(F71="","",F71*'🏠 INICIO'!C8)
B72: 68 | K72: =IF(F72="","",F72*'🏠 INICIO'!C8)
B73: 69 | K73: =IF(F73="","",F73*'🏠 INICIO'!C8)
B74: 70 | K74: =IF(F74="","",F74*'🏠 INICIO'!C8)
B75: 71 | K75: =IF(F75="","",F75*'🏠 INICIO'!C8)
B76: 72 | K76: =IF(F76="","",F76*'🏠 INICIO'!C8)
B77: 73 | K77: =IF(F77="","",F77*'🏠 INICIO'!C8)
B78: 74 | K78: =IF(F78="","",F78*'🏠 INICIO'!C8)
B79: 75 | K79: =IF(F79="","",F79*'🏠 INICIO'!C8)
B80: 76 | K80: =IF(F80="","",F80*'🏠 INICIO'!C8)
B81: 77 | K81: =IF(F81="","",F81*'🏠 INICIO'!C8)
B82: 78 | K82: =IF(F82="","",F82*'🏠 INICIO'!C8)
B83: 79 | K83: =IF(F83="","",F83*'🏠 INICIO'!C8)
B84: 80 | K84: =IF(F84="","",F84*'🏠 INICIO'!C8)
B85: 81 | K85: =IF(F85="","",F85*'🏠 INICIO'!C8)
B86: 82 | K86: =IF(F86="","",F86*'🏠 INICIO'!C8)
B87: 83 | K87: =IF(F87="","",F87*'🏠 INICIO'!C8)
B88: 84 | K88: =IF(F88="","",F88*'🏠 INICIO'!C8)
B89: 85 | K89: =IF(F89="","",F89*'🏠 INICIO'!C8)
B90: 86 | K90: =IF(F90="","",F90*'🏠 INICIO'!C8)
B91: 87 | K91: =IF(F91="","",F91*'🏠 INICIO'!C8)
B92: 88 | K92: =IF(F92="","",F92*'🏠 INICIO'!C8)
B93: 89 | K93: =IF(F93="","",F93*'🏠 INICIO'!C8)
B94: 90 | K94: =IF(F94="","",F94*'🏠 INICIO'!C8)
B95: 91 | K95: =IF(F95="","",F95*'🏠 INICIO'!C8)
B96: 92 | K96: =IF(F96="","",F96*'🏠 INICIO'!C8)
B97: 93 | K97: =IF(F97="","",F97*'🏠 INICIO'!C8)
B98: 94 | K98: =IF(F98="","",F98*'🏠 INICIO'!C8)
B99: 95 | K99: =IF(F99="","",F99*'🏠 INICIO'!C8)
B100: 96 | K100: =IF(F100="","",F100*'🏠 INICIO'!C8)
...

Sheet SEG - AGOSTO
A1: #VALUE! | B1: ✅ SEGUIMIENTO DE VENTAS — AGOSTO
B2: Registra tus ventas del mes. Usa los desplegables para catálogo, método de pago y estado.
B3: 🔍 Filtros (▼): Campaña · Catálogo · Método de pago · Estado | 🟢 PAGADO 🔴 FALTA CANCELAR 🟡 ADELANTO
A4: CAMPAÑA N° | B4: # | C4: CLIENTE | D4: PRODUCTO | E4: CATÁLOGO | F4: PRECIO (S/) | G4: MÉTODO PAGO | H4: ESTADO PAGO | I4: ADELANTO S/ | J4: NOTAS | K4: COMISIÓN (S/)
A5: 2 | B5: 1 | C5: PAOLA | D5: OHM NOW | E5: YANBAL | F5: 90 | G5: EFECTIVO | H5: PAGADO | K5: =IF(F5="","",F5*'🏠 INICIO'!C8) -> 9
A6: 5 | B6: 2 | K6: =IF(F6="","",F6*'🏠 INICIO'!C8)
B7: 3 | K7: =IF(F7="","",F7*'🏠 INICIO'!C8)
B8: 4 | K8: =IF(F8="","",F8*'🏠 INICIO'!C8)
B9: 5 | K9: =IF(F9="","",F9*'🏠 INICIO'!C8)
B10: 6 | K10: =IF(F10="","",F10*'🏠 INICIO'!C8)
B11: 7 | K11: =IF(F11="","",F11*'🏠 INICIO'!C8)
B12: 8 | K12: =IF(F12="","",F12*'🏠 INICIO'!C8)
B13: 9 | K13: =IF(F13="","",F13*'🏠 INICIO'!C8)
B14: 10 | K14: =IF(F14="","",F14*'🏠 INICIO'!C8)
B15: 11 | K15: =IF(F15="","",F15*'🏠 INICIO'!C8)
B16: 12 | K16: =IF(F16="","",F16*'🏠 INICIO'!C8)
B17: 13 | K17: =IF(F17="","",F17*'🏠 INICIO'!C8)
B18: 14 | K18: =IF(F18="","",F18*'🏠 INICIO'!C8)
B19: 15 | K19: =IF(F19="","",F19*'🏠 INICIO'!C8)
B20: 16 | K20: =IF(F20="","",F20*'🏠 INICIO'!C8)
B21: 17 | K21: =IF(F21="","",F21*'🏠 INICIO'!C8)
B22: 18 | K22: =IF(F22="","",F22*'🏠 INICIO'!C8)
B23: 19 | K23: =IF(F23="","",F23*'🏠 INICIO'!C8)
B24: 20 | K24: =IF(F24="","",F24*'🏠 INICIO'!C8)
B25: 21 | K25: =IF(F25="","",F25*'🏠 INICIO'!C8)
B26: 22 | K26: =IF(F26="","",F26*'🏠 INICIO'!C8)
B27: 23 | K27: =IF(F27="","",F27*'🏠 INICIO'!C8)
B28: 24 | K28: =IF(F28="","",F28*'🏠 INICIO'!C8)
B29: 25 | K29: =IF(F29="","",F29*'🏠 INICIO'!C8)
B30: 26 | K30: =IF(F30="","",F30*'🏠 INICIO'!C8)
B31: 27 | K31: =IF(F31="","",F31*'🏠 INICIO'!C8)
B32: 28 | K32: =IF(F32="","",F32*'🏠 INICIO'!C8)
B33: 29 | K33: =IF(F33="","",F33*'🏠 INICIO'!C8)
B34: 30 | K34: =IF(F34="","",F34*'🏠 INICIO'!C8)
B35: 31 | K35: =IF(F35="","",F35*'🏠 INICIO'!C8)
B36: 32 | K36: =IF(F36="","",F36*'🏠 INICIO'!C8)
B37: 33 | K37: =IF(F37="","",F37*'🏠 INICIO'!C8)
B38: 34 | K38: =IF(F38="","",F38*'🏠 INICIO'!C8)
B39: 35 | K39: =IF(F39="","",F39*'🏠 INICIO'!C8)
B40: 36 | K40: =IF(F40="","",F40*'🏠 INICIO'!C8)
B41: 37 | K41: =IF(F41="","",F41*'🏠 INICIO'!C8)
B42: 38 | K42: =IF(F42="","",F42*'🏠 INICIO'!C8)
B43: 39 | K43: =IF(F43="","",F43*'🏠 INICIO'!C8)
B44: 40 | K44: =IF(F44="","",F44*'🏠 INICIO'!C8)
B45: 41 | K45: =IF(F45="","",F45*'🏠 INICIO'!C8)
B46: 42 | K46: =IF(F46="","",F46*'🏠 INICIO'!C8)
B47: 43 | K47: =IF(F47="","",F47*'🏠 INICIO'!C8)
B48: 44 | K48: =IF(F48="","",F48*'🏠 INICIO'!C8)
B49: 45 | K49: =IF(F49="","",F49*'🏠 INICIO'!C8)
B50: 46 | K50: =IF(F50="","",F50*'🏠 INICIO'!C8)
B51: 47 | K51: =IF(F51="","",F51*'🏠 INICIO'!C8)
B52: 48 | K52: =IF(F52="","",F52*'🏠 INICIO'!C8)
B53: 49 | K53: =IF(F53="","",F53*'🏠 INICIO'!C8)
B54: 50 | K54: =IF(F54="","",F54*'🏠 INICIO'!C8)
B55: 51 | K55: =IF(F55="","",F55*'🏠 INICIO'!C8)
B56: 52 | K56: =IF(F56="","",F56*'🏠 INICIO'!C8)
B57: 53 | K57: =IF(F57="","",F57*'🏠 INICIO'!C8)
B58: 54 | K58: =IF(F58="","",F58*'🏠 INICIO'!C8)
B59: 55 | K59: =IF(F59="","",F59*'🏠 INICIO'!C8)
B60: 56 | K60: =IF(F60="","",F60*'🏠 INICIO'!C8)
B61: 57 | K61: =IF(F61="","",F61*'🏠 INICIO'!C8)
B62: 58 | K62: =IF(F62="","",F62*'🏠 INICIO'!C8)
B63: 59 | K63: =IF(F63="","",F63*'🏠 INICIO'!C8)
B64: 60 | K64: =IF(F64="","",F64*'🏠 INICIO'!C8)
B65: 61 | K65: =IF(F65="","",F65*'🏠 INICIO'!C8)
B66: 62 | K66: =IF(F66="","",F66*'🏠 INICIO'!C8)
B67: 63 | K67: =IF(F67="","",F67*'🏠 INICIO'!C8)
B68: 64 | K68: =IF(F68="","",F68*'🏠 INICIO'!C8)
B69: 65 | K69: =IF(F69="","",F69*'🏠 INICIO'!C8)
B70: 66 | K70: =IF(F70="","",F70*'🏠 INICIO'!C8)
B71: 67 | K71: =IF(F71="","",F71*'🏠 INICIO'!C8)
B72: 68 | K72: =IF(F72="","",F72*'🏠 INICIO'!C8)
B73: 69 | K73: =IF(F73="","",F73*'🏠 INICIO'!C8)
B74: 70 | K74: =IF(F74="","",F74*'🏠 INICIO'!C8)
B75: 71 | K75: =IF(F75="","",F75*'🏠 INICIO'!C8)
B76: 72 | K76: =IF(F76="","",F76*'🏠 INICIO'!C8)
B77: 73 | K77: =IF(F77="","",F77*'🏠 INICIO'!C8)
B78: 74 | K78: =IF(F78="","",F78*'🏠 INICIO'!C8)
B79: 75 | K79: =IF(F79="","",F79*'🏠 INICIO'!C8)
B80: 76 | K80: =IF(F80="","",F80*'🏠 INICIO'!C8)
B81: 77 | K81: =IF(F81="","",F81*'🏠 INICIO'!C8)
B82: 78 | K82: =IF(F82="","",F82*'🏠 INICIO'!C8)
B83: 79 | K83: =IF(F83="","",F83*'🏠 INICIO'!C8)
B84: 80 | K84: =IF(F84="","",F84*'🏠 INICIO'!C8)
B85: 81 | K85: =IF(F85="","",F85*'🏠 INICIO'!C8)
B86: 82 | K86: =IF(F86="","",F86*'🏠 INICIO'!C8)
B87: 83 | K87: =IF(F87="","",F87*'🏠 INICIO'!C8)
B88: 84 | K88: =IF(F88="","",F88*'🏠 INICIO'!C8)
B89: 85 | K89: =IF(F89="","",F89*'🏠 INICIO'!C8)
B90: 86 | K90: =IF(F90="","",F90*'🏠 INICIO'!C8)
B91: 87 | K91: =IF(F91="","",F91*'🏠 INICIO'!C8)
B92: 88 | K92: =IF(F92="","",F92*'🏠 INICIO'!C8)
B93: 89 | K93: =IF(F93="","",F93*'🏠 INICIO'!C8)
B94: 90 | K94: =IF(F94="","",F94*'🏠 INICIO'!C8)
B95: 91 | K95: =IF(F95="","",F95*'🏠 INICIO'!C8)
B96: 92 | K96: =IF(F96="","",F96*'🏠 INICIO'!C8)
B97: 93 | K97: =IF(F97="","",F97*'🏠 INICIO'!C8)
B98: 94 | K98: =IF(F98="","",F98*'🏠 INICIO'!C8)
B99: 95 | K99: =IF(F99="","",F99*'🏠 INICIO'!C8)
B100: 96 | K100: =IF(F100="","",F100*'🏠 INICIO'!C8)
...

Sheet SEG - SEPTIEMBRE
A1: #VALUE! | B1: ✅ SEGUIMIENTO DE VENTAS — SEPTIEMBRE
B2: Registra tus ventas del mes. Usa los desplegables para catálogo, método de pago y estado.
B3: 🔍 Filtros (▼): Campaña · Catálogo · Método de pago · Estado | 🟢 PAGADO 🔴 FALTA CANCELAR 🟡 ADELANTO
A4: CAMPAÑA N° | B4: # | C4: CLIENTE | D4: PRODUCTO | E4: CATÁLOGO | F4: PRECIO (S/) | G4: MÉTODO PAGO | H4: ESTADO PAGO | I4: ADELANTO S/ | J4: NOTAS | K4: COMISIÓN (S/)
A5: 2 | B5: 1 | C5: PAOLA | D5: OHM NOW | E5: YANBAL | F5: 90 | G5: EFECTIVO | H5: PAGADO | K5: =IF(F5="","",F5*'🏠 INICIO'!C8) -> 9
A6: 5 | B6: 2 | K6: =IF(F6="","",F6*'🏠 INICIO'!C8)
B7: 3 | K7: =IF(F7="","",F7*'🏠 INICIO'!C8)
B8: 4 | K8: =IF(F8="","",F8*'🏠 INICIO'!C8)
B9: 5 | K9: =IF(F9="","",F9*'🏠 INICIO'!C8)
B10: 6 | K10: =IF(F10="","",F10*'🏠 INICIO'!C8)
B11: 7 | K11: =IF(F11="","",F11*'🏠 INICIO'!C8)
B12: 8 | K12: =IF(F12="","",F12*'🏠 INICIO'!C8)
B13: 9 | K13: =IF(F13="","",F13*'🏠 INICIO'!C8)
B14: 10 | K14: =IF(F14="","",F14*'🏠 INICIO'!C8)
B15: 11 | K15: =IF(F15="","",F15*'🏠 INICIO'!C8)
B16: 12 | K16: =IF(F16="","",F16*'🏠 INICIO'!C8)
B17: 13 | K17: =IF(F17="","",F17*'🏠 INICIO'!C8)
B18: 14 | K18: =IF(F18="","",F18*'🏠 INICIO'!C8)
B19: 15 | K19: =IF(F19="","",F19*'🏠 INICIO'!C8)
B20: 16 | K20: =IF(F20="","",F20*'🏠 INICIO'!C8)
B21: 17 | K21: =IF(F21="","",F21*'🏠 INICIO'!C8)
B22: 18 | K22: =IF(F22="","",F22*'🏠 INICIO'!C8)
B23: 19 | K23: =IF(F23="","",F23*'🏠 INICIO'!C8)
B24: 20 | K24: =IF(F24="","",F24*'🏠 INICIO'!C8)
B25: 21 | K25: =IF(F25="","",F25*'🏠 INICIO'!C8)
B26: 22 | K26: =IF(F26="","",F26*'🏠 INICIO'!C8)
B27: 23 | K27: =IF(F27="","",F27*'🏠 INICIO'!C8)
B28: 24 | K28: =IF(F28="","",F28*'🏠 INICIO'!C8)
B29: 25 | K29: =IF(F29="","",F29*'🏠 INICIO'!C8)
B30: 26 | K30: =IF(F30="","",F30*'🏠 INICIO'!C8)
B31: 27 | K31: =IF(F31="","",F31*'🏠 INICIO'!C8)
B32: 28 | K32: =IF(F32="","",F32*'🏠 INICIO'!C8)
B33: 29 | K33: =IF(F33="","",F33*'🏠 INICIO'!C8)
B34: 30 | K34: =IF(F34="","",F34*'🏠 INICIO'!C8)
B35: 31 | K35: =IF(F35="","",F35*'🏠 INICIO'!C8)
B36: 32 | K36: =IF(F36="","",F36*'🏠 INICIO'!C8)
B37: 33 | K37: =IF(F37="","",F37*'🏠 INICIO'!C8)
B38: 34 | K38: =IF(F38="","",F38*'🏠 INICIO'!C8)
B39: 35 | K39: =IF(F39="","",F39*'🏠 INICIO'!C8)
B40: 36 | K40: =IF(F40="","",F40*'🏠 INICIO'!C8)
B41: 37 | K41: =IF(F41="","",F41*'🏠 INICIO'!C8)
B42: 38 | K42: =IF(F42="","",F42*'🏠 INICIO'!C8)
B43: 39 | K43: =IF(F43="","",F43*'🏠 INICIO'!C8)
B44: 40 | K44: =IF(F44="","",F44*'🏠 INICIO'!C8)
B45: 41 | K45: =IF(F45="","",F45*'🏠 INICIO'!C8)
B46: 42 | K46: =IF(F46="","",F46*'🏠 INICIO'!C8)
B47: 43 | K47: =IF(F47="","",F47*'🏠 INICIO'!C8)
B48: 44 | K48: =IF(F48="","",F48*'🏠 INICIO'!C8)
B49: 45 | K49: =IF(F49="","",F49*'🏠 INICIO'!C8)
B50: 46 | K50: =IF(F50="","",F50*'🏠 INICIO'!C8)
B51: 47 | K51: =IF(F51="","",F51*'🏠 INICIO'!C8)
B52: 48 | K52: =IF(F52="","",F52*'🏠 INICIO'!C8)
B53: 49 | K53: =IF(F53="","",F53*'🏠 INICIO'!C8)
B54: 50 | K54: =IF(F54="","",F54*'🏠 INICIO'!C8)
B55: 51 | K55: =IF(F55="","",F55*'🏠 INICIO'!C8)
B56: 52 | K56: =IF(F56="","",F56*'🏠 INICIO'!C8)
B57: 53 | K57: =IF(F57="","",F57*'🏠 INICIO'!C8)
B58: 54 | K58: =IF(F58="","",F58*'🏠 INICIO'!C8)
B59: 55 | K59: =IF(F59="","",F59*'🏠 INICIO'!C8)
B60: 56 | K60: =IF(F60="","",F60*'🏠 INICIO'!C8)
B61: 57 | K61: =IF(F61="","",F61*'🏠 INICIO'!C8)
B62: 58 | K62: =IF(F62="","",F62*'🏠 INICIO'!C8)
B63: 59 | K63: =IF(F63="","",F63*'🏠 INICIO'!C8)
B64: 60 | K64: =IF(F64="","",F64*'🏠 INICIO'!C8)
B65: 61 | K65: =IF(F65="","",F65*'🏠 INICIO'!C8)
B66: 62 | K66: =IF(F66="","",F66*'🏠 INICIO'!C8)
B67: 63 | K67: =IF(F67="","",F67*'🏠 INICIO'!C8)
B68: 64 | K68: =IF(F68="","",F68*'🏠 INICIO'!C8)
B69: 65 | K69: =IF(F69="","",F69*'🏠 INICIO'!C8)
B70: 66 | K70: =IF(F70="","",F70*'🏠 INICIO'!C8)
B71: 67 | K71: =IF(F71="","",F71*'🏠 INICIO'!C8)
B72: 68 | K72: =IF(F72="","",F72*'🏠 INICIO'!C8)
B73: 69 | K73: =IF(F73="","",F73*'🏠 INICIO'!C8)
B74: 70 | K74: =IF(F74="","",F74*'🏠 INICIO'!C8)
B75: 71 | K75: =IF(F75="","",F75*'🏠 INICIO'!C8)
B76: 72 | K76: =IF(F76="","",F76*'🏠 INICIO'!C8)
B77: 73 | K77: =IF(F77="","",F77*'🏠 INICIO'!C8)
B78: 74 | K78: =IF(F78="","",F78*'🏠 INICIO'!C8)
B79: 75 | K79: =IF(F79="","",F79*'🏠 INICIO'!C8)
B80: 76 | K80: =IF(F80="","",F80*'🏠 INICIO'!C8)
B81: 77 | K81: =IF(F81="","",F81*'🏠 INICIO'!C8)
B82: 78 | K82: =IF(F82="","",F82*'🏠 INICIO'!C8)
B83: 79 | K83: =IF(F83="","",F83*'🏠 INICIO'!C8)
B84: 80 | K84: =IF(F84="","",F84*'🏠 INICIO'!C8)
B85: 81 | K85: =IF(F85="","",F85*'🏠 INICIO'!C8)
B86: 82 | K86: =IF(F86="","",F86*'🏠 INICIO'!C8)
B87: 83 | K87: =IF(F87="","",F87*'🏠 INICIO'!C8)
B88: 84 | K88: =IF(F88="","",F88*'🏠 INICIO'!C8)
B89: 85 | K89: =IF(F89="","",F89*'🏠 INICIO'!C8)
B90: 86 | K90: =IF(F90="","",F90*'🏠 INICIO'!C8)
B91: 87 | K91: =IF(F91="","",F91*'🏠 INICIO'!C8)
B92: 88 | K92: =IF(F92="","",F92*'🏠 INICIO'!C8)
B93: 89 | K93: =IF(F93="","",F93*'🏠 INICIO'!C8)
B94: 90 | K94: =IF(F94="","",F94*'🏠 INICIO'!C8)
B95: 91 | K95: =IF(F95="","",F95*'🏠 INICIO'!C8)
B96: 92 | K96: =IF(F96="","",F96*'🏠 INICIO'!C8)
B97: 93 | K97: =IF(F97="","",F97*'🏠 INICIO'!C8)
B98: 94 | K98: =IF(F98="","",F98*'🏠 INICIO'!C8)
B99: 95 | K99: =IF(F99="","",F99*'🏠 INICIO'!C8)
B100: 96 | K100: =IF(F100="","",F100*'🏠 INICIO'!C8)
...

Sheet SEG - OCTUBRE
A1: #VALUE! | B1: ✅ SEGUIMIENTO DE VENTAS — OCTUBRE
B2: Registra tus ventas del mes. Usa los desplegables para catálogo, método de pago y estado.
B3: 🔍 Filtros (▼): Campaña · Catálogo · Método de pago · Estado | 🟢 PAGADO 🔴 FALTA CANCELAR 🟡 ADELANTO
A4: CAMPAÑA N° | B4: # | C4: CLIENTE | D4: PRODUCTO | E4: CATÁLOGO | F4: PRECIO (S/) | G4: MÉTODO PAGO | H4: ESTADO PAGO | I4: ADELANTO S/ | J4: NOTAS | K4: COMISIÓN (S/)
A5: 2 | B5: 1 | C5: PAOLA | D5: OHM NOW | E5: YANBAL | F5: 90 | G5: EFECTIVO | H5: PAGADO | K5: =IF(F5="","",F5*'🏠 INICIO'!C8) -> 9
A6: 5 | B6: 2 | K6: =IF(F6="","",F6*'🏠 INICIO'!C8)
B7: 3 | K7: =IF(F7="","",F7*'🏠 INICIO'!C8)
B8: 4 | K8: =IF(F8="","",F8*'🏠 INICIO'!C8)
B9: 5 | K9: =IF(F9="","",F9*'🏠 INICIO'!C8)
B10: 6 | K10: =IF(F10="","",F10*'🏠 INICIO'!C8)
B11: 7 | K11: =IF(F11="","",F11*'🏠 INICIO'!C8)
B12: 8 | K12: =IF(F12="","",F12*'🏠 INICIO'!C8)
B13: 9 | K13: =IF(F13="","",F13*'🏠 INICIO'!C8)
B14: 10 | K14: =IF(F14="","",F14*'🏠 INICIO'!C8)
B15: 11 | K15: =IF(F15="","",F15*'🏠 INICIO'!C8)
B16: 12 | K16: =IF(F16="","",F16*'🏠 INICIO'!C8)
B17: 13 | K17: =IF(F17="","",F17*'🏠 INICIO'!C8)
B18: 14 | K18: =IF(F18="","",F18*'🏠 INICIO'!C8)
B19: 15 | K19: =IF(F19="","",F19*'🏠 INICIO'!C8)
B20: 16 | K20: =IF(F20="","",F20*'🏠 INICIO'!C8)
B21: 17 | K21: =IF(F21="","",F21*'🏠 INICIO'!C8)
B22: 18 | K22: =IF(F22="","",F22*'🏠 INICIO'!C8)
B23: 19 | K23: =IF(F23="","",F23*'🏠 INICIO'!C8)
B24: 20 | K24: =IF(F24="","",F24*'🏠 INICIO'!C8)
B25: 21 | K25: =IF(F25="","",F25*'🏠 INICIO'!C8)
B26: 22 | K26: =IF(F26="","",F26*'🏠 INICIO'!C8)
B27: 23 | K27: =IF(F27="","",F27*'🏠 INICIO'!C8)
B28: 24 | K28: =IF(F28="","",F28*'🏠 INICIO'!C8)
B29: 25 | K29: =IF(F29="","",F29*'🏠 INICIO'!C8)
B30: 26 | K30: =IF(F30="","",F30*'🏠 INICIO'!C8)
B31: 27 | K31: =IF(F31="","",F31*'🏠 INICIO'!C8)
B32: 28 | K32: =IF(F32="","",F32*'🏠 INICIO'!C8)
B33: 29 | K33: =IF(F33="","",F33*'🏠 INICIO'!C8)
B34: 30 | K34: =IF(F34="","",F34*'🏠 INICIO'!C8)
B35: 31 | K35: =IF(F35="","",F35*'🏠 INICIO'!C8)
B36: 32 | K36: =IF(F36="","",F36*'🏠 INICIO'!C8)
B37: 33 | K37: =IF(F37="","",F37*'🏠 INICIO'!C8)
B38: 34 | K38: =IF(F38="","",F38*'🏠 INICIO'!C8)
B39: 35 | K39: =IF(F39="","",F39*'🏠 INICIO'!C8)
B40: 36 | K40: =IF(F40="","",F40*'🏠 INICIO'!C8)
B41: 37 | K41: =IF(F41="","",F41*'🏠 INICIO'!C8)
B42: 38 | K42: =IF(F42="","",F42*'🏠 INICIO'!C8)
B43: 39 | K43: =IF(F43="","",F43*'🏠 INICIO'!C8)
B44: 40 | K44: =IF(F44="","",F44*'🏠 INICIO'!C8)
B45: 41 | K45: =IF(F45="","",F45*'🏠 INICIO'!C8)
B46: 42 | K46: =IF(F46="","",F46*'🏠 INICIO'!C8)
B47: 43 | K47: =IF(F47="","",F47*'🏠 INICIO'!C8)
B48: 44 | K48: =IF(F48="","",F48*'🏠 INICIO'!C8)
B49: 45 | K49: =IF(F49="","",F49*'🏠 INICIO'!C8)
B50: 46 | K50: =IF(F50="","",F50*'🏠 INICIO'!C8)
B51: 47 | K51: =IF(F51="","",F51*'🏠 INICIO'!C8)
B52: 48 | K52: =IF(F52="","",F52*'🏠 INICIO'!C8)
B53: 49 | K53: =IF(F53="","",F53*'🏠 INICIO'!C8)
B54: 50 | K54: =IF(F54="","",F54*'🏠 INICIO'!C8)
B55: 51 | K55: =IF(F55="","",F55*'🏠 INICIO'!C8)
B56: 52 | K56: =IF(F56="","",F56*'🏠 INICIO'!C8)
B57: 53 | K57: =IF(F57="","",F57*'🏠 INICIO'!C8)
B58: 54 | K58: =IF(F58="","",F58*'🏠 INICIO'!C8)
B59: 55 | K59: =IF(F59="","",F59*'🏠 INICIO'!C8)
B60: 56 | K60: =IF(F60="","",F60*'🏠 INICIO'!C8)
B61: 57 | K61: =IF(F61="","",F61*'🏠 INICIO'!C8)
B62: 58 | K62: =IF(F62="","",F62*'🏠 INICIO'!C8)
B63: 59 | K63: =IF(F63="","",F63*'🏠 INICIO'!C8)
B64: 60 | K64: =IF(F64="","",F64*'🏠 INICIO'!C8)
B65: 61 | K65: =IF(F65="","",F65*'🏠 INICIO'!C8)
B66: 62 | K66: =IF(F66="","",F66*'🏠 INICIO'!C8)
B67: 63 | K67: =IF(F67="","",F67*'🏠 INICIO'!C8)
B68: 64 | K68: =IF(F68="","",F68*'🏠 INICIO'!C8)
B69: 65 | K69: =IF(F69="","",F69*'🏠 INICIO'!C8)
B70: 66 | K70: =IF(F70="","",F70*'🏠 INICIO'!C8)
B71: 67 | K71: =IF(F71="","",F71*'🏠 INICIO'!C8)
B72: 68 | K72: =IF(F72="","",F72*'🏠 INICIO'!C8)
B73: 69 | K73: =IF(F73="","",F73*'🏠 INICIO'!C8)
B74: 70 | K74: =IF(F74="","",F74*'🏠 INICIO'!C8)
B75: 71 | K75: =IF(F75="","",F75*'🏠 INICIO'!C8)
B76: 72 | K76: =IF(F76="","",F76*'🏠 INICIO'!C8)
B77: 73 | K77: =IF(F77="","",F77*'🏠 INICIO'!C8)
B78: 74 | K78: =IF(F78="","",F78*'🏠 INICIO'!C8)
B79: 75 | K79: =IF(F79="","",F79*'🏠 INICIO'!C8)
B80: 76 | K80: =IF(F80="","",F80*'🏠 INICIO'!C8)
B81: 77 | K81: =IF(F81="","",F81*'🏠 INICIO'!C8)
B82: 78 | K82: =IF(F82="","",F82*'🏠 INICIO'!C8)
B83: 79 | K83: =IF(F83="","",F83*'🏠 INICIO'!C8)
B84: 80 | K84: =IF(F84="","",F84*'🏠 INICIO'!C8)
B85: 81 | K85: =IF(F85="","",F85*'🏠 INICIO'!C8)
B86: 82 | K86: =IF(F86="","",F86*'🏠 INICIO'!C8)
B87: 83 | K87: =IF(F87="","",F87*'🏠 INICIO'!C8)
B88: 84 | K88: =IF(F88="","",F88*'🏠 INICIO'!C8)
B89: 85 | K89: =IF(F89="","",F89*'🏠 INICIO'!C8)
B90: 86 | K90: =IF(F90="","",F90*'🏠 INICIO'!C8)
B91: 87 | K91: =IF(F91="","",F91*'🏠 INICIO'!C8)
B92: 88 | K92: =IF(F92="","",F92*'🏠 INICIO'!C8)
B93: 89 | K93: =IF(F93="","",F93*'🏠 INICIO'!C8)
B94: 90 | K94: =IF(F94="","",F94*'🏠 INICIO'!C8)
B95: 91 | K95: =IF(F95="","",F95*'🏠 INICIO'!C8)
B96: 92 | K96: =IF(F96="","",F96*'🏠 INICIO'!C8)
B97: 93 | K97: =IF(F97="","",F97*'🏠 INICIO'!C8)
B98: 94 | K98: =IF(F98="","",F98*'🏠 INICIO'!C8)
B99: 95 | K99: =IF(F99="","",F99*'🏠 INICIO'!C8)
B100: 96 | K100: =IF(F100="","",F100*'🏠 INICIO'!C8)
...

Sheet SEG - NOVIEMBRE
A1: #VALUE! | B1: ✅ SEGUIMIENTO DE VENTAS — NOVIEMBRE
B2: Registra tus ventas del mes. Usa los desplegables para catálogo, método de pago y estado.
B3: 🔍 Filtros (▼): Campaña · Catálogo · Método de pago · Estado | 🟢 PAGADO 🔴 FALTA CANCELAR 🟡 ADELANTO
A4: CAMPAÑA N° | B4: # | C4: CLIENTE | D4: PRODUCTO | E4: CATÁLOGO | F4: PRECIO (S/) | G4: MÉTODO PAGO | H4: ESTADO PAGO | I4: ADELANTO S/ | J4: NOTAS | K4: COMISIÓN (S/)
A5: 2 | B5: 1 | C5: PAOLA | D5: OHM NOW | E5: YANBAL | F5: 90 | G5: EFECTIVO | H5: PAGADO | K5: =IF(F5="","",F5*'🏠 INICIO'!C8) -> 9
A6: 5 | B6: 2 | K6: =IF(F6="","",F6*'🏠 INICIO'!C8)
B7: 3 | K7: =IF(F7="","",F7*'🏠 INICIO'!C8)
B8: 4 | K8: =IF(F8="","",F8*'🏠 INICIO'!C8)
B9: 5 | K9: =IF(F9="","",F9*'🏠 INICIO'!C8)
B10: 6 | K10: =IF(F10="","",F10*'🏠 INICIO'!C8)
B11: 7 | K11: =IF(F11="","",F11*'🏠 INICIO'!C8)
B12: 8 | K12: =IF(F12="","",F12*'🏠 INICIO'!C8)
B13: 9 | K13: =IF(F13="","",F13*'🏠 INICIO'!C8)
B14: 10 | K14: =IF(F14="","",F14*'🏠 INICIO'!C8)
B15: 11 | K15: =IF(F15="","",F15*'🏠 INICIO'!C8)
B16: 12 | K16: =IF(F16="","",F16*'🏠 INICIO'!C8)
B17: 13 | K17: =IF(F17="","",F17*'🏠 INICIO'!C8)
B18: 14 | K18: =IF(F18="","",F18*'🏠 INICIO'!C8)
B19: 15 | K19: =IF(F19="","",F19*'🏠 INICIO'!C8)
B20: 16 | K20: =IF(F20="","",F20*'🏠 INICIO'!C8)
B21: 17 | K21: =IF(F21="","",F21*'🏠 INICIO'!C8)
B22: 18 | K22: =IF(F22="","",F22*'🏠 INICIO'!C8)
B23: 19 | K23: =IF(F23="","",F23*'🏠 INICIO'!C8)
B24: 20 | K24: =IF(F24="","",F24*'🏠 INICIO'!C8)
B25: 21 | K25: =IF(F25="","",F25*'🏠 INICIO'!C8)
B26: 22 | K26: =IF(F26="","",F26*'🏠 INICIO'!C8)
B27: 23 | K27: =IF(F27="","",F27*'🏠 INICIO'!C8)
B28: 24 | K28: =IF(F28="","",F28*'🏠 INICIO'!C8)
B29: 25 | K29: =IF(F29="","",F29*'🏠 INICIO'!C8)
B30: 26 | K30: =IF(F30="","",F30*'🏠 INICIO'!C8)
B31: 27 | K31: =IF(F31="","",F31*'🏠 INICIO'!C8)
B32: 28 | K32: =IF(F32="","",F32*'🏠 INICIO'!C8)
B33: 29 | K33: =IF(F33="","",F33*'🏠 INICIO'!C8)
B34: 30 | K34: =IF(F34="","",F34*'🏠 INICIO'!C8)
B35: 31 | K35: =IF(F35="","",F35*'🏠 INICIO'!C8)
B36: 32 | K36: =IF(F36="","",F36*'🏠 INICIO'!C8)
B37: 33 | K37: =IF(F37="","",F37*'🏠 INICIO'!C8)
B38: 34 | K38: =IF(F38="","",F38*'🏠 INICIO'!C8)
B39: 35 | K39: =IF(F39="","",F39*'🏠 INICIO'!C8)
B40: 36 | K40: =IF(F40="","",F40*'🏠 INICIO'!C8)
B41: 37 | K41: =IF(F41="","",F41*'🏠 INICIO'!C8)
B42: 38 | K42: =IF(F42="","",F42*'🏠 INICIO'!C8)
B43: 39 | K43: =IF(F43="","",F43*'🏠 INICIO'!C8)
B44: 40 | K44: =IF(F44="","",F44*'🏠 INICIO'!C8)
B45: 41 | K45: =IF(F45="","",F45*'🏠 INICIO'!C8)
B46: 42 | K46: =IF(F46="","",F46*'🏠 INICIO'!C8)
B47: 43 | K47: =IF(F47="","",F47*'🏠 INICIO'!C8)
B48: 44 | K48: =IF(F48="","",F48*'🏠 INICIO'!C8)
B49: 45 | K49: =IF(F49="","",F49*'🏠 INICIO'!C8)
B50: 46 | K50: =IF(F50="","",F50*'🏠 INICIO'!C8)
B51: 47 | K51: =IF(F51="","",F51*'🏠 INICIO'!C8)
B52: 48 | K52: =IF(F52="","",F52*'🏠 INICIO'!C8)
B53: 49 | K53: =IF(F53="","",F53*'🏠 INICIO'!C8)
B54: 50 | K54: =IF(F54="","",F54*'🏠 INICIO'!C8)
B55: 51 | K55: =IF(F55="","",F55*'🏠 INICIO'!C8)
B56: 52 | K56: =IF(F56="","",F56*'🏠 INICIO'!C8)
B57: 53 | K57: =IF(F57="","",F57*'🏠 INICIO'!C8)
B58: 54 | K58: =IF(F58="","",F58*'🏠 INICIO'!C8)
B59: 55 | K59: =IF(F59="","",F59*'🏠 INICIO'!C8)
B60: 56 | K60: =IF(F60="","",F60*'🏠 INICIO'!C8)
B61: 57 | K61: =IF(F61="","",F61*'🏠 INICIO'!C8)
B62: 58 | K62: =IF(F62="","",F62*'🏠 INICIO'!C8)
B63: 59 | K63: =IF(F63="","",F63*'🏠 INICIO'!C8)
B64: 60 | K64: =IF(F64="","",F64*'🏠 INICIO'!C8)
B65: 61 | K65: =IF(F65="","",F65*'🏠 INICIO'!C8)
B66: 62 | K66: =IF(F66="","",F66*'🏠 INICIO'!C8)
B67: 63 | K67: =IF(F67="","",F67*'🏠 INICIO'!C8)
B68: 64 | K68: =IF(F68="","",F68*'🏠 INICIO'!C8)
B69: 65 | K69: =IF(F69="","",F69*'🏠 INICIO'!C8)
B70: 66 | K70: =IF(F70="","",F70*'🏠 INICIO'!C8)
B71: 67 | K71: =IF(F71="","",F71*'🏠 INICIO'!C8)
B72: 68 | K72: =IF(F72="","",F72*'🏠 INICIO'!C8)
B73: 69 | K73: =IF(F73="","",F73*'🏠 INICIO'!C8)
B74: 70 | K74: =IF(F74="","",F74*'🏠 INICIO'!C8)
B75: 71 | K75: =IF(F75="","",F75*'🏠 INICIO'!C8)
B76: 72 | K76: =IF(F76="","",F76*'🏠 INICIO'!C8)
B77: 73 | K77: =IF(F77="","",F77*'🏠 INICIO'!C8)
B78: 74 | K78: =IF(F78="","",F78*'🏠 INICIO'!C8)
B79: 75 | K79: =IF(F79="","",F79*'🏠 INICIO'!C8)
B80: 76 | K80: =IF(F80="","",F80*'🏠 INICIO'!C8)
B81: 77 | K81: =IF(F81="","",F81*'🏠 INICIO'!C8)
B82: 78 | K82: =IF(F82="","",F82*'🏠 INICIO'!C8)
B83: 79 | K83: =IF(F83="","",F83*'🏠 INICIO'!C8)
B84: 80 | K84: =IF(F84="","",F84*'🏠 INICIO'!C8)
B85: 81 | K85: =IF(F85="","",F85*'🏠 INICIO'!C8)
B86: 82 | K86: =IF(F86="","",F86*'🏠 INICIO'!C8)
B87: 83 | K87: =IF(F87="","",F87*'🏠 INICIO'!C8)
B88: 84 | K88: =IF(F88="","",F88*'🏠 INICIO'!C8)
B89: 85 | K89: =IF(F89="","",F89*'🏠 INICIO'!C8)
B90: 86 | K90: =IF(F90="","",F90*'🏠 INICIO'!C8)
B91: 87 | K91: =IF(F91="","",F91*'🏠 INICIO'!C8)
B92: 88 | K92: =IF(F92="","",F92*'🏠 INICIO'!C8)
B93: 89 | K93: =IF(F93="","",F93*'🏠 INICIO'!C8)
B94: 90 | K94: =IF(F94="","",F94*'🏠 INICIO'!C8)
B95: 91 | K95: =IF(F95="","",F95*'🏠 INICIO'!C8)
B96: 92 | K96: =IF(F96="","",F96*'🏠 INICIO'!C8)
B97: 93 | K97: =IF(F97="","",F97*'🏠 INICIO'!C8)
B98: 94 | K98: =IF(F98="","",F98*'🏠 INICIO'!C8)
B99: 95 | K99: =IF(F99="","",F99*'🏠 INICIO'!C8)
B100: 96 | K100: =IF(F100="","",F100*'🏠 INICIO'!C8)
...

Sheet SEG - DICIEMBRE
A1: #VALUE! | B1: ✅ SEGUIMIENTO DE VENTAS — DICIEMBRE
B2: Registra tus ventas del mes. Usa los desplegables para catálogo, método de pago y estado.
B3: 🔍 Filtros (▼): Campaña · Catálogo · Método de pago · Estado | 🟢 PAGADO 🔴 FALTA CANCELAR 🟡 ADELANTO
A4: CAMPAÑA N° | B4: # | C4: CLIENTE | D4: PRODUCTO | E4: CATÁLOGO | F4: PRECIO (S/) | G4: MÉTODO PAGO | H4: ESTADO PAGO | I4: ADELANTO S/ | J4: NOTAS | K4: COMISIÓN (S/)
A5: 2 | B5: 1 | C5: PAOLA | D5: OHM NOW | E5: YANBAL | F5: 90 | G5: EFECTIVO | H5: PAGADO | K5: =IF(F5="","",F5*'🏠 INICIO'!C8) -> 9
A6: 5 | B6: 2 | K6: =IF(F6="","",F6*'🏠 INICIO'!C8)
B7: 3 | K7: =IF(F7="","",F7*'🏠 INICIO'!C8)
B8: 4 | K8: =IF(F8="","",F8*'🏠 INICIO'!C8)
B9: 5 | K9: =IF(F9="","",F9*'🏠 INICIO'!C8)
B10: 6 | K10: =IF(F10="","",F10*'🏠 INICIO'!C8)
B11: 7 | K11: =IF(F11="","",F11*'🏠 INICIO'!C8)
B12: 8 | K12: =IF(F12="","",F12*'🏠 INICIO'!C8)
B13: 9 | K13: =IF(F13="","",F13*'🏠 INICIO'!C8)
B14: 10 | K14: =IF(F14="","",F14*'🏠 INICIO'!C8)
B15: 11 | K15: =IF(F15="","",F15*'🏠 INICIO'!C8)
B16: 12 | K16: =IF(F16="","",F16*'🏠 INICIO'!C8)
B17: 13 | K17: =IF(F17="","",F17*'🏠 INICIO'!C8)
B18: 14 | K18: =IF(F18="","",F18*'🏠 INICIO'!C8)
B19: 15 | K19: =IF(F19="","",F19*'🏠 INICIO'!C8)
B20: 16 | K20: =IF(F20="","",F20*'🏠 INICIO'!C8)
B21: 17 | K21: =IF(F21="","",F21*'🏠 INICIO'!C8)
B22: 18 | K22: =IF(F22="","",F22*'🏠 INICIO'!C8)
B23: 19 | K23: =IF(F23="","",F23*'🏠 INICIO'!C8)
B24: 20 | K24: =IF(F24="","",F24*'🏠 INICIO'!C8)
B25: 21 | K25: =IF(F25="","",F25*'🏠 INICIO'!C8)
B26: 22 | K26: =IF(F26="","",F26*'🏠 INICIO'!C8)
B27: 23 | K27: =IF(F27="","",F27*'🏠 INICIO'!C8)
B28: 24 | K28: =IF(F28="","",F28*'🏠 INICIO'!C8)
B29: 25 | K29: =IF(F29="","",F29*'🏠 INICIO'!C8)
B30: 26 | K30: =IF(F30="","",F30*'🏠 INICIO'!C8)
B31: 27 | K31: =IF(F31="","",F31*'🏠 INICIO'!C8)
B32: 28 | K32: =IF(F32="","",F32*'🏠 INICIO'!C8)
B33: 29 | K33: =IF(F33="","",F33*'🏠 INICIO'!C8)
B34: 30 | K34: =IF(F34="","",F34*'🏠 INICIO'!C8)
B35: 31 | K35: =IF(F35="","",F35*'🏠 INICIO'!C8)
B36: 32 | K36: =IF(F36="","",F36*'🏠 INICIO'!C8)
B37: 33 | K37: =IF(F37="","",F37*'🏠 INICIO'!C8)
B38: 34 | K38: =IF(F38="","",F38*'🏠 INICIO'!C8)
B39: 35 | K39: =IF(F39="","",F39*'🏠 INICIO'!C8)
B40: 36 | K40: =IF(F40="","",F40*'🏠 INICIO'!C8)
B41: 37 | K41: =IF(F41="","",F41*'🏠 INICIO'!C8)
B42: 38 | K42: =IF(F42="","",F42*'🏠 INICIO'!C8)
B43: 39 | K43: =IF(F43="","",F43*'🏠 INICIO'!C8)
B44: 40 | K44: =IF(F44="","",F44*'🏠 INICIO'!C8)
B45: 41 | K45: =IF(F45="","",F45*'🏠 INICIO'!C8)
B46: 42 | K46: =IF(F46="","",F46*'🏠 INICIO'!C8)
B47: 43 | K47: =IF(F47="","",F47*'🏠 INICIO'!C8)
B48: 44 | K48: =IF(F48="","",F48*'🏠 INICIO'!C8)
B49: 45 | K49: =IF(F49="","",F49*'🏠 INICIO'!C8)
B50: 46 | K50: =IF(F50="","",F50*'🏠 INICIO'!C8)
B51: 47 | K51: =IF(F51="","",F51*'🏠 INICIO'!C8)
B52: 48 | K52: =IF(F52="","",F52*'🏠 INICIO'!C8)
B53: 49 | K53: =IF(F53="","",F53*'🏠 INICIO'!C8)
B54: 50 | K54: =IF(F54="","",F54*'🏠 INICIO'!C8)
B55: 51 | K55: =IF(F55="","",F55*'🏠 INICIO'!C8)
B56: 52 | K56: =IF(F56="","",F56*'🏠 INICIO'!C8)
B57: 53 | K57: =IF(F57="","",F57*'🏠 INICIO'!C8)
B58: 54 | K58: =IF(F58="","",F58*'🏠 INICIO'!C8)
B59: 55 | K59: =IF(F59="","",F59*'🏠 INICIO'!C8)
B60: 56 | K60: =IF(F60="","",F60*'🏠 INICIO'!C8)
B61: 57 | K61: =IF(F61="","",F61*'🏠 INICIO'!C8)
B62: 58 | K62: =IF(F62="","",F62*'🏠 INICIO'!C8)
B63: 59 | K63: =IF(F63="","",F63*'🏠 INICIO'!C8)
B64: 60 | K64: =IF(F64="","",F64*'🏠 INICIO'!C8)
B65: 61 | K65: =IF(F65="","",F65*'🏠 INICIO'!C8)
B66: 62 | K66: =IF(F66="","",F66*'🏠 INICIO'!C8)
B67: 63 | K67: =IF(F67="","",F67*'🏠 INICIO'!C8)
B68: 64 | K68: =IF(F68="","",F68*'🏠 INICIO'!C8)
B69: 65 | K69: =IF(F69="","",F69*'🏠 INICIO'!C8)
B70: 66 | K70: =IF(F70="","",F70*'🏠 INICIO'!C8)
B71: 67 | K71: =IF(F71="","",F71*'🏠 INICIO'!C8)
B72: 68 | K72: =IF(F72="","",F72*'🏠 INICIO'!C8)
B73: 69 | K73: =IF(F73="","",F73*'🏠 INICIO'!C8)
B74: 70 | K74: =IF(F74="","",F74*'🏠 INICIO'!C8)
B75: 71 | K75: =IF(F75="","",F75*'🏠 INICIO'!C8)
B76: 72 | K76: =IF(F76="","",F76*'🏠 INICIO'!C8)
B77: 73 | K77: =IF(F77="","",F77*'🏠 INICIO'!C8)
B78: 74 | K78: =IF(F78="","",F78*'🏠 INICIO'!C8)
B79: 75 | K79: =IF(F79="","",F79*'🏠 INICIO'!C8)
B80: 76 | K80: =IF(F80="","",F80*'🏠 INICIO'!C8)
B81: 77 | K81: =IF(F81="","",F81*'🏠 INICIO'!C8)
B82: 78 | K82: =IF(F82="","",F82*'🏠 INICIO'!C8)
B83: 79 | K83: =IF(F83="","",F83*'🏠 INICIO'!C8)
B84: 80 | K84: =IF(F84="","",F84*'🏠 INICIO'!C8)
B85: 81 | K85: =IF(F85="","",F85*'🏠 INICIO'!C8)
B86: 82 | K86: =IF(F86="","",F86*'🏠 INICIO'!C8)
B87: 83 | K87: =IF(F87="","",F87*'🏠 INICIO'!C8)
B88: 84 | K88: =IF(F88="","",F88*'🏠 INICIO'!C8)
B89: 85 | K89: =IF(F89="","",F89*'🏠 INICIO'!C8)
B90: 86 | K90: =IF(F90="","",F90*'🏠 INICIO'!C8)
B91: 87 | K91: =IF(F91="","",F91*'🏠 INICIO'!C8)
B92: 88 | K92: =IF(F92="","",F92*'🏠 INICIO'!C8)
B93: 89 | K93: =IF(F93="","",F93*'🏠 INICIO'!C8)
B94: 90 | K94: =IF(F94="","",F94*'🏠 INICIO'!C8)
B95: 91 | K95: =IF(F95="","",F95*'🏠 INICIO'!C8)
B96: 92 | K96: =IF(F96="","",F96*'🏠 INICIO'!C8)
B97: 93 | K97: =IF(F97="","",F97*'🏠 INICIO'!C8)
B98: 94 | K98: =IF(F98="","",F98*'🏠 INICIO'!C8)
B99: 95 | K99: =IF(F99="","",F99*'🏠 INICIO'!C8)
B100: 96 | K100: =IF(F100="","",F100*'🏠 INICIO'!C8)
...

Sheet 📊 RESUMEN ANUAL
A1: 📊 DASHBOARD ANUAL — AMYSA 2026 | E1: #VALUE!
A3: MES | B3: VENTAS PAGADAS (S/) | C3: N° PAGADOS | D3: FALTA CANCELAR | E3: COMISIÓN (S/)
A4: ENERO | B4: ='SEG - ENERO'!B108 -> 90 | C4: ='SEG - ENERO'!E108 -> 1 | D4: ='SEG - ENERO'!G108 -> 0 | E4: ='SEG - ENERO'!K108 -> 9
A5: FEBRERO | B5: ='SEG - FEBRERO'!B108 -> 90 | C5: ='SEG - FEBRERO'!E108 -> 1 | D5: ='SEG - FEBRERO'!G108 -> 0 | E5: ='SEG - FEBRERO'!K108 -> 9
A6: MARZO | B6: ='SEG - MARZO'!B108 -> 90 | C6: ='SEG - MARZO'!E108 -> 1 | D6: ='SEG - MARZO'!G108 -> 0 | E6: ='SEG - MARZO'!K108 -> 9
A7: ABRIL | B7: ='SEG - ABRIL'!B108 -> 0 | C7: ='SEG - ABRIL'!E108 -> 0 | D7: ='SEG - ABRIL'!G108 -> 0 | E7: ='SEG - ABRIL'!K108 -> 9
A8: MAYO | B8: ='SEG - MAYO'!B108 -> 90 | C8: ='SEG - MAYO'!E108 -> 1 | D8: ='SEG - MAYO'!G108 -> 0 | E8: ='SEG - MAYO'!K108 -> 9
A9: JUNIO | B9: ='SEG - JUNIO'!B108 -> 90 | C9: ='SEG - JUNIO'!E108 -> 1 | D9: ='SEG - JUNIO'!G108 -> 0 | E9: ='SEG - JUNIO'!K108 -> 9
A10: JULIO | B10: ='SEG - JULIO'!B108 -> 90 | C10: ='SEG - JULIO'!E108 -> 1 | D10: ='SEG - JULIO'!G108 -> 0 | E10: ='SEG - JULIO'!K108 -> 9
A11: AGOSTO | B11: ='SEG - AGOSTO'!B108 -> 90 | C11: ='SEG - AGOSTO'!E108 -> 1 | D11: ='SEG - AGOSTO'!G108 -> 0 | E11: ='SEG - AGOSTO'!K108 -> 9
A12: SEPTIEMBRE | B12: ='SEG - SEPTIEMBRE'!B108 -> 90 | C12: ='SEG - SEPTIEMBRE'!E108 -> 1 | D12: ='SEG - SEPTIEMBRE'!G108 -> 0 | E12: ='SEG - SEPTIEMBRE'!K108 -> 9
A13: OCTUBRE | B13: ='SEG - OCTUBRE'!B108 -> 90 | C13: ='SEG - OCTUBRE'!E108 -> 1 | D13: ='SEG - OCTUBRE'!G108 -> 0 | E13: ='SEG - OCTUBRE'!K108 -> 9
A14: NOVIEMBRE | B14: ='SEG - NOVIEMBRE'!B108 -> 90 | C14: ='SEG - NOVIEMBRE'!E108 -> 1 | D14: ='SEG - NOVIEMBRE'!G108 -> 0 | E14: ='SEG - NOVIEMBRE'!K108 -> 9
A15: DICIEMBRE | B15: ='SEG - DICIEMBRE'!B108 -> 90 | C15: ='SEG - DICIEMBRE'!E108 -> 1 | D15: ='SEG - DICIEMBRE'!G108 -> 0 | E15: ='SEG - DICIEMBRE'!K108 -> 9
A17: TOTAL AÑO | B17: =SUM(B4:B15) -> 990 | C17: =SUM(C4:C15) -> 11 | D17: =SUM(D4:D15) -> 0 | E17: =SUM(E4:E15) -> 108
