Workbook

Sheet 🏠 INICIO
B6: AMYSA · GESTIÓN DE VENTAS POR CATÁLOGO
B7: Controla tu negocio y conoce tu ganancia real · Yanbal · Esika · Cyzone · LBel · Natura · Avon · Farmasi · Oriflame
B9: ⚙️ CONFIGURA TU SISTEMA AQUÍ
B10: 👤 Tu nombre de consultora: | C10: ESCRIBE TU NOMBRE | D10: ← escribe tu nombre aquí
B11: 💰 Tu % de comisión base: | C11: 0.1 | D11: ← lo que gana tu vendedora por vender (o tú, si vendes)
B12: 📅 Año de control: | C12: 2026 | D12: ← el año que estás registrando
B14: 📋 GUÍA DE HOJAS — ¿QUÉ HACE CADA UNA?
B15: 💰 INVENTARIO | C15: Tu menú de productos: ingresa el costo y el margen, y obtienes precio de venta, ganancia y comisión.
B16: 📌 CONFIGURA UNA VEZ. Solo cuando cambian tus costos o agregas un producto.
B17: 📊 CALCULADORA CAMPAÑA | C17: Registra lo que vendiste en UNA campaña y calcula ganancia + comisión al instante.
B18: ✅ ÚSALA CADA CAMPAÑA (cada ~3 semanas).
B19: 📅 SEG — ENERO … DIC | C19: Registro detallado de cada venta: cliente, producto, pago, estado y comisión.
B20: 📝 ÚSALA DIARIO. Anota cada venta en el mes que corresponde.
B21: 📊 RESUMEN ANUAL | C21: Dashboard de todo el año: ventas, comisiones y gráfico mes a mes.
B22: 👀 SOLO LECTURA. Se calcula solo con lo que vas registrando.
B24: 🎨 LEYENDA DE COLORES EN LAS TABLAS
B25: 🔵 Celda azul sobre fondo amarillo | C25: Aquí TÚ escribes los datos (nombre, producto, precio, cantidad…)
B26: ⚫ Celda azul sobre fondo claro | C26: Se calcula sola automáticamente — NO la edites
B27: 🟠 Celda naranja | C27: Tu % de margen — puedes editarlo por producto
B28: 🟢 Celda verde | C28: Pagado / dinero que entra / tu ganancia
B29: 🔴 Celda roja | C29: Falta cancelar / costo / dinero que sale
B31: 💡 Empieza en INVENTARIO definiendo tus productos y márgenes. Cada campaña usa la CALCULADORA CAMPAÑA, anota tus ventas en la hoja del mes (SEG) y mira tu RESUMEN ANUAL crecer mes a mes. ¡Tú puedes! 🌸

Sheet 💰 INVENTARIO
A1: 💰 INVENTARIO — Precios y Ganancia por Producto
A2: Ingresa tu COSTO y tu % de MARGEN. El sistema calcula solo el precio de venta, tu ganancia y la comisión de tu vendedora.
A3: ⚙️ COMISIÓN GLOBAL (se toma de INICIO): | F3: ='🏠 INICIO'!$C$11 -> 0.1 | G3: ← cámbiala en la hoja INICIO
A4: # | B4: CATÁLOGO | C4: PRODUCTO | D4: 💰 COSTO (lo que pagas) | E4: 📈 % MARGEN | F4: 🏷️ PRECIO VENTA (auto) | G4: 💵 GANANCIA S/ | H4: 🏆 COMISIÓN % | I4: 💎 COMISIÓN S/ | J4: ✅ GANANCIA NETA
A5: 1 | B5: NATURA | C5: Crema Tododía Ciruela y Flor de Vainilla | D5: 20 | E5: 0.3 | F5: =IF(D5<>"",D5/(1-E5)/(1-H5),"") -> 31.746032 | G5: =IF(D5<>"",D5/(1-E5)-D5,"") -> 8.5714286 | H5: ='🏠 INICIO'!$C$11 -> 0.1 | I5: =IF(F5<>"",F5*H5,"") -> 3.1746032 | J5: =IF(G5<>"",G5,"") -> 8.5714286
A6: 2 | B6: CYZONE | C6: Mini Chic Colonia | D6: 15 | E6: 0.3 | F6: =IF(D6<>"",D6/(1-E6)/(1-H6),"") -> 23.809524 | G6: =IF(D6<>"",D6/(1-E6)-D6,"") -> 6.4285714 | H6: ='🏠 INICIO'!$C$11 -> 0.1 | I6: =IF(F6<>"",F6*H6,"") -> 2.3809524 | J6: =IF(G6<>"",G6,"") -> 6.4285714
A7: 3 | B7: ESIKA | C7: Expression Magic Rímel | D7: 18 | E7: 0.35 | F7: =IF(D7<>"",D7/(1-E7)/(1-H7),"") -> 30.769231 | G7: =IF(D7<>"",D7/(1-E7)-D7,"") -> 9.6923077 | H7: ='🏠 INICIO'!$C$11 -> 0.1 | I7: =IF(F7<>"",F7*H7,"") -> 3.0769231 | J7: =IF(G7<>"",G7,"") -> 9.6923077
A8: 4 | B8: YANBAL | C8: Kit Perfume Dulce Vanidad | D8: 65 | E8: 0.36 | F8: =IF(D8<>"",D8/(1-E8)/(1-H8),"") -> 112.84722 | G8: =IF(D8<>"",D8/(1-E8)-D8,"") -> 36.5625 | H8: ='🏠 INICIO'!$C$11 -> 0.1 | I8: =IF(F8<>"",F8*H8,"") -> 11.284722 | J8: =IF(G8<>"",G8,"") -> 36.5625
A9: 5 | B9: AVON | C9: Anew Gold Crema Facial | D9: 35.5 | E9: 0.3 | F9: =IF(D9<>"",D9/(1-E9)/(1-H9),"") -> 56.349206 | G9: =IF(D9<>"",D9/(1-E9)-D9,"") -> 15.214286 | H9: ='🏠 INICIO'!$C$11 -> 0.1 | I9: =IF(F9<>"",F9*H9,"") -> 5.6349206 | J9: =IF(G9<>"",G9,"") -> 15.214286
A10: 6 | F10: =IF(D10<>"",D10/(1-E10)/(1-H10),"") | G10: =IF(D10<>"",D10/(1-E10)-D10,"") | H10: ='🏠 INICIO'!$C$11 -> 0.1 | I10: =IF(F10<>"",F10*H10,"") | J10: =IF(G10<>"",G10,"")
A11: 7 | F11: =IF(D11<>"",D11/(1-E11)/(1-H11),"") | G11: =IF(D11<>"",D11/(1-E11)-D11,"") | H11: ='🏠 INICIO'!$C$11 -> 0.1 | I11: =IF(F11<>"",F11*H11,"") | J11: =IF(G11<>"",G11,"")
A12: 8 | F12: =IF(D12<>"",D12/(1-E12)/(1-H12),"") | G12: =IF(D12<>"",D12/(1-E12)-D12,"") | H12: ='🏠 INICIO'!$C$11 -> 0.1 | I12: =IF(F12<>"",F12*H12,"") | J12: =IF(G12<>"",G12,"")
A13: 9 | F13: =IF(D13<>"",D13/(1-E13)/(1-H13),"") | G13: =IF(D13<>"",D13/(1-E13)-D13,"") | H13: ='🏠 INICIO'!$C$11 -> 0.1 | I13: =IF(F13<>"",F13*H13,"") | J13: =IF(G13<>"",G13,"")
A14: 10 | F14: =IF(D14<>"",D14/(1-E14)/(1-H14),"") | G14: =IF(D14<>"",D14/(1-E14)-D14,"") | H14: ='🏠 INICIO'!$C$11 -> 0.1 | I14: =IF(F14<>"",F14*H14,"") | J14: =IF(G14<>"",G14,"")
A15: 11 | F15: =IF(D15<>"",D15/(1-E15)/(1-H15),"") | G15: =IF(D15<>"",D15/(1-E15)-D15,"") | H15: ='🏠 INICIO'!$C$11 -> 0.1 | I15: =IF(F15<>"",F15*H15,"") | J15: =IF(G15<>"",G15,"")
A16: 12 | F16: =IF(D16<>"",D16/(1-E16)/(1-H16),"") | G16: =IF(D16<>"",D16/(1-E16)-D16,"") | H16: ='🏠 INICIO'!$C$11 -> 0.1 | I16: =IF(F16<>"",F16*H16,"") | J16: =IF(G16<>"",G16,"")
A17: 13 | F17: =IF(D17<>"",D17/(1-E17)/(1-H17),"") | G17: =IF(D17<>"",D17/(1-E17)-D17,"") | H17: ='🏠 INICIO'!$C$11 -> 0.1 | I17: =IF(F17<>"",F17*H17,"") | J17: =IF(G17<>"",G17,"")
A18: 14 | F18: =IF(D18<>"",D18/(1-E18)/(1-H18),"") | G18: =IF(D18<>"",D18/(1-E18)-D18,"") | H18: ='🏠 INICIO'!$C$11 -> 0.1 | I18: =IF(F18<>"",F18*H18,"") | J18: =IF(G18<>"",G18,"")
A19: 15 | F19: =IF(D19<>"",D19/(1-E19)/(1-H19),"") | G19: =IF(D19<>"",D19/(1-E19)-D19,"") | H19: ='🏠 INICIO'!$C$11 -> 0.1 | I19: =IF(F19<>"",F19*H19,"") | J19: =IF(G19<>"",G19,"")
A20: 16 | F20: =IF(D20<>"",D20/(1-E20)/(1-H20),"") | G20: =IF(D20<>"",D20/(1-E20)-D20,"") | H20: ='🏠 INICIO'!$C$11 -> 0.1 | I20: =IF(F20<>"",F20*H20,"") | J20: =IF(G20<>"",G20,"")
A21: 17 | F21: =IF(D21<>"",D21/(1-E21)/(1-H21),"") | G21: =IF(D21<>"",D21/(1-E21)-D21,"") | H21: ='🏠 INICIO'!$C$11 -> 0.1 | I21: =IF(F21<>"",F21*H21,"") | J21: =IF(G21<>"",G21,"")
... A54: 50 | F54: =IF(D54<>"",D54/(1-E54)/(1-H54),"") | G54: =IF(D54<>"",D54/(1-E54)-D54,"") | H54: ='🏠 INICIO'!$C$11 -> 0.1 | I54: =IF(F54<>"",F54*H54,"") | J54: =IF(G54<>"",G54,"")
A55: 📊 TOTALES | D55: =SUM(D5:D54) -> 153.5 | F55: =SUM(F5:F54) -> 255.52121 | G55: =SUM(G5:G54) -> 76.469093 | I55: =SUM(I5:I54) -> 25.552121 | J55: =SUM(J5:J54) -> 76.469093
A57: 🟡 ¿CÓMO SE CALCULA TU PRECIO DE VENTA?
A58: PASO 1 → | B58: PRECIO CON GANANCIA = Costo ÷ (1 − margen). Ej: margen 30% → divides entre 0.70 para que tu 30% quede DENTRO del precio.
A59: PASO 2 → | B59: PRECIO FINAL DE VENTA = Precio con ganancia ÷ (1 − comisión). Ej: comisión 10% → divides entre 0.90 para que la comisión quede DENTRO.
A60: PASO 3 → | B60: TU GANANCIA = Precio con ganancia − Costo. COMISIÓN VENDEDORA = Precio final × comisión.
A61: ✅ EJEMPLO: Costo S/15, margen 30%, comisión 10% → Precio con ganancia = 15 ÷ 0.70 = S/21.43 → Precio final = 21.43 ÷ 0.90 = S/23.81 | Tu ganancia = S/6.43 · Comisión vendedora = S/2.38
A63: 🔑 ¿QUÉ SIGNIFICA CADA COLUMNA?
A64: 💰 COSTO | B64: Lo que TÚ pagas al catálogo por el producto.
A65: 📈 % MARGEN | B65: Tu ganancia deseada. 30% = de cada S/100 que vendes, S/30 son tuyos.
A66: 🏷️ PRECIO VENTA | B66: Lo que le cobras al cliente. Ya incluye tu ganancia + la comisión.
A67: 💵 GANANCIA S/ | B67: Lo que ganas TÚ en soles por cada producto.
A68: 💎 COMISIÓN S/ | B68: Lo que le pagas a tu vendedora por venderlo.
A69: ✅ GANANCIA NETA | B69: Lo que REALMENTE te queda a ti (tu margen).

Sheet 📊 CALCULADORA CAMPAÑA
A1: 📊 CALCULADORA DE CAMPAÑA — Registra lo que vendiste esta campaña
A2: Úsala cada campaña (cada ~3 semanas). Ingresa costo y % de ganancia; el precio, la comisión y tu ganancia se calculan solos.
A3: CAMPAÑA N°: | B3: 1 | C3: MES: | D3: JUNIO | E3: % COMISIÓN: | F3: ='🏠 INICIO'!$C$11 -> 0.1 | G3: ← se toma de INICIO
A4: # | B4: MES | C4: CATÁLOGO | D4: PRODUCTO | E4: 💰 COSTO | F4: 📈 % GANANCIA | G4: 🏷️ PRECIO VENTA | H4: 💵 MARGEN S/ | I4: 🏆 COM. % | J4: 💎 COM. S/ | K4: ✅ GANANCIA NETA
A5: 1 | B5: JUNIO | C5: NATURA | D5: Crema Corporal Tododía | E5: 20 | F5: 0.36 | G5: =IF(E5<>"",E5/(1-F5)/(1-$F$3),"") -> 34.722222 | H5: =IF(E5<>"",E5/(1-F5)-E5,"") -> 11.25 | I5: =$F$3 -> 0.1 | J5: =IF(G5<>"",G5*$F$3,"") -> 3.4722222 | K5: =IF(H5<>"",H5,"") -> 11.25
A6: 2 | B6: JUNIO | C6: ESIKA | D6: Expression Magic Rímel | E6: 21 | F6: 0.35 | G6: =IF(E6<>"",E6/(1-F6)/(1-$F$3),"") -> 35.897436 | H6: =IF(E6<>"",E6/(1-F6)-E6,"") -> 11.307692 | I6: =$F$3 -> 0.1 | J6: =IF(G6<>"",G6*$F$3,"") -> 3.5897436 | K6: =IF(H6<>"",H6,"") -> 11.307692
A7: 3 | B7: JUNIO | C7: CYZONE | D7: Mini Chic Colonia | E7: 12 | F7: 0.3 | G7: =IF(E7<>"",E7/(1-F7)/(1-$F$3),"") -> 19.047619 | H7: =IF(E7<>"",E7/(1-F7)-E7,"") -> 5.1428571 | I7: =$F$3 -> 0.1 | J7: =IF(G7<>"",G7*$F$3,"") -> 1.9047619 | K7: =IF(H7<>"",H7,"") -> 5.1428571
A8: 4 | B8: JUNIO | C8: YANBAL | D8: Kit Perfume Dulce Vanidad | E8: 65 | F8: 0.36 | G8: =IF(E8<>"",E8/(1-F8)/(1-$F$3),"") -> 112.84722 | H8: =IF(E8<>"",E8/(1-F8)-E8,"") -> 36.5625 | I8: =$F$3 -> 0.1 | J8: =IF(G8<>"",G8*$F$3,"") -> 11.284722 | K8: =IF(H8<>"",H8,"") -> 36.5625
A9: 5 | B9: JUNIO | C9: AVON | D9: Anew Gold Crema Facial | E9: 35.5 | F9: 0.3 | G9: =IF(E9<>"",E9/(1-F9)/(1-$F$3),"") -> 56.349206 | H9: =IF(E9<>"",E9/(1-F9)-E9,"") -> 15.214286 | I9: =$F$3 -> 0.1 | J9: =IF(G9<>"",G9*$F$3,"") -> 5.6349206 | K9: =IF(H9<>"",H9,"") -> 15.214286
A10: 6 | B10: JUNIO | C10: ORIFLAME | D10: Giordani Gold Serum | E10: 51 | F10: 0.3 | G10: =IF(E10<>"",E10/(1-F10)/(1-$F$3),"") -> 80.952381 | H10: =IF(E10<>"",E10/(1-F10)-E10,"") -> 21.857143 | I10: =$F$3 -> 0.1 | J10: =IF(G10<>"",G10*$F$3,"") -> 8.0952381 | K10: =IF(H10<>"",H10,"") -> 21.857143
A11: 7 | G11: =IF(E11<>"",E11/(1-F11)/(1-$F$3),"") | H11: =IF(E11<>"",E11/(1-F11)-E11,"") | I11: =$F$3 -> 0.1 | J11: =IF(G11<>"",G11*$F$3,"") | K11: =IF(H11<>"",H11,"")
A12: 8 | G12: =IF(E12<>"",E12/(1-F12)/(1-$F$3),"") | H12: =IF(E12<>"",E12/(1-F12)-E12,"") | I12: =$F$3 -> 0.1 | J12: =IF(G12<>"",G12*$F$3,"") | K12: =IF(H12<>"",H12,"")
A13: 9 | G13: =IF(E13<>"",E13/(1-F13)/(1-$F$3),"") | H13: =IF(E13<>"",E13/(1-F13)-E13,"") | I13: =$F$3 -> 0.1 | J13: =IF(G13<>"",G13*$F$3,"") | K13: =IF(H13<>"",H13,"")
A14: 10 | G14: =IF(E14<>"",E14/(1-F14)/(1-$F$3),"") | H14: =IF(E14<>"",E14/(1-F14)-E14,"") | I14: =$F$3 -> 0.1 | J14: =IF(G14<>"",G14*$F$3,"") | K14: =IF(H14<>"",H14,"")
A15: 11 | G15: =IF(E15<>"",E15/(1-F15)/(1-$F$3),"") | H15: =IF(E15<>"",E15/(1-F15)-E15,"") | I15: =$F$3 -> 0.1 | J15: =IF(G15<>"",G15*$F$3,"") | K15: =IF(H15<>"",H15,"")
A16: 12 | G16: =IF(E16<>"",E16/(1-F16)/(1-$F$3),"") | H16: =IF(E16<>"",E16/(1-F16)-E16,"") | I16: =$F$3 -> 0.1 | J16: =IF(G16<>"",G16*$F$3,"") | K16: =IF(H16<>"",H16,"")
A17: 13 | G17: =IF(E17<>"",E17/(1-F17)/(1-$F$3),"") | H17: =IF(E17<>"",E17/(1-F17)-E17,"") | I17: =$F$3 -> 0.1 | J17: =IF(G17<>"",G17*$F$3,"") | K17: =IF(H17<>"",H17,"")
A18: 14 | G18: =IF(E18<>"",E18/(1-F18)/(1-$F$3),"") | H18: =IF(E18<>"",E18/(1-F18)-E18,"") | I18: =$F$3 -> 0.1 | J18: =IF(G18<>"",G18*$F$3,"") | K18: =IF(H18<>"",H18,"")
A19: 15 | G19: =IF(E19<>"",E19/(1-F19)/(1-$F$3),"") | H19: =IF(E19<>"",E19/(1-F19)-E19,"") | I19: =$F$3 -> 0.1 | J19: =IF(G19<>"",G19*$F$3,"") | K19: =IF(H19<>"",H19,"")
A20: 16 | G20: =IF(E20<>"",E20/(1-F20)/(1-$F$3),"") | H20: =IF(E20<>"",E20/(1-F20)-E20,"") | I20: =$F$3 -> 0.1 | J20: =IF(G20<>"",G20*$F$3,"") | K20: =IF(H20<>"",H20,"")
A21: 17 | G21: =IF(E21<>"",E21/(1-F21)/(1-$F$3),"") | H21: =IF(E21<>"",E21/(1-F21)-E21,"") | I21: =$F$3 -> 0.1 | J21: =IF(G21<>"",G21*$F$3,"") | K21: =IF(H21<>"",H21,"")
A22: 18 | G22: =IF(E22<>"",E22/(1-F22)/(1-$F$3),"") | H22: =IF(E22<>"",E22/(1-F22)-E22,"") | I22: =$F$3 -> 0.1 | J22: =IF(G22<>"",G22*$F$3,"") | K22: =IF(H22<>"",H22,"")
... A54: 50 | G54: =IF(E54<>"",E54/(1-F54)/(1-$F$3),"") | H54: =IF(E54<>"",E54/(1-F54)-E54,"") | I54: =$F$3 -> 0.1 | J54: =IF(G54<>"",G54*$F$3,"") | K54: =IF(H54<>"",H54,"")
A55: 📊 TOTALES DE ESTA CAMPAÑA | E55: =SUM(E5:E54) -> 204.5 | G55: =SUM(G5:G54) -> 339.81609 | H55: =SUM(H5:H54) -> 101.33448 | J55: =SUM(J5:J54) -> 33.981609 | K55: =SUM(K5:K54) -> 101.33448
A57: 📈 RESUMEN DE ESTA CAMPAÑA
A58: 💰 VENTAS TOTALES | C58: 🏆 COMISIÓN TOTAL | E58: 💵 GANANCIA NETA | G58: 📦 PRODUCTOS VENDIDOS
A59: =SUM(G5:G54) -> 339.81609 | C59: =SUM(J5:J54) -> 33.981609 | E59: =SUM(K5:K54) -> 101.33448 | G59: =COUNTA(D5:D54) -> 6

Sheet SEG - ENERO
A1: ✅ SEGUIMIENTO DE VENTAS — ENERO
A2: Registra tus ventas del mes. Usa los desplegables ▼ para Campaña, Catálogo, Método de pago y Estado.
A3: 🟢 PAGADO 🔴 FALTA CANCELAR 🟡 ADELANTO
A4: CAMPAÑA N° | B4: # | C4: CLIENTE | D4: PRODUCTO | E4: CATÁLOGO | F4: PRECIO (S/) | G4: MÉTODO PAGO | H4: ESTADO PAGO | I4: ADELANTO S/ | J4: NOTAS | K4: COMISIÓN (S/)
A5: 1 | B5: 1 | C5: PAOLA | D5: Crema Tododía Ciruela | E5: NATURA | F5: 25 | G5: EFECTIVO | H5: PAGADO | K5: =IF(F5<>"",F5*'🏠 INICIO'!$C$11,"") -> 2.5
B6: 2 | K6: =IF(F6<>"",F6*'🏠 INICIO'!$C$11,"")
B7: 3 | K7: =IF(F7<>"",F7*'🏠 INICIO'!$C$11,"")
B8: 4 | K8: =IF(F8<>"",F8*'🏠 INICIO'!$C$11,"")
B9: 5 | K9: =IF(F9<>"",F9*'🏠 INICIO'!$C$11,"")
B10: 6 | K10: =IF(F10<>"",F10*'🏠 INICIO'!$C$11,"")
B11: 7 | K11: =IF(F11<>"",F11*'🏠 INICIO'!$C$11,"")
B12: 8 | K12: =IF(F12<>"",F12*'🏠 INICIO'!$C$11,"")
B13: 9 | K13: =IF(F13<>"",F13*'🏠 INICIO'!$C$11,"")
B14: 10 | K14: =IF(F14<>"",F14*'🏠 INICIO'!$C$11,"")
B15: 11 | K15: =IF(F15<>"",F15*'🏠 INICIO'!$C$11,"")
B16: 12 | K16: =IF(F16<>"",F16*'🏠 INICIO'!$C$11,"")
B17: 13 | K17: =IF(F17<>"",F17*'🏠 INICIO'!$C$11,"")
... B54: 50 | K54: =IF(F54<>"",F54*'🏠 INICIO'!$C$11,"")
A56: 📊 RESUMEN DEL MES — ENERO
A57: 💰 TOTAL VENDIDO (S/) | C57: 🟢 PAGADOS | E57: 🔴 FALTA CANCELAR | G57: 🟡 ADELANTOS (S/) | I57: 💎 COMISIÓN DEL MES (S/)
A58: =SUM(F5:F54) -> 25 | C58: =COUNTIF(H5:H54,"PAGADO") -> 1 | E58: =COUNTIF(H5:H54,"FALTA CANCELAR") -> 0 | G58: =SUM(I5:I54) -> 0 | I58: =SUM(K5:K54) -> 2.5

Sheet SEG - FEBRERO
A1: ✅ SEGUIMIENTO DE VENTAS — FEBRERO
A2: Registra tus ventas del mes. Usa los desplegables ▼ para Campaña, Catálogo, Método de pago y Estado.
A3: 🟢 PAGADO 🔴 FALTA CANCELAR 🟡 ADELANTO
A4: CAMPAÑA N° | B4: # | C4: CLIENTE | D4: PRODUCTO | E4: CATÁLOGO | F4: PRECIO (S/) | G4: MÉTODO PAGO | H4: ESTADO PAGO | I4: ADELANTO S/ | J4: NOTAS | K4: COMISIÓN (S/)
B5: 1 | K5: =IF(F5<>"",F5*'🏠 INICIO'!$C$11,"")
B6: 2 | K6: =IF(F6<>"",F6*'🏠 INICIO'!$C$11,"")
B7: 3 | K7: =IF(F7<>"",F7*'🏠 INICIO'!$C$11,"")
B8: 4 | K8: =IF(F8<>"",F8*'🏠 INICIO'!$C$11,"")
B9: 5 | K9: =IF(F9<>"",F9*'🏠 INICIO'!$C$11,"")
B10: 6 | K10: =IF(F10<>"",F10*'🏠 INICIO'!$C$11,"")
B11: 7 | K11: =IF(F11<>"",F11*'🏠 INICIO'!$C$11,"")
B12: 8 | K12: =IF(F12<>"",F12*'🏠 INICIO'!$C$11,"")
B13: 9 | K13: =IF(F13<>"",F13*'🏠 INICIO'!$C$11,"")
B14: 10 | K14: =IF(F14<>"",F14*'🏠 INICIO'!$C$11,"")
B15: 11 | K15: =IF(F15<>"",F15*'🏠 INICIO'!$C$11,"")
B16: 12 | K16: =IF(F16<>"",F16*'🏠 INICIO'!$C$11,"")
... B54: 50 | K54: =IF(F54<>"",F54*'🏠 INICIO'!$C$11,"")
A56: 📊 RESUMEN DEL MES — FEBRERO
A57: 💰 TOTAL VENDIDO (S/) | C57: 🟢 PAGADOS | E57: 🔴 FALTA CANCELAR | G57: 🟡 ADELANTOS (S/) | I57: 💎 COMISIÓN DEL MES (S/)
A58: =SUM(F5:F54) -> 0 | C58: =COUNTIF(H5:H54,"PAGADO") -> 0 | E58: =COUNTIF(H5:H54,"FALTA CANCELAR") -> 0 | G58: =SUM(I5:I54) -> 0 | I58: =SUM(K5:K54) -> 0

Sheet SEG - MARZO
A1: ✅ SEGUIMIENTO DE VENTAS — MARZO
A2: Registra tus ventas del mes. Usa los desplegables ▼ para Campaña, Catálogo, Método de pago y Estado.
A3: 🟢 PAGADO 🔴 FALTA CANCELAR 🟡 ADELANTO
A4: CAMPAÑA N° | B4: # | C4: CLIENTE | D4: PRODUCTO | E4: CATÁLOGO | F4: PRECIO (S/) | G4: MÉTODO PAGO | H4: ESTADO PAGO | I4: ADELANTO S/ | J4: NOTAS | K4: COMISIÓN (S/)
B5: 1 | K5: =IF(F5<>"",F5*'🏠 INICIO'!$C$11,"")
B6: 2 | K6: =IF(F6<>"",F6*'🏠 INICIO'!$C$11,"")
B7: 3 | K7: =IF(F7<>"",F7*'🏠 INICIO'!$C$11,"")
B8: 4 | K8: =IF(F8<>"",F8*'🏠 INICIO'!$C$11,"")
B9: 5 | K9: =IF(F9<>"",F9*'🏠 INICIO'!$C$11,"")
B10: 6 | K10: =IF(F10<>"",F10*'🏠 INICIO'!$C$11,"")
B11: 7 | K11: =IF(F11<>"",F11*'🏠 INICIO'!$C$11,"")
B12: 8 | K12: =IF(F12<>"",F12*'🏠 INICIO'!$C$11,"")
B13: 9 | K13: =IF(F13<>"",F13*'🏠 INICIO'!$C$11,"")
B14: 10 | K14: =IF(F14<>"",F14*'🏠 INICIO'!$C$11,"")
B15: 11 | K15: =IF(F15<>"",F15*'🏠 INICIO'!$C$11,"")
B16: 12 | K16: =IF(F16<>"",F16*'🏠 INICIO'!$C$11,"")
... B54: 50 | K54: =IF(F54<>"",F54*'🏠 INICIO'!$C$11,"")
A56: 📊 RESUMEN DEL MES — MARZO
A57: 💰 TOTAL VENDIDO (S/) | C57: 🟢 PAGADOS | E57: 🔴 FALTA CANCELAR | G57: 🟡 ADELANTOS (S/) | I57: 💎 COMISIÓN DEL MES (S/)
A58: =SUM(F5:F54) -> 0 | C58: =COUNTIF(H5:H54,"PAGADO") -> 0 | E58: =COUNTIF(H5:H54,"FALTA CANCELAR") -> 0 | G58: =SUM(I5:I54) -> 0 | I58: =SUM(K5:K54) -> 0

Sheet SEG - ABRIL
A1: ✅ SEGUIMIENTO DE VENTAS — ABRIL
A2: Registra tus ventas del mes. Usa los desplegables ▼ para Campaña, Catálogo, Método de pago y Estado.
A3: 🟢 PAGADO 🔴 FALTA CANCELAR 🟡 ADELANTO
A4: CAMPAÑA N° | B4: # | C4: CLIENTE | D4: PRODUCTO | E4: CATÁLOGO | F4: PRECIO (S/) | G4: MÉTODO PAGO | H4: ESTADO PAGO | I4: ADELANTO S/ | J4: NOTAS | K4: COMISIÓN (S/)
B5: 1 | K5: =IF(F5<>"",F5*'🏠 INICIO'!$C$11,"")
B6: 2 | K6: =IF(F6<>"",F6*'🏠 INICIO'!$C$11,"")
B7: 3 | K7: =IF(F7<>"",F7*'🏠 INICIO'!$C$11,"")
B8: 4 | K8: =IF(F8<>"",F8*'🏠 INICIO'!$C$11,"")
B9: 5 | K9: =IF(F9<>"",F9*'🏠 INICIO'!$C$11,"")
B10: 6 | K10: =IF(F10<>"",F10*'🏠 INICIO'!$C$11,"")
B11: 7 | K11: =IF(F11<>"",F11*'🏠 INICIO'!$C$11,"")
B12: 8 | K12: =IF(F12<>"",F12*'🏠 INICIO'!$C$11,"")
B13: 9 | K13: =IF(F13<>"",F13*'🏠 INICIO'!$C$11,"")
B14: 10 | K14: =IF(F14<>"",F14*'🏠 INICIO'!$C$11,"")
B15: 11 | K15: =IF(F15<>"",F15*'🏠 INICIO'!$C$11,"")
B16: 12 | K16: =IF(F16<>"",F16*'🏠 INICIO'!$C$11,"")
... B54: 50 | K54: =IF(F54<>"",F54*'🏠 INICIO'!$C$11,"")
A56: 📊 RESUMEN DEL MES — ABRIL
A57: 💰 TOTAL VENDIDO (S/) | C57: 🟢 PAGADOS | E57: 🔴 FALTA CANCELAR | G57: 🟡 ADELANTOS (S/) | I57: 💎 COMISIÓN DEL MES (S/)
A58: =SUM(F5:F54) -> 0 | C58: =COUNTIF(H5:H54,"PAGADO") -> 0 | E58: =COUNTIF(H5:H54,"FALTA CANCELAR") -> 0 | G58: =SUM(I5:I54) -> 0 | I58: =SUM(K5:K54) -> 0

Sheet SEG - MAYO
A1: ✅ SEGUIMIENTO DE VENTAS — MAYO
A2: Registra tus ventas del mes. Usa los desplegables ▼ para Campaña, Catálogo, Método de pago y Estado.
A3: 🟢 PAGADO 🔴 FALTA CANCELAR 🟡 ADELANTO
A4: CAMPAÑA N° | B4: # | C4: CLIENTE | D4: PRODUCTO | E4: CATÁLOGO | F4: PRECIO (S/) | G4: MÉTODO PAGO | H4: ESTADO PAGO | I4: ADELANTO S/ | J4: NOTAS | K4: COMISIÓN (S/)
B5: 1 | K5: =IF(F5<>"",F5*'🏠 INICIO'!$C$11,"")
B6: 2 | K6: =IF(F6<>"",F6*'🏠 INICIO'!$C$11,"")
B7: 3 | K7: =IF(F7<>"",F7*'🏠 INICIO'!$C$11,"")
B8: 4 | K8: =IF(F8<>"",F8*'🏠 INICIO'!$C$11,"")
B9: 5 | K9: =IF(F9<>"",F9*'🏠 INICIO'!$C$11,"")
B10: 6 | K10: =IF(F10<>"",F10*'🏠 INICIO'!$C$11,"")
B11: 7 | K11: =IF(F11<>"",F11*'🏠 INICIO'!$C$11,"")
B12: 8 | K12: =IF(F12<>"",F12*'🏠 INICIO'!$C$11,"")
B13: 9 | K13: =IF(F13<>"",F13*'🏠 INICIO'!$C$11,"")
B14: 10 | K14: =IF(F14<>"",F14*'🏠 INICIO'!$C$11,"")
B15: 11 | K15: =IF(F15<>"",F15*'🏠 INICIO'!$C$11,"")
B16: 12 | K16: =IF(F16<>"",F16*'🏠 INICIO'!$C$11,"")
... B54: 50 | K54: =IF(F54<>"",F54*'🏠 INICIO'!$C$11,"")
A56: 📊 RESUMEN DEL MES — MAYO
A57: 💰 TOTAL VENDIDO (S/) | C57: 🟢 PAGADOS | E57: 🔴 FALTA CANCELAR | G57: 🟡 ADELANTOS (S/) | I57: 💎 COMISIÓN DEL MES (S/)
A58: =SUM(F5:F54) -> 0 | C58: =COUNTIF(H5:H54,"PAGADO") -> 0 | E58: =COUNTIF(H5:H54,"FALTA CANCELAR") -> 0 | G58: =SUM(I5:I54) -> 0 | I58: =SUM(K5:K54) -> 0

Sheet SEG - JUNIO
A1: ✅ SEGUIMIENTO DE VENTAS — JUNIO
A2: Registra tus ventas del mes. Usa los desplegables ▼ para Campaña, Catálogo, Método de pago y Estado.
A3: 🟢 PAGADO 🔴 FALTA CANCELAR 🟡 ADELANTO
A4: CAMPAÑA N° | B4: # | C4: CLIENTE | D4: PRODUCTO | E4: CATÁLOGO | F4: PRECIO (S/) | G4: MÉTODO PAGO | H4: ESTADO PAGO | I4: ADELANTO S/ | J4: NOTAS | K4: COMISIÓN (S/)
B5: 1 | K5: =IF(F5<>"",F5*'🏠 INICIO'!$C$11,"")
B6: 2 | K6: =IF(F6<>"",F6*'🏠 INICIO'!$C$11,"")
B7: 3 | K7: =IF(F7<>"",F7*'🏠 INICIO'!$C$11,"")
B8: 4 | K8: =IF(F8<>"",F8*'🏠 INICIO'!$C$11,"")
B9: 5 | K9: =IF(F9<>"",F9*'🏠 INICIO'!$C$11,"")
B10: 6 | K10: =IF(F10<>"",F10*'🏠 INICIO'!$C$11,"")
B11: 7 | K11: =IF(F11<>"",F11*'🏠 INICIO'!$C$11,"")
B12: 8 | K12: =IF(F12<>"",F12*'🏠 INICIO'!$C$11,"")
B13: 9 | K13: =IF(F13<>"",F13*'🏠 INICIO'!$C$11,"")
B14: 10 | K14: =IF(F14<>"",F14*'🏠 INICIO'!$C$11,"")
B15: 11 | K15: =IF(F15<>"",F15*'🏠 INICIO'!$C$11,"")
B16: 12 | K16: =IF(F16<>"",F16*'🏠 INICIO'!$C$11,"")
... B54: 50 | K54: =IF(F54<>"",F54*'🏠 INICIO'!$C$11,"")
A56: 📊 RESUMEN DEL MES — JUNIO
A57: 💰 TOTAL VENDIDO (S/) | C57: 🟢 PAGADOS | E57: 🔴 FALTA CANCELAR | G57: 🟡 ADELANTOS (S/) | I57: 💎 COMISIÓN DEL MES (S/)
A58: =SUM(F5:F54) -> 0 | C58: =COUNTIF(H5:H54,"PAGADO") -> 0 | E58: =COUNTIF(H5:H54,"FALTA CANCELAR") -> 0 | G58: =SUM(I5:I54) -> 0 | I58: =SUM(K5:K54) -> 0

Sheet SEG - JULIO
A1: ✅ SEGUIMIENTO DE VENTAS — JULIO
A2: Registra tus ventas del mes. Usa los desplegables ▼ para Campaña, Catálogo, Método de pago y Estado.
A3: 🟢 PAGADO 🔴 FALTA CANCELAR 🟡 ADELANTO
A4: CAMPAÑA N° | B4: # | C4: CLIENTE | D4: PRODUCTO | E4: CATÁLOGO | F4: PRECIO (S/) | G4: MÉTODO PAGO | H4: ESTADO PAGO | I4: ADELANTO S/ | J4: NOTAS | K4: COMISIÓN (S/)
B5: 1 | K5: =IF(F5<>"",F5*'🏠 INICIO'!$C$11,"")
B6: 2 | K6: =IF(F6<>"",F6*'🏠 INICIO'!$C$11,"")
B7: 3 | K7: =IF(F7<>"",F7*'🏠 INICIO'!$C$11,"")
B8: 4 | K8: =IF(F8<>"",F8*'🏠 INICIO'!$C$11,"")
B9: 5 | K9: =IF(F9<>"",F9*'🏠 INICIO'!$C$11,"")
B10: 6 | K10: =IF(F10<>"",F10*'🏠 INICIO'!$C$11,"")
B11: 7 | K11: =IF(F11<>"",F11*'🏠 INICIO'!$C$11,"")
B12: 8 | K12: =IF(F12<>"",F12*'🏠 INICIO'!$C$11,"")
B13: 9 | K13: =IF(F13<>"",F13*'🏠 INICIO'!$C$11,"")
B14: 10 | K14: =IF(F14<>"",F14*'🏠 INICIO'!$C$11,"")
B15: 11 | K15: =IF(F15<>"",F15*'🏠 INICIO'!$C$11,"")
B16: 12 | K16: =IF(F16<>"",F16*'🏠 INICIO'!$C$11,"")
... B54: 50 | K54: =IF(F54<>"",F54*'🏠 INICIO'!$C$11,"")
A56: 📊 RESUMEN DEL MES — JULIO
A57: 💰 TOTAL VENDIDO (S/) | C57: 🟢 PAGADOS | E57: 🔴 FALTA CANCELAR | G57: 🟡 ADELANTOS (S/) | I57: 💎 COMISIÓN DEL MES (S/)
A58: =SUM(F5:F54) -> 0 | C58: =COUNTIF(H5:H54,"PAGADO") -> 0 | E58: =COUNTIF(H5:H54,"FALTA CANCELAR") -> 0 | G58: =SUM(I5:I54) -> 0 | I58: =SUM(K5:K54) -> 0

Sheet SEG - AGOSTO
A1: ✅ SEGUIMIENTO DE VENTAS — AGOSTO
A2: Registra tus ventas del mes. Usa los desplegables ▼ para Campaña, Catálogo, Método de pago y Estado.
A3: 🟢 PAGADO 🔴 FALTA CANCELAR 🟡 ADELANTO
A4: CAMPAÑA N° | B4: # | C4: CLIENTE | D4: PRODUCTO | E4: CATÁLOGO | F4: PRECIO (S/) | G4: MÉTODO PAGO | H4: ESTADO PAGO | I4: ADELANTO S/ | J4: NOTAS | K4: COMISIÓN (S/)
B5: 1 | K5: =IF(F5<>"",F5*'🏠 INICIO'!$C$11,"")
B6: 2 | K6: =IF(F6<>"",F6*'🏠 INICIO'!$C$11,"")
B7: 3 | K7: =IF(F7<>"",F7*'🏠 INICIO'!$C$11,"")
B8: 4 | K8: =IF(F8<>"",F8*'🏠 INICIO'!$C$11,"")
B9: 5 | K9: =IF(F9<>"",F9*'🏠 INICIO'!$C$11,"")
B10: 6 | K10: =IF(F10<>"",F10*'🏠 INICIO'!$C$11,"")
B11: 7 | K11: =IF(F11<>"",F11*'🏠 INICIO'!$C$11,"")
B12: 8 | K12: =IF(F12<>"",F12*'🏠 INICIO'!$C$11,"")
B13: 9 | K13: =IF(F13<>"",F13*'🏠 INICIO'!$C$11,"")
B14: 10 | K14: =IF(F14<>"",F14*'🏠 INICIO'!$C$11,"")
B15: 11 | K15: =IF(F15<>"",F15*'🏠 INICIO'!$C$11,"")
B16: 12 | K16: =IF(F16<>"",F16*'🏠 INICIO'!$C$11,"")
... B54: 50 | K54: =IF(F54<>"",F54*'🏠 INICIO'!$C$11,"")
A56: 📊 RESUMEN DEL MES — AGOSTO
A57: 💰 TOTAL VENDIDO (S/) | C57: 🟢 PAGADOS | E57: 🔴 FALTA CANCELAR | G57: 🟡 ADELANTOS (S/) | I57: 💎 COMISIÓN DEL MES (S/)
A58: =SUM(F5:F54) -> 0 | C58: =COUNTIF(H5:H54,"PAGADO") -> 0 | E58: =COUNTIF(H5:H54,"FALTA CANCELAR") -> 0 | G58: =SUM(I5:I54) -> 0 | I58: =SUM(K5:K54) -> 0

Sheet SEG - SEPTIEMBRE
A1: ✅ SEGUIMIENTO DE VENTAS — SEPTIEMBRE
A2: Registra tus ventas del mes. Usa los desplegables ▼ para Campaña, Catálogo, Método de pago y Estado.
A3: 🟢 PAGADO 🔴 FALTA CANCELAR 🟡 ADELANTO
A4: CAMPAÑA N° | B4: # | C4: CLIENTE | D4: PRODUCTO | E4: CATÁLOGO | F4: PRECIO (S/) | G4: MÉTODO PAGO | H4: ESTADO PAGO | I4: ADELANTO S/ | J4: NOTAS | K4: COMISIÓN (S/)
B5: 1 | K5: =IF(F5<>"",F5*'🏠 INICIO'!$C$11,"")
B6: 2 | K6: =IF(F6<>"",F6*'🏠 INICIO'!$C$11,"")
B7: 3 | K7: =IF(F7<>"",F7*'🏠 INICIO'!$C$11,"")
B8: 4 | K8: =IF(F8<>"",F8*'🏠 INICIO'!$C$11,"")
B9: 5 | K9: =IF(F9<>"",F9*'🏠 INICIO'!$C$11,"")
B10: 6 | K10: =IF(F10<>"",F10*'🏠 INICIO'!$C$11,"")
B11: 7 | K11: =IF(F11<>"",F11*'🏠 INICIO'!$C$11,"")
B12: 8 | K12: =IF(F12<>"",F12*'🏠 INICIO'!$C$11,"")
B13: 9 | K13: =IF(F13<>"",F13*'🏠 INICIO'!$C$11,"")
B14: 10 | K14: =IF(F14<>"",F14*'🏠 INICIO'!$C$11,"")
B15: 11 | K15: =IF(F15<>"",F15*'🏠 INICIO'!$C$11,"")
B16: 12 | K16: =IF(F16<>"",F16*'🏠 INICIO'!$C$11,"")
... B54: 50 | K54: =IF(F54<>"",F54*'🏠 INICIO'!$C$11,"")
A56: 📊 RESUMEN DEL MES — SEPTIEMBRE
A57: 💰 TOTAL VENDIDO (S/) | C57: 🟢 PAGADOS | E57: 🔴 FALTA CANCELAR | G57: 🟡 ADELANTOS (S/) | I57: 💎 COMISIÓN DEL MES (S/)
A58: =SUM(F5:F54) -> 0 | C58: =COUNTIF(H5:H54,"PAGADO") -> 0 | E58: =COUNTIF(H5:H54,"FALTA CANCELAR") -> 0 | G58: =SUM(I5:I54) -> 0 | I58: =SUM(K5:K54) -> 0

Sheet SEG - OCTUBRE
A1: ✅ SEGUIMIENTO DE VENTAS — OCTUBRE
A2: Registra tus ventas del mes. Usa los desplegables ▼ para Campaña, Catálogo, Método de pago y Estado.
A3: 🟢 PAGADO 🔴 FALTA CANCELAR 🟡 ADELANTO
A4: CAMPAÑA N° | B4: # | C4: CLIENTE | D4: PRODUCTO | E4: CATÁLOGO | F4: PRECIO (S/) | G4: MÉTODO PAGO | H4: ESTADO PAGO | I4: ADELANTO S/ | J4: NOTAS | K4: COMISIÓN (S/)
B5: 1 | K5: =IF(F5<>"",F5*'🏠 INICIO'!$C$11,"")
B6: 2 | K6: =IF(F6<>"",F6*'🏠 INICIO'!$C$11,"")
B7: 3 | K7: =IF(F7<>"",F7*'🏠 INICIO'!$C$11,"")
B8: 4 | K8: =IF(F8<>"",F8*'🏠 INICIO'!$C$11,"")
B9: 5 | K9: =IF(F9<>"",F9*'🏠 INICIO'!$C$11,"")
B10: 6 | K10: =IF(F10<>"",F10*'🏠 INICIO'!$C$11,"")
B11: 7 | K11: =IF(F11<>"",F11*'🏠 INICIO'!$C$11,"")
B12: 8 | K12: =IF(F12<>"",F12*'🏠 INICIO'!$C$11,"")
B13: 9 | K13: =IF(F13<>"",F13*'🏠 INICIO'!$C$11,"")
B14: 10 | K14: =IF(F14<>"",F14*'🏠 INICIO'!$C$11,"")
B15: 11 | K15: =IF(F15<>"",F15*'🏠 INICIO'!$C$11,"")
B16: 12 | K16: =IF(F16<>"",F16*'🏠 INICIO'!$C$11,"")
... B54: 50 | K54: =IF(F54<>"",F54*'🏠 INICIO'!$C$11,"")
A56: 📊 RESUMEN DEL MES — OCTUBRE
A57: 💰 TOTAL VENDIDO (S/) | C57: 🟢 PAGADOS | E57: 🔴 FALTA CANCELAR | G57: 🟡 ADELANTOS (S/) | I57: 💎 COMISIÓN DEL MES (S/)
A58: =SUM(F5:F54) -> 0 | C58: =COUNTIF(H5:H54,"PAGADO") -> 0 | E58: =COUNTIF(H5:H54,"FALTA CANCELAR") -> 0 | G58: =SUM(I5:I54) -> 0 | I58: =SUM(K5:K54) -> 0

Sheet SEG - NOVIEMBRE
A1: ✅ SEGUIMIENTO DE VENTAS — NOVIEMBRE
A2: Registra tus ventas del mes. Usa los desplegables ▼ para Campaña, Catálogo, Método de pago y Estado.
A3: 🟢 PAGADO 🔴 FALTA CANCELAR 🟡 ADELANTO
A4: CAMPAÑA N° | B4: # | C4: CLIENTE | D4: PRODUCTO | E4: CATÁLOGO | F4: PRECIO (S/) | G4: MÉTODO PAGO | H4: ESTADO PAGO | I4: ADELANTO S/ | J4: NOTAS | K4: COMISIÓN (S/)
B5: 1 | K5: =IF(F5<>"",F5*'🏠 INICIO'!$C$11,"")
B6: 2 | K6: =IF(F6<>"",F6*'🏠 INICIO'!$C$11,"")
B7: 3 | K7: =IF(F7<>"",F7*'🏠 INICIO'!$C$11,"")
B8: 4 | K8: =IF(F8<>"",F8*'🏠 INICIO'!$C$11,"")
B9: 5 | K9: =IF(F9<>"",F9*'🏠 INICIO'!$C$11,"")
B10: 6 | K10: =IF(F10<>"",F10*'🏠 INICIO'!$C$11,"")
B11: 7 | K11: =IF(F11<>"",F11*'🏠 INICIO'!$C$11,"")
B12: 8 | K12: =IF(F12<>"",F12*'🏠 INICIO'!$C$11,"")
B13: 9 | K13: =IF(F13<>"",F13*'🏠 INICIO'!$C$11,"")
B14: 10 | K14: =IF(F14<>"",F14*'🏠 INICIO'!$C$11,"")
B15: 11 | K15: =IF(F15<>"",F15*'🏠 INICIO'!$C$11,"")
B16: 12 | K16: =IF(F16<>"",F16*'🏠 INICIO'!$C$11,"")
... B54: 50 | K54: =IF(F54<>"",F54*'🏠 INICIO'!$C$11,"")
A56: 📊 RESUMEN DEL MES — NOVIEMBRE
A57: 💰 TOTAL VENDIDO (S/) | C57: 🟢 PAGADOS | E57: 🔴 FALTA CANCELAR | G57: 🟡 ADELANTOS (S/) | I57: 💎 COMISIÓN DEL MES (S/)
A58: =SUM(F5:F54) -> 0 | C58: =COUNTIF(H5:H54,"PAGADO") -> 0 | E58: =COUNTIF(H5:H54,"FALTA CANCELAR") -> 0 | G58: =SUM(I5:I54) -> 0 | I58: =SUM(K5:K54) -> 0

Sheet SEG - DICIEMBRE
A1: ✅ SEGUIMIENTO DE VENTAS — DICIEMBRE
A2: Registra tus ventas del mes. Usa los desplegables ▼ para Campaña, Catálogo, Método de pago y Estado.
A3: 🟢 PAGADO 🔴 FALTA CANCELAR 🟡 ADELANTO
A4: CAMPAÑA N° | B4: # | C4: CLIENTE | D4: PRODUCTO | E4: CATÁLOGO | F4: PRECIO (S/) | G4: MÉTODO PAGO | H4: ESTADO PAGO | I4: ADELANTO S/ | J4: NOTAS | K4: COMISIÓN (S/)
B5: 1 | K5: =IF(F5<>"",F5*'🏠 INICIO'!$C$11,"")
B6: 2 | K6: =IF(F6<>"",F6*'🏠 INICIO'!$C$11,"")
B7: 3 | K7: =IF(F7<>"",F7*'🏠 INICIO'!$C$11,"")
B8: 4 | K8: =IF(F8<>"",F8*'🏠 INICIO'!$C$11,"")
B9: 5 | K9: =IF(F9<>"",F9*'🏠 INICIO'!$C$11,"")
B10: 6 | K10: =IF(F10<>"",F10*'🏠 INICIO'!$C$11,"")
B11: 7 | K11: =IF(F11<>"",F11*'🏠 INICIO'!$C$11,"")
B12: 8 | K12: =IF(F12<>"",F12*'🏠 INICIO'!$C$11,"")
B13: 9 | K13: =IF(F13<>"",F13*'🏠 INICIO'!$C$11,"")
B14: 10 | K14: =IF(F14<>"",F14*'🏠 INICIO'!$C$11,"")
B15: 11 | K15: =IF(F15<>"",F15*'🏠 INICIO'!$C$11,"")
B16: 12 | K16: =IF(F16<>"",F16*'🏠 INICIO'!$C$11,"")
... B54: 50 | K54: =IF(F54<>"",F54*'🏠 INICIO'!$C$11,"")
A56: 📊 RESUMEN DEL MES — DICIEMBRE
A57: 💰 TOTAL VENDIDO (S/) | C57: 🟢 PAGADOS | E57: 🔴 FALTA CANCELAR | G57: 🟡 ADELANTOS (S/) | I57: 💎 COMISIÓN DEL MES (S/)
A58: =SUM(F5:F54) -> 0 | C58: =COUNTIF(H5:H54,"PAGADO") -> 0 | E58: =COUNTIF(H5:H54,"FALTA CANCELAR") -> 0 | G58: =SUM(I5:I54) -> 0 | I58: =SUM(K5:K54) -> 0

Sheet 📊 RESUMEN ANUAL
A1: ="📊 DASHBOARD ANUAL — AMYSA "&'🏠 INICIO'!$C$12 -> 📊 DASHBOARD ANUAL — AMYSA 2026
A2: MES | B2: 💰 VENTAS PAGADAS (S/) | C2: 🟢 N° PAGADOS | D2: 🔴 FALTA CANCELAR | E2: 💎 COMISIÓN (S/)
A3: ENERO | B3: =SUMIF('SEG - ENERO'!H5:H54,"PAGADO",'SEG - ENERO'!F5:F54) -> 25 | C3: ='SEG - ENERO'!C58 -> 1 | D3: ='SEG - ENERO'!E58 -> 0 | E3: ='SEG - ENERO'!I58 -> 2.5
A4: FEBRERO | B4: =SUMIF('SEG - FEBRERO'!H5:H54,"PAGADO",'SEG - FEBRERO'!F5:F54) -> 0 | C4: ='SEG - FEBRERO'!C58 -> 0 | D4: ='SEG - FEBRERO'!E58 -> 0 | E4: ='SEG - FEBRERO'!I58 -> 0
A5: MARZO | B5: =SUMIF('SEG - MARZO'!H5:H54,"PAGADO",'SEG - MARZO'!F5:F54) -> 0 | C5: ='SEG - MARZO'!C58 -> 0 | D5: ='SEG - MARZO'!E58 -> 0 | E5: ='SEG - MARZO'!I58 -> 0
A6: ABRIL | B6: =SUMIF('SEG - ABRIL'!H5:H54,"PAGADO",'SEG - ABRIL'!F5:F54) -> 0 | C6: ='SEG - ABRIL'!C58 -> 0 | D6: ='SEG - ABRIL'!E58 -> 0 | E6: ='SEG - ABRIL'!I58 -> 0
A7: MAYO | B7: =SUMIF('SEG - MAYO'!H5:H54,"PAGADO",'SEG - MAYO'!F5:F54) -> 0 | C7: ='SEG - MAYO'!C58 -> 0 | D7: ='SEG - MAYO'!E58 -> 0 | E7: ='SEG - MAYO'!I58 -> 0
A8: JUNIO | B8: =SUMIF('SEG - JUNIO'!H5:H54,"PAGADO",'SEG - JUNIO'!F5:F54) -> 0 | C8: ='SEG - JUNIO'!C58 -> 0 | D8: ='SEG - JUNIO'!E58 -> 0 | E8: ='SEG - JUNIO'!I58 -> 0
A9: JULIO | B9: =SUMIF('SEG - JULIO'!H5:H54,"PAGADO",'SEG - JULIO'!F5:F54) -> 0 | C9: ='SEG - JULIO'!C58 -> 0 | D9: ='SEG - JULIO'!E58 -> 0 | E9: ='SEG - JULIO'!I58 -> 0
A10: AGOSTO | B10: =SUMIF('SEG - AGOSTO'!H5:H54,"PAGADO",'SEG - AGOSTO'!F5:F54) -> 0 | C10: ='SEG - AGOSTO'!C58 -> 0 | D10: ='SEG - AGOSTO'!E58 -> 0 | E10: ='SEG - AGOSTO'!I58 -> 0
A11: SEPTIEMBRE | B11: =SUMIF('SEG - SEPTIEMBRE'!H5:H54,"PAGADO",'SEG - SEPTIEMBRE'!F5:F54) -> 0 | C11: ='SEG - SEPTIEMBRE'!C58 -> 0 | D11: ='SEG - SEPTIEMBRE'!E58 -> 0 | E11: ='SEG - SEPTIEMBRE'!I58 -> 0
A12: OCTUBRE | B12: =SUMIF('SEG - OCTUBRE'!H5:H54,"PAGADO",'SEG - OCTUBRE'!F5:F54) -> 0 | C12: ='SEG - OCTUBRE'!C58 -> 0 | D12: ='SEG - OCTUBRE'!E58 -> 0 | E12: ='SEG - OCTUBRE'!I58 -> 0
A13: NOVIEMBRE | B13: =SUMIF('SEG - NOVIEMBRE'!H5:H54,"PAGADO",'SEG - NOVIEMBRE'!F5:F54) -> 0 | C13: ='SEG - NOVIEMBRE'!C58 -> 0 | D13: ='SEG - NOVIEMBRE'!E58 -> 0 | E13: ='SEG - NOVIEMBRE'!I58 -> 0
A14: DICIEMBRE | B14: =SUMIF('SEG - DICIEMBRE'!H5:H54,"PAGADO",'SEG - DICIEMBRE'!F5:F54) -> 0 | C14: ='SEG - DICIEMBRE'!C58 -> 0 | D14: ='SEG - DICIEMBRE'!E58 -> 0 | E14: ='SEG - DICIEMBRE'!I58 -> 0
A15: TOTAL AÑO | B15: =SUM(B3:B14) -> 25 | C15: =SUM(C3:C14) -> 1 | D15: =SUM(D3:D14) -> 0 | E15: =SUM(E3:E14) -> 2.5
A17: 💡 Esta hoja se calcula sola con lo que registras en las hojas SEG de cada mes. ¡Solo lectura!
